Workbook

Sheet PROYECTADA
R1: =R2*8 -> 216 | S1: Horas | Y1: FDM
R2: 27 | S2: Dias laborables
R3: 31 | S3: Dias | AF3: BONIFICACIÓN ENERO 2026
A4: MES DE ENERO 2026 | X4: SISTEMA MES DE ENERO 2026
A5: Nº | B5: NOMBRES | C5: SPP o SNP | D5: SUELDO BRUTO | H5: SUELDO BRUTO | I5: DSCTO. A.F.P.(Prima de Seguro | J5: SUELDO NETO | K5: BENEFICIOS SOCIALES PROYECTADOS | O5: APORTES DEL EMPLEADOR | S5: SUELDO NETO + BENF. SOCI. PROYEC. | T5: SUELDO BRUTO + BENF. SOCI. PROYEC. + APORT. EMPLE. | U5: JORNAL DIARIO | V5: COSTO HORA | X5: Nº | Y5: NOMBRES | Z5: DIFERENCIA O BONIFICACION | AA5: SUELDO NETO TOTAL | AB5: SUELDO BRUTO NEGRO | AC5: SUELDO POR DIA | AD5: SUELDO POR HORA | AF5: Diferencia por h. | AG5: Diferencia real
D6: REMUNERACIÓN BÁSICA | E6: BONIF. | F6: ASIGNACION FAMILIAR | G6: COMPEN. | K6: CTS | L6: GRATIFICACIONES | M6: ESSALUD GRATIFICACIONES | N6: BETA 30 % | O6: ESSALUD | P6: VIDA LEY | Q6: PENSION SCTR | R6: ESSALUD EPS | AI6: Diferencia real de personas en vacaciones
A7: 1 | B7: Apaza Tito Patricia | C7: PRO F | D7: =37.6666666666667*$R$3 -> 1167.6667 | E7: 125 | H7: =SUM(D7:G7) -> 1292.6667 | I7: =H7*$D$66 -> 168.82227 | J7: =H7-I7 -> 1123.8444 | K7: =((D7+E7+F7)*(9.72%)) -> 125.6472 | L7: =(D7+E7+F7)*(16.66%) -> 215.35827 | M7: =L7*6% -> 12.921496 | N7: =(1130*30%)/(30)*30 -> 339 | O7: =H7*6% -> 77.56 | P7: =((H7*(0.63%))*1.18) -> 9.609684 | Q7: =(H7*(0.57%))*1.18 -> 8.694476 | R7: =(H7*(0.55%))*1.18 -> 8.3894067 | S7: =J7+K7+L7+M7+N7 -> 1816.7714 | T7: =H7+K7+L7+M7+N7+O7+P7+Q7+R7 -> 2089.8472 | U7: =T7/$R$2 -> 77.401748 | V7: =+U7/8 -> 9.6752185 | X7: =A7 -> 1 | Y7: =B7 -> Apaza Tito Patricia | Z7: =AA7-S7 -> 708.22864 | AA7: =2400+125 -> 2525 | AB7: =T7+Z7 -> 2798.0758 | AC7: =AB7/$R$2 -> 103.63244 | AD7: =+AC7/8 -> 12.954055 | AF7: =Z7/$R$1 -> 3.2788363
A8: 2 | B8: Aquino Gómez Basilia Isabel | C8: PRO F | D8: =37.6666666666667*$R$3 -> 1167.6667 | H8: =SUM(D8:G8) -> 1167.6667 | I8: =H8*$D$66 -> 152.49727 | J8: =H8-I8 -> 1015.1694 | K8: =((D8+E8+F8)*(9.72%)) -> 113.4972 | L8: =(D8+E8+F8)*(16.66%) -> 194.53327 | M8: =L8*6% -> 11.671996 | N8: =(1130*30%)/(30)*30 -> 339 | O8: =H8*6% -> 70.06 | P8: =((H8*(0.63%))*1.18) -> 8.680434 | Q8: =(H8*(0.57%))*1.18 -> 7.853726 | R8: =(H8*(0.55%))*1.18 -> 7.5781567 | S8: =J8+K8+L8+M8+N8 -> 1673.8719 | T8: =H8+K8+L8+M8+N8+O8+P8+Q8+R8 -> 1920.5414 | U8: =T8/$R$2 -> 71.131165 | V8: =+U8/8 -> 8.8913956 | X8: =A8 -> 2 | Y8: =B8 -> Aquino Gómez Basilia Isabel | Z8: =AA8-S8 -> 326.12814 | AA8: =1775+100+125 -> 2000 | AB8: =T8+Z8 -> 2246.6696 | AC8: =AB8/$R$2 -> 83.209985 | AD8: =+AC8/8 -> 10.401248 | AF8: =Z8/$R$1 -> 1.5098525
A9: 3 | B9: Calla G Guillermina | C9: PRO F | D9: =37.6666666666667*$R$3 -> 1167.6667 | H9: =SUM(D9:G9) -> 1167.6667 | I9: =H9*$D$66 -> 152.49727 | J9: =H9-I9 -> 1015.1694 | K9: =((D9+E9+F9)*(9.72%)) -> 113.4972 | L9: =(D9+E9+F9)*(16.66%) -> 194.53327 | M9: =L9*6% -> 11.671996 | N9: =(1130*30%)/(30)*30 -> 339 | O9: =H9*6% -> 70.06 | P9: =((H9*(0.63%))*1.18) -> 8.680434 | Q9: =(H9*(0.57%))*1.18 -> 7.853726 | R9: =(H9*(0.55%))*1.18 -> 7.5781567 | S9: =J9+K9+L9+M9+N9 -> 1673.8719 | T9: =H9+K9+L9+M9+N9+O9+P9+Q9+R9 -> 1920.5414 | U9: =T9/$R$2 -> 71.131165 | V9: =+U9/8 -> 8.8913956 | X9: =A9 -> 3 | Y9: =B9 -> Calla G Guillermina | Z9: =AA9-S9 -> 326.12814 | AA9: =1775+100+125 -> 2000 | AB9: =T9+Z9 -> 2246.6696 | AC9: =AB9/$R$2 -> 83.209985 | AD9: =+AC9/8 -> 10.401248 | AF9: =Z9/$R$1 -> 1.5098525
A10: 4 | B10: Challco Laime, Gilberta | C10: HAB M | D10: =37.6666666666667*$R$3 -> 1167.6667 | H10: =SUM(D10:G10) -> 1167.6667 | I10: =H10*$E$68 -> 132.7637 | J10: =H10-I10 -> 1034.903 | K10: =((D10+E10+F10)*(9.72%)) -> 113.4972 | L10: =(D10+E10+F10)*(16.66%) -> 194.53327 | M10: =L10*6% -> 11.671996 | N10: =(1130*30%)/(30)*30 -> 339 | O10: =H10*6% -> 70.06 | P10: =((H10*(0.63%))*1.18) -> 8.680434 | Q10: =(H10*(0.57%))*1.18 -> 7.853726 | R10: =(H10*(0.55%))*1.18 -> 7.5781567 | S10: =J10+K10+L10+M10+N10 -> 1693.6054 | T10: =H10+K10+L10+M10+N10+O10+P10+Q10+R10 -> 1920.5414 | U10: =T10/$R$2 -> 71.131165 | V10: =+U10/8 -> 8.8913956 | X10: =A10 -> 4 | Y10: =B10 -> Challco Laime, Gilberta | Z10: =AA10-S10 -> 306.39457 | AA10: =1775+100+125 -> 2000 | AB10: =T10+Z10 -> 2226.936 | AC10: =AB10/$R$2 -> 82.479112 | AD10: =+AC10/8 -> 10.309889 | AF10: =Z10/$R$1 -> 1.4184934
A11: 5 | B11: Choquehuayta Huallpa, Estefania | C11: PRO M | D11: =37.6666666666667*$R$3 -> 1167.6667 | F11: 113 | H11: =SUM(D11:G11) -> 1280.6667 | I11: =H11*$E$70 -> 145.6118 | J11: =H11-I11 -> 1135.0549 | K11: =((D11+E11+F11)*(9.72%)) -> 124.4808 | L11: =(D11+E11+F11)*(16.66%) -> 213.35907 | M11: =L11*6% -> 12.801544 | N11: =(1130*30%)/(30)*30 -> 339 | O11: =H11*6% -> 76.84 | P11: =((H11*(0.63%))*1.18) -> 9.520476 | Q11: =(H11*(0.57%))*1.18 -> 8.613764 | R11: =(H11*(0.55%))*1.18 -> 8.3115267 | S11: =J11+K11+L11+M11+N11 -> 1824.6963 | T11: =H11+K11+L11+M11+N11+O11+P11+Q11+R11 -> 2073.5938 | U11: =T11/$R$2 -> 76.799772 | V11: =+U11/8 -> 9.5999715 | X11: =A11 -> 5 | Y11: =B11 -> Choquehuayta Huallpa, Estefania | Z11: =AA11-S11 -> 175.30372 | AA11: =1775+100+125 -> 2000 | AB11: =T11+Z11 -> 2248.8976 | AC11: =AB11/$R$2 -> 83.292502 | AD11: =+AC11/8 -> 10.411563 | AF11: =Z11/$R$1 -> 0.81159131
A12: 6 | B12: Idme Huaraccallo, Gladis | C12: SNP | D12: =37.6666666666667*$R$3 -> 1167.6667 | H12: =SUM(D12:G12) -> 1167.6667 | I12: =H12*$E$69 -> 151.79667 | J12: =H12-I12 -> 1015.87 | K12: =((D12+E12+F12)*(9.72%)) -> 113.4972 | L12: =(D12+E12+F12)*(16.66%) -> 194.53327 | M12: =L12*6% -> 11.671996 | N12: =(1130*30%)/(30)*30 -> 339 | O12: =H12*6% -> 70.06 | P12: =((H12*(0.63%))*1.18) -> 8.680434 | Q12: =(H12*(0.57%))*1.18 -> 7.853726 | R12: =(H12*(0.55%))*1.18 -> 7.5781567 | S12: =J12+K12+L12+M12+N12 -> 1674.5725 | T12: =H12+K12+L12+M12+N12+O12+P12+Q12+R12 -> 1920.5414 | U12: =T12/$R$2 -> 71.131165 | V12: =+U12/8 -> 8.8913956 | X12: =A12 -> 6 | Y12: =B12 -> Idme Huaraccallo, Gladis | Z12: =AA12-S12 -> 325.42754 | AA12: =1775+100+125 -> 2000 | AB12: =T12+Z12 -> 2245.969 | AC12: =AB12/$R$2 -> 83.184036 | AD12: =+AC12/8 -> 10.398005 | AF12: =Z12/$R$1 -> 1.506609
A13: 7 | B13: Jacha Gomez, Flavia | C13: INT F | D13: =37.6666666666667*$R$3 -> 1167.6667 | H13: =SUM(D13:G13) -> 1167.6667 | I13: =H13*$D$64 -> 150.86253 | J13: =H13-I13 -> 1016.8041 | K13: =((D13+E13+F13)*(9.72%)) -> 113.4972 | L13: =(D13+E13+F13)*(16.66%) -> 194.53327 | M13: =L13*6% -> 11.671996 | N13: =(1130*30%)/(30)*30 -> 339 | O13: =H13*6% -> 70.06 | P13: =((H13*(0.63%))*1.18) -> 8.680434 | Q13: =(H13*(0.57%))*1.18 -> 7.853726 | R13: =(H13*(0.55%))*1.18 -> 7.5781567 | S13: =J13+K13+L13+M13+N13 -> 1675.5066 | T13: =H13+K13+L13+M13+N13+O13+P13+Q13+R13 -> 1920.5414 | U13: =T13/$R$2 -> 71.131165 | V13: =+U13/8 -> 8.8913956 | X13: =A13 -> 7 | Y13: =B13 -> Jacha Gomez, Flavia | Z13: =AA13-S13 -> 474.4934 | AA13: =1925+100+125 -> 2150 | AB13: =T13+Z13 -> 2395.0349 | AC13: =AB13/$R$2 -> 88.704994 | AD13: =+AC13/8 -> 11.088124 | AF13: =Z13/$R$1 -> 2.1967287
A14: 8 | B14: Lerma Yanarico Elena | C14: PRO F | D14: =37.6666666666667*$R$3 -> 1167.6667 | F14: 113 | H14: =SUM(D14:G14) -> 1280.6667 | I14: =H14*$D$66 -> 167.25507 | J14: =H14-I14 -> 1113.4116 | K14: =((D14+E14+F14)*(9.72%)) -> 124.4808 | L14: =(D14+E14+F14)*(16.66%) -> 213.35907 | M14: =L14*6% -> 12.801544 | N14: =(1130*30%)/(30)*30 -> 339 | O14: =H14*6% -> 76.84 | P14: =((H14*(0.63%))*1.18) -> 9.520476 | Q14: =(H14*(0.57%))*1.18 -> 8.613764 | R14: =(H14*(0.55%))*1.18 -> 8.3115267 | S14: =J14+K14+L14+M14+N14 -> 1803.053 | T14: =H14+K14+L14+M14+N14+O14+P14+Q14+R14 -> 2073.5938 | U14: =T14/$R$2 -> 76.799772 | V14: =+U14/8 -> 9.5999715 | X14: =A14 -> 8 | Y14: =B14 -> Lerma Yanarico Elena | Z14: =AA14-S14 -> 196.94699 | AA14: =1775+100+125 -> 2000 | AB14: =T14+Z14 -> 2270.5408 | AC14: =AB14/$R$2 -> 84.094105 | AD14: =+AC14/8 -> 10.511763 | AF14: =Z14/$R$1 -> 0.91179162
A15: 9 | B15: Machaca Calcina, Benedicta | C15: INT M | D15: =37.6666666666667*$R$3 -> 1167.6667 | F15: 113 | H15: =SUM(D15:G15) -> 1280.6667 | I15: =H15*$E$71 -> 145.6118 | J15: =H15-I15 -> 1135.0549 | K15: =((D15+E15+F15)*(9.72%)) -> 124.4808 | L15: =(D15+E15+F15)*(16.66%) -> 213.35907 | M15: =L15*6% -> 12.801544 | N15: =(1130*30%)/(30)*30 -> 339 | O15: =H15*6% -> 76.84 | P15: =((H15*(0.63%))*1.18) -> 9.520476 | Q15: =(H15*(0.57%))*1.18 -> 8.613764 | R15: =(H15*(0.55%))*1.18 -> 8.3115267 | S15: =J15+K15+L15+M15+N15 -> 1824.6963 | T15: =H15+K15+L15+M15+N15+O15+P15+Q15+R15 -> 2073.5938 | U15: =T15/$R$2 -> 76.799772 | V15: =+U15/8 -> 9.5999715 | X15: =A15 -> 9 | Y15: =B15 -> Machaca Calcina, Benedicta | Z15: =AA15-S15 -> 175.30372 | AA15: =1775+100+125 -> 2000 | AB15: =T15+Z15 -> 2248.8976 | AC15: =AB15/$R$2 -> 83.292502 | AD15: =+AC15/8 -> 10.411563 | AF15: =Z15/$R$1 -> 0.81159131
A16: 10 | B16: Mamani Hancco, Elsa Teresa | C16: INT F | D16: =37.6666666666667*$R$3 -> 1167.6667 | F16: 113 | H16: =SUM(D16:G16) -> 1280.6667 | I16: =H16*$D$64 -> 165.46213 | J16: =H16-I16 -> 1115.2045 | K16: =((D16+E16+F16)*(9.72%)) -> 124.4808 | L16: =(D16+E16+F16)*(16.66%) -> 213.35907 | M16: =L16*6% -> 12.801544 | N16: =(1130*30%)/(30)*30 -> 339 | O16: =H16*6% -> 76.84 | P16: =((H16*(0.63%))*1.18) -> 9.520476 | Q16: =(H16*(0.57%))*1.18 -> 8.613764 | R16: =(H16*(0.55%))*1.18 -> 8.3115267 | S16: =J16+K16+L16+M16+N16 -> 1804.8459 | T16: =H16+K16+L16+M16+N16+O16+P16+Q16+R16 -> 2073.5938 | U16: =T16/$R$2 -> 76.799772 | V16: =+U16/8 -> 9.5999715 | X16: =A16 -> 10 | Y16: =B16 -> Mamani Hancco, Elsa Teresa | Z16: =AA16-S16 -> 195.15406 | AA16: =1775+100+125 -> 2000 | AB16: =T16+Z16 -> 2268.7479 | AC16: =AB16/$R$2 -> 84.0277 | AD16: =+AC16/8 -> 10.503463 | AF16: =Z16/$R$1 -> 0.903491
A17: 11 | B17: Mamani Itusaca de Perca Guzmila | C17: HAB M | D17: =37.6666666666667*$R$3 -> 1167.6667 | H17: =SUM(D17:G17) -> 1167.6667 | I17: =H17*$E$68 -> 132.7637 | J17: =H17-I17 -> 1034.903 | K17: =((D17+E17+F17)*(9.72%)) -> 113.4972 | L17: =(D17+E17+F17)*(16.66%) -> 194.53327 | M17: =L17*6% -> 11.671996 | N17: =(1130*30%)/(30)*30 -> 339 | O17: =H17*6% -> 70.06 | P17: =((H17*(0.63%))*1.18) -> 8.680434 | Q17: =(H17*(0.57%))*1.18 -> 7.853726 | R17: =(H17*(0.55%))*1.18 -> 7.5781567 | S17: =J17+K17+L17+M17+N17 -> 1693.6054 | T17: =H17+K17+L17+M17+N17+O17+P17+Q17+R17 -> 1920.5414 | U17: =T17/$R$2 -> 71.131165 | V17: =+U17/8 -> 8.8913956 | X17: =A17 -> 11 | Y17: =B17 -> Mamani Itusaca de Perca Guzmila | Z17: =AA17-S17 -> 306.39457 | AA17: =1775+100+125 -> 2000 | AB17: =T17+Z17 -> 2226.936 | AC17: =AB17/$R$2 -> 82.479112 | AD17: =+AC17/8 -> 10.309889 | AF17: =Z17/$R$1 -> 1.4184934
A18: 12 | B18: Mayta Coaquira Janet Venancia | C18: INT M | D18: =37.6666666666667*$R$3 -> 1167.6667 | H18: =SUM(D18:G18) -> 1167.6667 | I18: =H18*$E$71 -> 132.7637 | J18: =H18-I18 -> 1034.903 | K18: =((D18+E18+F18)*(9.72%)) -> 113.4972 | L18: =(D18+E18+F18)*(16.66%) -> 194.53327 | M18: =L18*6% -> 11.671996 | N18: =(1130*30%)/(30)*30 -> 339 | O18: =H18*6% -> 70.06 | P18: =((H18*(0.63%))*1.18) -> 8.680434 | Q18: =(H18*(0.57%))*1.18 -> 7.853726 | R18: =(H18*(0.55%))*1.18 -> 7.5781567 | S18: =J18+K18+L18+M18+N18 -> 1693.6054 | T18: =H18+K18+L18+M18+N18+O18+P18+Q18+R18 -> 1920.5414 | U18: =T18/$R$2 -> 71.131165 | V18: =+U18/8 -> 8.8913956 | X18: =A18 -> 12 | Y18: =B18 -> Mayta Coaquira Janet Venancia | Z18: =AA18-S18 -> 306.39457 | AA18: =1775+100+125 -> 2000 | AB18: =T18+Z18 -> 2226.936 | AC18: =AB18/$R$2 -> 82.479112 | AD18: =+AC18/8 -> 10.309889 | AF18: =Z18/$R$1 -> 1.4184934
A19: 13 | B19: Parari Laura Teresa Lucy | C19: PRO M | D19: =37.6666666666667*$R$3 -> 1167.6667 | H19: =SUM(D19:G19) -> 1167.6667 | I19: =H19*$E$70 -> 132.7637 | J19: =H19-I19 -> 1034.903 | K19: =((D19+E19+F19)*(9.72%)) -> 113.4972 | L19: =(D19+E19+F19)*(16.66%) -> 194.53327 | M19: =L19*6% -> 11.671996 | N19: =(1130*30%)/(30)*30 -> 339 | O19: =H19*6% -> 70.06 | P19: =((H19*(0.63%))*1.18) -> 8.680434 | Q19: =(H19*(0.57%))*1.18 -> 7.853726 | R19: =(H19*(0.55%))*1.18 -> 7.5781567 | S19: =J19+K19+L19+M19+N19 -> 1693.6054 | T19: =H19+K19+L19+M19+N19+O19+P19+Q19+R19 -> 1920.5414 | U19: =T19/$R$2 -> 71.131165 | V19: =+U19/8 -> 8.8913956 | X19: =A19 -> 13 | Y19: =B19 -> Parari Laura Teresa Lucy | Z19: =AA19-S19 -> 306.39457 | AA19: =1775+100+125 -> 2000 | AB19: =T19+Z19 -> 2226.936 | AC19: =AB19/$R$2 -> 82.479112 | AD19: =+AC19/8 -> 10.309889 | AF19: =Z19/$R$1 -> 1.4184934
A20: 14 | B20: Pelinco Machaca, Monica | C20: PRI M | D20: =37.6666666666667*$R$3 -> 1167.6667 | H20: =SUM(D20:G20) -> 1167.6667 | I20: =H20*$E$72 -> 132.7637 | J20: =H20-I20 -> 1034.903 | K20: =((D20+E20+F20)*(9.72%)) -> 113.4972 | L20: =(D20+E20+F20)*(16.66%) -> 194.53327 | M20: =L20*6% -> 11.671996 | N20: =(1130*30%)/(30)*30 -> 339 | O20: =H20*6% -> 70.06 | P20: =((H20*(0.63%))*1.18) -> 8.680434 | Q20: =(H20*(0.57%))*1.18 -> 7.853726 | R20: =(H20*(0.55%))*1.18 -> 7.5781567 | S20: =J20+K20+L20+M20+N20 -> 1693.6054 | T20: =H20+K20+L20+M20+N20+O20+P20+Q20+R20 -> 1920.5414 | U20: =T20/$R$2 -> 71.131165 | V20: =+U20/8 -> 8.8913956 | X20: =A20 -> 14 | Y20: =B20 -> Pelinco Machaca, Monica | Z20: =AA20-S20 -> 306.39457 | AA20: =1775+100+125 -> 2000 | AB20: =T20+Z20 -> 2226.936 | AC20: =AB20/$R$2 -> 82.479112 | AD20: =+AC20/8 -> 10.309889 | AF20: =Z20/$R$1 -> 1.4184934
A21: 15 | B21: Quispe Pacco Obita | C21: PRO F | D21: =37.6666666666667*$R$3 -> 1167.6667 | H21: =SUM(D21:G21) -> 1167.6667 | I21: =H21*$D$66 -> 152.49727 | J21: =H21-I21 -> 1015.1694 | K21: =((D21+E21+F21)*(9.72%)) -> 113.4972 | L21: =(D21+E21+F21)*(16.66%) -> 194.53327 | M21: =L21*6% -> 11.671996 | N21: =(1130*30%)/(30)*30 -> 339 | O21: =H21*6% -> 70.06 | P21: =((H21*(0.63%))*1.18) -> 8.680434 | Q21: =(H21*(0.57%))*1.18 -> 7.853726 | R21: =(H21*(0.55%))*1.18 -> 7.5781567 | S21: =J21+K21+L21+M21+N21 -> 1673.8719 | T21: =H21+K21+L21+M21+N21+O21+P21+Q21+R21 -> 1920.5414 | U21: =T21/$R$2 -> 71.131165 | V21: =+U21/8 -> 8.8913956 | X21: =A21 -> 15 | Y21: =B21 -> Quispe Pacco Obita | Z21: =AA21-S21 -> 326.12814 | AA21: =1775+100+125 -> 2000 | AB21: =T21+Z21 -> 2246.6696 | AC21: =AB21/$R$2 -> 83.209985 | AD21: =+AC21/8 -> 10.401248 | AF21: =Z21/$R$1 -> 1.5098525
A22: 16 | B22: Aragon Hancco Delia Jesusa | C22: INT M | D22: =37.6666666666667*$R$3 -> 1167.6667 | F22: 113 | G22: 103.58 | H22: =SUM(D22:G22) -> 1384.2467 | I22: =H22*$E$71 -> 157.38885 | J22: =H22-I22 -> 1226.8578 | K22: =((D22+E22+F22)*(9.72%)) -> 124.4808 | L22: =(D22+E22+F22)*(16.66%) -> 213.35907 | M22: =L22*6% -> 12.801544 | N22: =(1130*30%)/(30)*29 -> 327.7 | O22: =H22*6% -> 83.0548 | P22: =((H22*(0.63%))*1.18) -> 10.29049 | Q22: =(H22*(0.57%))*1.18 -> 9.3104431 | R22: =(H22*(0.55%))*1.18 -> 8.9837609 | S22: =J22+K22+L22+M22+N22 -> 1905.1992 | T22: =H22+K22+L22+M22+N22+O22+P22+Q22+R22 -> 2174.2276 | U22: =T22/$R$2 -> 80.526947 | V22: =+U22/8 -> 10.065868 | X22: =A22 -> 16 | Y22: =B22 -> Aragon Hancco Delia Jesusa | Z22: =AA22-S22 -> 242.80077 | AA22: =1923+100+125 -> 2148 | AB22: =T22+Z22 -> 2417.0283 | AC22: =AB22/$R$2 -> 89.519568 | AD22: =+AC22/8 -> 11.189946 | AF22: =Z22/$R$1 -> 1.1240776
A23: 17 | B23: Gonzales Aparicio Lisbeth | C23: INT M | D23: =37.6666666666667*$R$3 -> 1167.6667 | G23: 94.16 | H23: =SUM(D23:G23) -> 1261.8267 | I23: =H23*$E$71 -> 143.46969 | J23: =H23-I23 -> 1118.357 | K23: =((D23+E23+F23)*(9.72%)) -> 113.4972 | L23: =(D23+E23+F23)*(16.66%) -> 194.53327 | M23: =L23*6% -> 11.671996 | N23: =(1130*30%)/(30)*30 -> 339 | O23: =H23*6% -> 75.7096 | P23: =((H23*(0.63%))*1.18) -> 9.3804194 | Q23: =(H23*(0.57%))*1.18 -> 8.4870462 | R23: =(H23*(0.55%))*1.18 -> 8.1892551 | S23: =J23+K23+L23+M23+N23 -> 1777.0594 | T23: =H23+K23+L23+M23+N23+O23+P23+Q23+R23 -> 2022.2955 | U23: =T23/$R$2 -> 74.899831 | V23: =+U23/8 -> 9.3624789 | X23: =A23 -> 17 | Y23: =B23 -> Gonzales Aparicio Lisbeth | Z23: =AA23-S23 -> 370.94056 | AA23: =1923+100+125 -> 2148 | AB23: =T23+Z23 -> 2393.236 | AC23: =AB23/$R$2 -> 88.638371 | AD23: =+AC23/8 -> 11.079796 | AF23: =Z23/$R$1 -> 1.7173174
A24: 18 | B24: Sánchez Huanca María Luisa | C24: PRO M | D24: =37.6666666666667*$R$3 -> 1167.6667 | F24: 113 | G24: 103.58 | H24: =SUM(D24:G24) -> 1384.2467 | I24: =H24*$E$70 -> 157.38885 | J24: =H24-I24 -> 1226.8578 | K24: =((D24+E24+F24)*(9.72%)) -> 124.4808 | L24: =(D24+E24+F24)*(16.66%) -> 213.35907 | M24: =L24*6% -> 12.801544 | N24: =(1130*30%)/(30)*30 -> 339 | O24: =H24*6% -> 83.0548 | P24: =((H24*(0.63%))*1.18) -> 10.29049 | Q24: =(H24*(0.57%))*1.18 -> 9.3104431 | R24: =(H24*(0.55%))*1.18 -> 8.9837609 | S24: =J24+K24+L24+M24+N24 -> 1916.4992 | T24: =H24+K24+L24+M24+N24+O24+P24+Q24+R24 -> 2185.5276 | U24: =T24/$R$2 -> 80.945466 | V24: =+U24/8 -> 10.118183 | X24: =A24 -> 18 | Y24: =B24 -> Sánchez Huanca María Luisa | Z24: =AA24-S24 -> 231.50077 | AA24: =1923+100+125 -> 2148 | AB24: =T24+Z24 -> 2417.0283 | AC24: =AB24/$R$2 -> 89.519568 | AD24: =+AC24/8 -> 11.189946 | AF24: =Z24/$R$1 -> 1.0717628
A25: 19 | B25: Alvarez Chavez, Richard | C25: PRO F | D25: =37.6666666666667*$R$3 -> 1167.6667 | F25: 113 | H25: =SUM(D25:G25) -> 1280.6667 | I25: =H25*$D$66 -> 167.25507 | J25: =H25-I25 -> 1113.4116 | K25: =((D25+E25+F25)*(9.72%)) -> 124.4808 | L25: =(D25+E25+F25)*(16.66%) -> 213.35907 | M25: =L25*6% -> 12.801544 | N25: =(1130*30%)/(30)*30 -> 339 | O25: =H25*6% -> 76.84 | P25: =((H25*(0.63%))*1.18) -> 9.520476 | Q25: =(H25*(0.57%))*1.18 -> 8.613764 | R25: =(H25*(0.55%))*1.18 -> 8.3115267 | S25: =J25+K25+L25+M25+N25 -> 1803.053 | T25: =H25+K25+L25+M25+N25+O25+P25+Q25+R25 -> 2073.5938 | U25: =T25/$R$2 -> 76.799772 | V25: =+U25/8 -> 9.5999715 | X25: =A25 -> 19 | Y25: =B25 -> Alvarez Chavez, Richard | Z25: =AA25-S25 -> 386.94699 | AA25: =1925+140+125 -> 2190 | AB25: =T25+Z25 -> 2460.5408 | AC25: =AB25/$R$2 -> 91.131142 | AD25: =+AC25/8 -> 11.391393 | AF25: =Z25/$R$1 -> 1.7914212
A26: 20 | B26: Aparicio Ch Claver | C26: PRO F | D26: =37.6666666666667*$R$3 -> 1167.6667 | F26: 113 | H26: =SUM(D26:G26) -> 1280.6667 | I26: =H26*$D$66 -> 167.25507 | J26: =H26-I26 -> 1113.4116 | K26: =((D26+E26+F26)*(9.72%)) -> 124.4808 | L26: =(D26+E26+F26)*(16.66%) -> 213.35907 | M26: =L26*6% -> 12.801544 | N26: =(1130*30%)/(30)*30 -> 339 | O26: =H26*6% -> 76.84 | P26: =((H26*(0.63%))*1.18) -> 9.520476 | Q26: =(H26*(0.57%))*1.18 -> 8.613764 | R26: =(H26*(0.55%))*1.18 -> 8.3115267 | S26: =J26+K26+L26+M26+N26 -> 1803.053 | T26: =H26+K26+L26+M26+N26+O26+P26+Q26+R26 -> 2073.5938 | U26: =T26/$R$2 -> 76.799772 | V26: =+U26/8 -> 9.5999715 | X26: =A26 -> 20 | Y26: =B26 -> Aparicio Ch Claver | Z26: =AA26-S26 -> 386.94699 | AA26: =1925+140+125 -> 2190 | AB26: =T26+Z26 -> 2460.5408 | AC26: =AB26/$R$2 -> 91.131142 | AD26: =+AC26/8 -> 11.391393 | AF26: =Z26/$R$1 -> 1.7914212
A27: 21 | B27: Aquino Gomez Carmelo | C27: PRO F | D27: =37.6666666666667*$R$3 -> 1167.6667 | F27: 113 | H27: =SUM(D27:G27) -> 1280.6667 | I27: =H27*$D$66 -> 167.25507 | J27: =H27-I27 -> 1113.4116 | K27: =((D27+E27+F27)*(9.72%)) -> 124.4808 | L27: =(D27+E27+F27)*(16.66%) -> 213.35907 | M27: =L27*6% -> 12.801544 | N27: =(1130*30%)/(30)*30 -> 339 | O27: =H27*6% -> 76.84 | P27: =((H27*(0.63%))*1.18) -> 9.520476 | Q27: =(H27*(0.57%))*1.18 -> 8.613764 | R27: =(H27*(0.55%))*1.18 -> 8.3115267 | S27: =J27+K27+L27+M27+N27 -> 1803.053 | T27: =H27+K27+L27+M27+N27+O27+P27+Q27+R27 -> 2073.5938 | U27: =T27/$R$2 -> 76.799772 | V27: =+U27/8 -> 9.5999715 | X27: =A27 -> 21 | Y27: =B27 -> Aquino Gomez Carmelo | Z27: =AA27-S27 -> 246.94699 | AA27: =1825+100+125 -> 2050 | AB27: =T27+Z27 -> 2320.5408 | AC27: =AB27/$R$2 -> 85.945957 | AD27: =+AC27/8 -> 10.743245 | AF27: =Z27/$R$1 -> 1.1432731
A28: 22 | B28: Ayamamani Chura Elver Emilio | C28: PRO F | D28: =37.6666666666667*$R$3 -> 1167.6667 | E28: 27.77 | F28: 113 | H28: =SUM(D28:G28) -> 1308.4367 | I28: =H28*$D$66 -> 170.88183 | J28: =H28-I28 -> 1137.5548 | K28: =((D28+E28+F28)*(9.72%)) -> 127.18004 | L28: =(D28+E28+F28)*(16.66%) -> 217.98555 | M28: =L28*6% -> 13.079133 | N28: =(1130*30%)/(30)*30 -> 339 | O28: =H28*6% -> 78.5062 | P28: =((H28*(0.63%))*1.18) -> 9.7269182 | Q28: =(H28*(0.57%))*1.18 -> 8.800545 | R28: =(H28*(0.55%))*1.18 -> 8.491754 | S28: =J28+K28+L28+M28+N28 -> 1834.7996 | T28: =H28+K28+L28+M28+N28+O28+P28+Q28+R28 -> 2111.2068 | U28: =T28/$R$2 -> 78.192845 | V28: =+U28/8 -> 9.7741056 | X28: =A28 -> 22 | Y28: =B28 -> Ayamamani Chura Elver Emilio | Z28: =AA28-S28 -> 690.20044 | AA28: =2300+100+125 -> 2525 | AB28: =T28+Z28 -> 2801.4072 | AC28: =AB28/$R$2 -> 103.75582 | AD28: =+AC28/8 -> 12.969478 | AF28: =Z28/$R$1 -> 3.1953724
A29: 23 | B29: Cañari Pucho, Guillermo | C29: INT F | D29: =37.6666666666667*$R$3 -> 1167.6667 | H29: =SUM(D29:G29) -> 1167.6667 | I29: =H29*$D$64 -> 150.86253 | J29: =H29-I29 -> 1016.8041 | K29: =((D29+E29+F29)*(9.72%)) -> 113.4972 | L29: =(D29+E29+F29)*(16.66%) -> 194.53327 | M29: =L29*6% -> 11.671996 | N29: =(1130*30%)/(30)*30 -> 339 | O29: =H29*6% -> 70.06 | P29: =((H29*(0.63%))*1.18) -> 8.680434 | Q29: =(H29*(0.57%))*1.18 -> 7.853726 | R29: =(H29*(0.55%))*1.18 -> 7.5781567 | S29: =J29+K29+L29+M29+N29 -> 1675.5066 | T29: =H29+K29+L29+M29+N29+O29+P29+Q29+R29 -> 1920.5414 | U29: =T29/$R$2 -> 71.131165 | V29: =+U29/8 -> 8.8913956 | X29: =A29 -> 23 | Y29: =B29 -> Cañari Pucho, Guillermo | Z29: =AA29-S29 -> 324.4934 | AA29: =1775+100+125 -> 2000 | AB29: =T29+Z29 -> 2245.0349 | AC29: =AB29/$R$2 -> 83.149439 | AD29: =+AC29/8 -> 10.39368 | AF29: =Z29/$R$1 -> 1.5022843
A30: 24 | B30: Ccanchi Neira, Juan Lorenzo | C30: PRO F | D30: =37.6666666666667*$R$3 -> 1167.6667 | H30: =SUM(D30:G30) -> 1167.6667 | I30: =H30*$D$66 -> 152.49727 | J30: =H30-I30 -> 1015.1694 | K30: =((D30+E30+F30)*(9.72%)) -> 113.4972 | L30: =(D30+E30+F30)*(16.66%) -> 194.53327 | M30: =L30*6% -> 11.671996 | N30: =(1130*30%)/(30)*30 -> 339 | O30: =H30*6% -> 70.06 | P30: =((H30*(0.63%))*1.18) -> 8.680434 | Q30: =(H30*(0.57%))*1.18 -> 7.853726 | R30: =(H30*(0.55%))*1.18 -> 7.5781567 | S30: =J30+K30+L30+M30+N30 -> 1673.8719 | T30: =H30+K30+L30+M30+N30+O30+P30+Q30+R30 -> 1920.5414 | U30: =T30/$R$2 -> 71.131165 | V30: =+U30/8 -> 8.8913956 | X30: =A30 -> 24 | Y30: =B30 -> Ccanchi Neira, Juan Lorenzo | Z30: =AA30-S30 -> 326.12814 | AA30: =1775+100+125 -> 2000 | AB30: =T30+Z30 -> 2246.6696 | AC30: =AB30/$R$2 -> 83.209985 | AD30: =+AC30/8 -> 10.401248 | AF30: =Z30/$R$1 -> 1.5098525
A31: 25 | B31: Gamarra Chambi, Ernesto | C31: SNP | D31: =37.6666666666667*$R$3 -> 1167.6667 | H31: =SUM(D31:G31) -> 1167.6667 | I31: =H31*$E$69 -> 151.79667 | J31: =H31-I31 -> 1015.87 | K31: =((D31+E31+F31)*(9.72%)) -> 113.4972 | L31: =(D31+E31+F31)*(16.66%) -> 194.53327 | M31: =L31*6% -> 11.671996 | N31: =(1130*30%)/(30)*30 -> 339 | O31: =H31*6% -> 70.06 | P31: =((H31*(0.63%))*1.18) -> 8.680434 | Q31: =(H31*(0.57%))*1.18 -> 7.853726 | R31: =(H31*(0.55%))*1.18 -> 7.5781567 | S31: =J31+K31+L31+M31+N31 -> 1674.5725 | T31: =H31+K31+L31+M31+N31+O31+P31+Q31+R31 -> 1920.5414 | U31: =T31/$R$2 -> 71.131165 | V31: =+U31/8 -> 8.8913956 | X31: =A31 -> 25 | Y31: =B31 -> Gamarra Chambi, Ernesto | Z31: =AA31-S31 -> 325.42754 | AA31: =1775+100+125 -> 2000 | AB31: =T31+Z31 -> 2245.969 | AC31: =AB31/$R$2 -> 83.184036 | AD31: =+AC31/8 -> 10.398005 | AF31: =Z31/$R$1 -> 1.506609
A32: 26 | B32: Huaynacho Otazu, Donar | C32: PRO M | D32: =37.6666666666667*$R$3 -> 1167.6667 | F32: 113 | H32: =SUM(D32:G32) -> 1280.6667 | I32: =H32*$E$70 -> 145.6118 | J32: =H32-I32 -> 1135.0549 | K32: =((D32+E32+F32)*(9.72%)) -> 124.4808 | L32: =(D32+E32+F32)*(16.66%) -> 213.35907 | M32: =L32*6% -> 12.801544 | N32: =(1130*30%)/(30)*30 -> 339 | O32: =H32*6% -> 76.84 | P32: =((H32*(0.63%))*1.18) -> 9.520476 | Q32: =(H32*(0.57%))*1.18 -> 8.613764 | R32: =(H32*(0.55%))*1.18 -> 8.3115267 | S32: =J32+K32+L32+M32+N32 -> 1824.6963 | T32: =H32+K32+L32+M32+N32+O32+P32+Q32+R32 -> 2073.5938 | U32: =T32/$R$2 -> 76.799772 | V32: =+U32/8 -> 9.5999715 | X32: =A32 -> 26 | Y32: =B32 -> Huaynacho Otazu, Donar | Z32: =AA32-S32 -> 225.30372 | AA32: =1825+100+125 -> 2050 | AB32: =T32+Z32 -> 2298.8976 | AC32: =AB32/$R$2 -> 85.144354 | AD32: =+AC32/8 -> 10.643044 | AF32: =Z32/$R$1 -> 1.0430728
A33: 27 | B33: Huaynapata Itusaca Yoni Angel | C33: PRI M | D33: =37.6666666666667*$R$3 -> 1167.6667 | F33: 113 | H33: =SUM(D33:G33) -> 1280.6667 | I33: =H33*$E$72 -> 145.6118 | J33: =H33-I33 -> 1135.0549 | K33: =((D33+E33+F33)*(9.72%)) -> 124.4808 | L33: =(D33+E33+F33)*(16.66%) -> 213.35907 | M33: =L33*6% -> 12.801544 | N33: =(1130*30%)/(30)*30 -> 339 | O33: =H33*6% -> 76.84 | P33: =((H33*(0.63%))*1.18) -> 9.520476 | Q33: =(H33*(0.57%))*1.18 -> 8.613764 | R33: =(H33*(0.55%))*1.18 -> 8.3115267 | S33: =J33+K33+L33+M33+N33 -> 1824.6963 | T33: =H33+K33+L33+M33+N33+O33+P33+Q33+R33 -> 2073.5938 | U33: =T33/$R$2 -> 76.799772 | V33: =+U33/8 -> 9.5999715 | X33: =A33 -> 27 | Y33: =B33 -> Huaynapata Itusaca Yoni Angel | Z33: =AA33-S33 -> 225.30372 | AA33: =1925+125 -> 2050 | AB33: =T33+Z33 -> 2298.8976 | AC33: =AB33/$R$2 -> 85.144354 | AD33: =+AC33/8 -> 10.643044 | AF33: =Z33/$R$1 -> 1.0430728
A34: 28 | B34: Idme Huaraccallo, Agustin | C34: PRO F | D34: =37.6666666666667*$R$3 -> 1167.6667 | H34: =SUM(D34:G34) -> 1167.6667 | I34: =H34*$D$66 -> 152.49727 | J34: =H34-I34 -> 1015.1694 | K34: =((D34+E34+F34)*(9.72%)) -> 113.4972 | L34: =(D34+E34+F34)*(16.66%) -> 194.53327 | M34: =L34*6% -> 11.671996 | N34: =(1130*30%)/(30)*30 -> 339 | O34: =H34*6% -> 70.06 | P34: =((H34*(0.63%))*1.18) -> 8.680434 | Q34: =(H34*(0.57%))*1.18 -> 7.853726 | R34: =(H34*(0.55%))*1.18 -> 7.5781567 | S34: =J34+K34+L34+M34+N34 -> 1673.8719 | T34: =H34+K34+L34+M34+N34+O34+P34+Q34+R34 -> 1920.5414 | U34: =T34/$R$2 -> 71.131165 | V34: =+U34/8 -> 8.8913956 | X34: =A34 -> 28 | Y34: =B34 -> Idme Huaraccallo, Agustin | Z34: =AA34-S34 -> 376.12814 | AA34: =1825+100+125 -> 2050 | AB34: =T34+Z34 -> 2296.6696 | AC34: =AB34/$R$2 -> 85.061836 | AD34: =+AC34/8 -> 10.63273 | AF34: =Z34/$R$1 -> 1.741334
A35: 29 | B35: Lope Choquehuanca, Cirilo | C35: PROF | D35: =37.6666666666667*$R$3 -> 1167.6667 | H35: =SUM(D35:G35) -> 1167.6667 | I35: 0 | J35: =H35-I35 -> 1167.6667 | K35: =((D35+E35+F35)*(9.72%)) -> 113.4972 | L35: =(D35+E35+F35)*(16.66%) -> 194.53327 | M35: =L35*6% -> 11.671996 | N35: =(1130*30%)/(30)*30 -> 339 | O35: =H35*6% -> 70.06 | P35: =((H35*(0.63%))*1.18) -> 8.680434 | Q35: =(H35*(0.57%))*1.18 -> 7.853726 | R35: =(H35*(0.55%))*1.18 -> 7.5781567 | S35: =J35+K35+L35+M35+N35 -> 1826.3691 | T35: =H35+K35+L35+M35+N35+O35+P35+Q35+R35 -> 1920.5414 | U35: =T35/$R$2 -> 71.131165 | V35: =+U35/8 -> 8.8913956 | X35: =A35 -> 29 | Y35: =B35 -> Lope Choquehuanca, Cirilo | Z35: =AA35-S35 -> 884.63087 | AA35: =2361+125+100+125 -> 2711 | AB35: =T35+Z35 -> 2805.1723 | AC35: =AB35/$R$2 -> 103.89527 | AD35: =+AC35/8 -> 12.986909 | AF35: =Z35/$R$1 -> 4.0955133
A36: 30 | B36: Lope Choquehuanca, Luis | C36: SNP | D36: =37.6666666666667*$R$3 -> 1167.6667 | H36: =SUM(D36:G36) -> 1167.6667 | I36: 0 | J36: =H36-I36 -> 1167.6667 | K36: =((D36+E36+F36)*(9.72%)) -> 113.4972 | L36: =(D36+E36+F36)*(16.66%) -> 194.53327 | M36: =L36*6% -> 11.671996 | N36: =(1130*30%)/(30)*30 -> 339 | O36: =H36*6% -> 70.06 | P36: =((H36*(0.63%))*1.18) -> 8.680434 | Q36: =(H36*(0.57%))*1.18 -> 7.853726 | R36: =(H36*(0.55%))*1.18 -> 7.5781567 | S36: =J36+K36+L36+M36+N36 -> 1826.3691 | T36: =H36+K36+L36+M36+N36+O36+P36+Q36+R36 -> 1920.5414 | U36: =T36/$R$2 -> 71.131165 | V36: =+U36/8 -> 8.8913956 | X36: =A36 -> 30 | Y36: =B36 -> Lope Choquehuanca, Luis | Z36: =AA36-S36 -> 573.63087 | AA36: =1900+125+100+125+150 -> 2400 | AB36: =T36+Z36 -> 2494.1723 | AC36: =AB36/$R$2 -> 92.376752 | AD36: =+AC36/8 -> 11.547094 | AF36: =Z36/$R$1 -> 2.6556985
A37: 31 | B37: Lopez Mamani, Nestor | C37: SNP | D37: =37.6666666666667*$R$3 -> 1167.6667 | F37: 113 | H37: =SUM(D37:G37) -> 1280.6667 | I37: =H37*$E$69 -> 166.48667 | J37: =H37-I37 -> 1114.18 | K37: =((D37+E37+F37)*(9.72%)) -> 124.4808 | L37: =(D37+E37+F37)*(16.66%) -> 213.35907 | M37: =L37*6% -> 12.801544 | N37: =(1130*30%)/(30)*30 -> 339 | O37: =H37*6% -> 76.84 | P37: =((H37*(0.63%))*1.18) -> 9.520476 | Q37: =(H37*(0.57%))*1.18 -> 8.613764 | R37: =(H37*(0.55%))*1.18 -> 8.3115267 | S37: =J37+K37+L37+M37+N37 -> 1803.8214 | T37: =H37+K37+L37+M37+N37+O37+P37+Q37+R37 -> 2073.5938 | U37: =T37/$R$2 -> 76.799772 | V37: =+U37/8 -> 9.5999715 | X37: =A37 -> 31 | Y37: =B37 -> Lopez Mamani, Nestor | Z37: =AA37-S37 -> 386.17859 | AA37: =1925+140+125 -> 2190 | AB37: =T37+Z37 -> 2459.7724 | AC37: =AB37/$R$2 -> 91.102683 | AD37: =+AC37/8 -> 11.387835 | AF37: =Z37/$R$1 -> 1.7878638
A38: 32 | B38: Mamani Anconaira, Santo Domingo | C38: SNP | D38: =37.6666666666667*$R$3 -> 1167.6667 | F38: 113 | H38: =SUM(D38:G38) -> 1280.6667 | I38: =H38*$E$69 -> 166.48667 | J38: =H38-I38 -> 1114.18 | K38: =((D38+E38+F38)*(9.72%)) -> 124.4808 | L38: =(D38+E38+F38)*(16.66%) -> 213.35907 | M38: =L38*6% -> 12.801544 | N38: =(1130*30%)/(30)*30 -> 339 | O38: =H38*6% -> 76.84 | P38: =((H38*(0.63%))*1.18) -> 9.520476 | Q38: =(H38*(0.57%))*1.18 -> 8.613764 | R38: =(H38*(0.55%))*1.18 -> 8.3115267 | S38: =J38+K38+L38+M38+N38 -> 1803.8214 | T38: =H38+K38+L38+M38+N38+O38+P38+Q38+R38 -> 2073.5938 | U38: =T38/$R$2 -> 76.799772 | V38: =+U38/8 -> 9.5999715 | X38: =A38 -> 32 | Y38: =B38 -> Mamani Anconaira, Santo Domingo | Z38: =AA38-S38 -> 196.17859 | AA38: =1775+100+125 -> 2000 | AB38: =T38+Z38 -> 2269.7724 | AC38: =AB38/$R$2 -> 84.065646 | AD38: =+AC38/8 -> 10.508206 | AF38: =Z38/$R$1 -> 0.90823421
A39: 33 | B39: Mamani Idme, Vicente | C39: PRO F | D39: =37.6666666666667*$R$3 -> 1167.6667 | E39: 106.8999 | F39: 113 | H39: =SUM(D39:G39) -> 1387.5666 | I39: =H39*$D$66 -> 181.21619 | J39: =H39-I39 -> 1206.3504 | K39: =((D39+E39+F39)*(9.72%)) -> 134.87147 | L39: =(D39+E39+F39)*(16.66%) -> 231.16859 | M39: =L39*6% -> 13.870115 | N39: =(1130*30%)/(30)*30 -> 339 | O39: =H39*6% -> 83.253994 | P39: =((H39*(0.63%))*1.18) -> 10.31517 | Q39: =(H39*(0.57%))*1.18 -> 9.3327727 | R39: =(H39*(0.55%))*1.18 -> 9.005307 | S39: =J39+K39+L39+M39+N39 -> 1925.2605 | T39: =H39+K39+L39+M39+N39+O39+P39+Q39+R39 -> 2218.384 | U39: =T39/$R$2 -> 82.16237 | V39: =+U39/8 -> 10.270296 | X39: =A39 -> 33 | Y39: =B39 -> Mamani Idme, Vicente | Z39: =AA39-S39 -> 1924.7395 | AA39: =3625+100+125 -> 3850 | AB39: =T39+Z39 -> 4143.1234 | AC39: =AB39/$R$2 -> 153.44902 | AD39: =+AC39/8 -> 19.181127 | AF39: =Z39/$R$1 -> 8.9108308
A40: 34 | B40: Mamani Mamani, Alejandro | C40: PRO M | D40: =37.6666666666667*$R$3 -> 1167.6667 | H40: =SUM(D40:G40) -> 1167.6667 | I40: =H40*$E$70 -> 132.7637 | J40: =H40-I40 -> 1034.903 | K40: =((D40+E40+F40)*(9.72%)) -> 113.4972 | L40: =(D40+E40+F40)*(16.66%) -> 194.53327 | M40: =L40*6% -> 11.671996 | N40: =(1130*30%)/(30)*30 -> 339 | O40: =H40*6% -> 70.06 | P40: =((H40*(0.63%))*1.18) -> 8.680434 | Q40: =(H40*(0.57%))*1.18 -> 7.853726 | R40: =(H40*(0.55%))*1.18 -> 7.5781567 | S40: =J40+K40+L40+M40+N40 -> 1693.6054 | T40: =H40+K40+L40+M40+N40+O40+P40+Q40+R40 -> 1920.5414 | U40: =T40/$R$2 -> 71.131165 | V40: =+U40/8 -> 8.8913956 | X40: =A40 -> 34 | Y40: =B40 -> Mamani Mamani, Alejandro | Z40: =AA40-S40 -> 596.39457 | AA40: =2025+140+125 -> 2290 | AB40: =T40+Z40 -> 2516.936 | AC40: =AB40/$R$2 -> 93.219852 | AD40: =+AC40/8 -> 11.652482 | AF40: =Z40/$R$1 -> 2.761086
A41: 35 | B41: Palaco Retamozo Alberto Gilberto | C41: PRO F | D41: =37.6666666666667*$R$3 -> 1167.6667 | F41: 113 | H41: =SUM(D41:G41) -> 1280.6667 | I41: =H41*$D$66 -> 167.25507 | J41: =H41-I41 -> 1113.4116 | K41: =((D41+E41+F41)*(9.72%)) -> 124.4808 | L41: =(D41+E41+F41)*(16.66%) -> 213.35907 | M41: =L41*6% -> 12.801544 | N41: =(1130*30%)/(30)*30 -> 339 | O41: =H41*6% -> 76.84 | P41: =((H41*(0.63%))*1.18) -> 9.520476 | Q41: =(H41*(0.57%))*1.18 -> 8.613764 | R41: =(H41*(0.55%))*1.18 -> 8.3115267 | S41: =J41+K41+L41+M41+N41 -> 1803.053 | T41: =H41+K41+L41+M41+N41+O41+P41+Q41+R41 -> 2073.5938 | U41: =T41/$R$2 -> 76.799772 | V41: =+U41/8 -> 9.5999715 | X41: =A41 -> 35 | Y41: =B41 -> Palaco Retamozo Alberto Gilberto | Z41: =AA41-S41 -> 386.94699 | AA41: =1925+140+125 -> 2190 | AB41: =T41+Z41 -> 2460.5408 | AC41: =AB41/$R$2 -> 91.131142 | AD41: =+AC41/8 -> 11.391393 | AF41: =Z41/$R$1 -> 1.7914212
A42: 36 | B42: Perca Mamani Julio Alberto | C42: INT M | D42: =37.6666666666667*$R$3 -> 1167.6667 | H42: =SUM(D42:G42) -> 1167.6667 | I42: =H42*$E$71 -> 132.7637 | J42: =H42-I42 -> 1034.903 | K42: =((D42+E42+F42)*(9.72%)) -> 113.4972 | L42: =(D42+E42+F42)*(16.66%) -> 194.53327 | M42: =L42*6% -> 11.671996 | N42: =(1130*30%)/(30)*30 -> 339 | O42: =H42*6% -> 70.06 | P42: =((H42*(0.63%))*1.18) -> 8.680434 | Q42: =(H42*(0.57%))*1.18 -> 7.853726 | R42: =(H42*(0.55%))*1.18 -> 7.5781567 | S42: =J42+K42+L42+M42+N42 -> 1693.6054 | T42: =H42+K42+L42+M42+N42+O42+P42+Q42+R42 -> 1920.5414 | U42: =T42/$R$2 -> 71.131165 | V42: =+U42/8 -> 8.8913956 | X42: =A42 -> 36 | Y42: =B42 -> Perca Mamani Julio Alberto | Z42: =AA42-S42 -> 496.39457 | AA42: =1925+140+125 -> 2190 | AB42: =T42+Z42 -> 2416.936 | AC42: =AB42/$R$2 -> 89.516149 | AD42: =+AC42/8 -> 11.189519 | AF42: =Z42/$R$1 -> 2.298123
A43: 37 | B43: Quispe Belizario Alvaro | C43: PRI M | D43: =37.6666666666667*$R$3 -> 1167.6667 | H43: =SUM(D43:G43) -> 1167.6667 | I43: =H43*$E$72 -> 132.7637 | J43: =H43-I43 -> 1034.903 | K43: =((D43+E43+F43)*(9.72%)) -> 113.4972 | L43: =(D43+E43+F43)*(16.66%) -> 194.53327 | M43: =L43*6% -> 11.671996 | N43: =(1130*30%)/(30)*30 -> 339 | O43: =H43*6% -> 70.06 | P43: =((H43*(0.63%))*1.18) -> 8.680434 | Q43: =(H43*(0.57%))*1.18 -> 7.853726 | R43: =(H43*(0.55%))*1.18 -> 7.5781567 | S43: =J43+K43+L43+M43+N43 -> 1693.6054 | T43: =H43+K43+L43+M43+N43+O43+P43+Q43+R43 -> 1920.5414 | U43: =T43/$R$2 -> 71.131165 | V43: =+U43/8 -> 8.8913956 | X43: =A43 -> 37 | Y43: =B43 -> Quispe Belizario Alvaro | Z43: =AA43-S43 -> 496.39457 | AA43: =1925+140+125 -> 2190 | AB43: =T43+Z43 -> 2416.936 | AC43: =AB43/$R$2 -> 89.516149 | AD43: =+AC43/8 -> 11.189519 | AF43: =Z43/$R$1 -> 2.298123
A44: 38 | B44: Quispe Quispe Luis | C44: PRO F | D44: =37.6666666666667*$R$3 -> 1167.6667 | H44: =SUM(D44:G44) -> 1167.6667 | I44: =H44*$D$66 -> 152.49727 | J44: =H44-I44 -> 1015.1694 | K44: =((D44+E44+F44)*(9.72%)) -> 113.4972 | L44: =(D44+E44+F44)*(16.66%) -> 194.53327 | M44: =L44*6% -> 11.671996 | N44: =(1130*30%)/(30)*30 -> 339 | O44: =H44*6% -> 70.06 | P44: =((H44*(0.63%))*1.18) -> 8.680434 | Q44: =(H44*(0.57%))*1.18 -> 7.853726 | R44: =(H44*(0.55%))*1.18 -> 7.5781567 | S44: =J44+K44+L44+M44+N44 -> 1673.8719 | T44: =H44+K44+L44+M44+N44+O44+P44+Q44+R44 -> 1920.5414 | U44: =T44/$R$2 -> 71.131165 | V44: =+U44/8 -> 8.8913956 | X44: =A44 -> 38 | Y44: =B44 -> Quispe Quispe Luis | Z44: =AA44-S44 -> 326.12814 | AA44: =1775+100+125 -> 2000 | AB44: =T44+Z44 -> 2246.6696 | AC44: =AB44/$R$2 -> 83.209985 | AD44: =+AC44/8 -> 10.401248 | AF44: =Z44/$R$1 -> 1.5098525
A45: 39 | B45: Reynoso Gamero Rufino | C45: PRO F | D45: =37.6666666666667*$R$3 -> 1167.6667 | H45: =SUM(D45:G45) -> 1167.6667 | I45: =H45*D73 -> 136.50023 | J45: =H45-I45 -> 1031.1664 | K45: =((D45+E45+F45)*(9.72%)) -> 113.4972 | L45: =(D45+E45+F45)*(16.66%) -> 194.53327 | M45: =L45*6% -> 11.671996 | N45: =(1130*30%)/(30)*30 -> 339 | O45: =H45*6% -> 70.06 | P45: =((H45*(0.63%))*1.18) -> 8.680434 | Q45: =(H45*(0.57%))*1.18 -> 7.853726 | R45: =(H45*(0.55%))*1.18 -> 7.5781567 | S45: =J45+K45+L45+M45+N45 -> 1689.8689 | T45: =H45+K45+L45+M45+N45+O45+P45+Q45+R45 -> 1920.5414 | U45: =T45/$R$2 -> 71.131165 | V45: =+U45/8 -> 8.8913956 | X45: =A45 -> 39 | Y45: =B45 -> Reynoso Gamero Rufino | Z45: =AA45-S45 -> 310.1311 | AA45: =1775+100+125 -> 2000 | AB45: =T45+Z45 -> 2230.6726 | AC45: =AB45/$R$2 -> 82.617502 | AD45: =+AC45/8 -> 10.327188 | AF45: =Z45/$R$1 -> 1.4357921
A46: 40 | B46: Rivera Ramos Elmer Delis | C46: INT F | D46: =37.6666666666667*$R$3 -> 1167.6667 | F46: 113 | H46: =SUM(D46:G46) -> 1280.6667 | I46: =H46*$D$64 -> 165.46213 | J46: =H46-I46 -> 1115.2045 | K46: =((D46+E46+F46)*(9.72%)) -> 124.4808 | L46: =(D46+E46+F46)*(16.66%) -> 213.35907 | M46: =L46*6% -> 12.801544 | N46: =(1130*30%)/(30)*30 -> 339 | O46: =H46*6% -> 76.84 | P46: =((H46*(0.63%))*1.18) -> 9.520476 | Q46: =(H46*(0.57%))*1.18 -> 8.613764 | R46: =(H46*(0.55%))*1.18 -> 8.3115267 | S46: =J46+K46+L46+M46+N46 -> 1804.8459 | T46: =H46+K46+L46+M46+N46+O46+P46+Q46+R46 -> 2073.5938 | U46: =T46/$R$2 -> 76.799772 | V46: =+U46/8 -> 9.5999715 | X46: =A46 -> 40 | Y46: =B46 -> Rivera Ramos Elmer Delis | Z46: =AA46-S46 -> 385.15406 | AA46: =1925+140+125 -> 2190 | AB46: =T46+Z46 -> 2458.7479 | AC46: =AB46/$R$2 -> 91.064737 | AD46: =+AC46/8 -> 11.383092 | AF46: =Z46/$R$1 -> 1.7831206
A47: 41 | B47: Soncco Soncco, Santos Evaristo | C47: PRO F | D47: =37.6666666666667*$R$3 -> 1167.6667 | H47: =SUM(D47:G47) -> 1167.6667 | I47: =H47*D73 -> 136.50023 | J47: =H47-I47 -> 1031.1664 | K47: =((D47+E47+F47)*(9.72%)) -> 113.4972 | L47: =(D47+E47+F47)*(16.66%) -> 194.53327 | M47: =L47*6% -> 11.671996 | N47: =(1130*30%)/(30)*30 -> 339 | O47: =H47*6% -> 70.06 | P47: =((H47*(0.63%))*1.18) -> 8.680434 | Q47: =(H47*(0.57%))*1.18 -> 7.853726 | R47: =(H47*(0.55%))*1.18 -> 7.5781567 | S47: =J47+K47+L47+M47+N47 -> 1689.8689 | T47: =H47+K47+L47+M47+N47+O47+P47+Q47+R47 -> 1920.5414 | U47: =T47/$R$2 -> 71.131165 | V47: =+U47/8 -> 8.8913956 | X47: =A47 -> 41 | Y47: =B47 -> Soncco Soncco, Santos Evaristo | Z47: =AA47-S47 -> 460.1311 | AA47: =1925+100+125 -> 2150 | AB47: =T47+Z47 -> 2380.6726 | AC47: =AB47/$R$2 -> 88.173057 | AD47: =+AC47/8 -> 11.021632 | AF47: =Z47/$R$1 -> 2.1302366
A48: 42 | B48: Ttito Tapara, Jose Pascual | C48: SNP | D48: =37.6666666666667*$R$3 -> 1167.6667 | F48: 113 | H48: =SUM(D48:G48) -> 1280.6667 | I48: =H48*$E$69 -> 166.48667 | J48: =H48-I48 -> 1114.18 | K48: =((D48+E48+F48)*(9.72%)) -> 124.4808 | L48: =(D48+E48+F48)*(16.66%) -> 213.35907 | M48: =L48*6% -> 12.801544 | N48: =(1130*30%)/(30)*30 -> 339 | O48: =H48*6% -> 76.84 | P48: =((H48*(0.63%))*1.18) -> 9.520476 | Q48: =(H48*(0.57%))*1.18 -> 8.613764 | R48: =(H48*(0.55%))*1.18 -> 8.3115267 | S48: =J48+K48+L48+M48+N48 -> 1803.8214 | T48: =H48+K48+L48+M48+N48+O48+P48+Q48+R48 -> 2073.5938 | U48: =T48/$R$2 -> 76.799772 | V48: =+U48/8 -> 9.5999715 | X48: =A48 -> 42 | Y48: =B48 -> Ttito Tapara, Jose Pascual | Z48: =AA48-S48 -> 346.17859 | AA48: =1925+100+125 -> 2150 | AB48: =T48+Z48 -> 2419.7724 | AC48: =AB48/$R$2 -> 89.621201 | AD48: =+AC48/8 -> 11.20265 | AF48: =Z48/$R$1 -> 1.6026787
A49: 43 | B49: Turpo Quispe Yury | C49: INT M | D49: =37.6666666666667*$R$3 -> 1167.6667 | F49: 113 | H49: =SUM(D49:G49) -> 1280.6667 | I49: =H49*$E$71 -> 145.6118 | J49: =H49-I49 -> 1135.0549 | K49: =((D49+E49+F49)*(9.72%)) -> 124.4808 | L49: =(D49+E49+F49)*(16.66%) -> 213.35907 | M49: =L49*6% -> 12.801544 | N49: =(1130*30%)/(30)*30 -> 339 | O49: =H49*6% -> 76.84 | P49: =((H49*(0.63%))*1.18) -> 9.520476 | Q49: =(H49*(0.57%))*1.18 -> 8.613764 | R49: =(H49*(0.55%))*1.18 -> 8.3115267 | S49: =J49+K49+L49+M49+N49 -> 1824.6963 | T49: =H49+K49+L49+M49+N49+O49+P49+Q49+R49 -> 2073.5938 | U49: =T49/$R$2 -> 76.799772 | V49: =+U49/8 -> 9.5999715 | X49: =A49 -> 43 | Y49: =B49 -> Turpo Quispe Yury | Z49: =AA49-S49 -> 325.30372 | AA49: =1925+100+125 -> 2150 | AB49: =T49+Z49 -> 2398.8976 | AC49: =AB49/$R$2 -> 88.848058 | AD49: =+AC49/8 -> 11.106007 | AF49: =Z49/$R$1 -> 1.5060358
A50: 44 | B50: Zea Mamani, Ignacio | C50: PRO F | D50: =37.6666666666667*$R$3 -> 1167.6667 | F50: 113 | H50: =SUM(D50:G50) -> 1280.6667 | I50: =H50*$D$66 -> 167.25507 | J50: =H50-I50 -> 1113.4116 | K50: =((D50+E50+F50)*(9.72%)) -> 124.4808 | L50: =(D50+E50+F50)*(16.66%) -> 213.35907 | M50: =L50*6% -> 12.801544 | N50: =(1130*30%)/(30)*30 -> 339 | O50: =H50*6% -> 76.84 | P50: =((H50*(0.63%))*1.18) -> 9.520476 | Q50: =(H50*(0.57%))*1.18 -> 8.613764 | R50: =(H50*(0.55%))*1.18 -> 8.3115267 | S50: =J50+K50+L50+M50+N50 -> 1803.053 | T50: =H50+K50+L50+M50+N50+O50+P50+Q50+R50 -> 2073.5938 | U50: =T50/$R$2 -> 76.799772 | V50: =+U50/8 -> 9.5999715 | X50: =A50 -> 44 | Y50: =B50 -> Zea Mamani, Ignacio | Z50: =AA50-S50 -> 386.94699 | AA50: =1925+140+125 -> 2190 | AB50: =T50+Z50 -> 2460.5408 | AC50: =AB50/$R$2 -> 91.131142 | AD50: =+AC50/8 -> 11.391393 | AF50: =Z50/$R$1 -> 1.7914212
A51: 45 | B51: Chile Yareta Justino | C51: INT M | D51: =37.6666666666667*$R$3 -> 1167.6667 | F51: 113 | G51: 103.58 | H51: =SUM(D51:G51) -> 1384.2467 | I51: =H51*$E$71 -> 157.38885 | J51: =H51-I51 -> 1226.8578 | K51: =((D51+E51+F51)*(9.72%)) -> 124.4808 | L51: =(D51+E51+F51)*(16.66%) -> 213.35907 | M51: =L51*6% -> 12.801544 | N51: =(1130*30%)/(30)*30 -> 339 | O51: =H51*6% -> 83.0548 | P51: =((H51*(0.63%))*1.18) -> 10.29049 | Q51: =(H51*(0.57%))*1.18 -> 9.3104431 | R51: =(H51*(0.55%))*1.18 -> 8.9837609 | S51: =J51+K51+L51+M51+N51 -> 1916.4992 | T51: =H51+K51+L51+M51+N51+O51+P51+Q51+R51 -> 2185.5276 | U51: =T51/$R$2 -> 80.945466 | V51: =+U51/8 -> 10.118183 | X51: =A51 -> 45 | Y51: =B51 -> Chile Yareta Justino | Z51: =AA51-S51 -> 231.50077 | AA51: =1923+100+125 -> 2148 | AB51: =T51+Z51 -> 2417.0283 | AC51: =AB51/$R$2 -> 89.519568 | AD51: =+AC51/8 -> 11.189946 | AF51: =Z51/$R$1 -> 1.0717628
A52: 46 | B52: Diaz Chipana Walter | C52: INT M | D52: =37.6666666666667*$R$3 -> 1167.6667 | H52: =SUM(D52:G52) -> 1167.6667 | I52: =H52*$E$71 -> 132.7637 | J52: =H52-I52 -> 1034.903 | K52: =((D52+E52+F52)*(9.72%)) -> 113.4972 | L52: =(D52+E52+F52)*(16.66%) -> 194.53327 | M52: =L52*6% -> 11.671996 | N52: =(1130*30%)/(30)*30 -> 339 | O52: =H52*6% -> 70.06 | P52: =((H52*(0.63%))*1.18) -> 8.680434 | Q52: =(H52*(0.57%))*1.18 -> 7.853726 | R52: =(H52*(0.55%))*1.18 -> 7.5781567 | S52: =J52+K52+L52+M52+N52 -> 1693.6054 | T52: =H52+K52+L52+M52+N52+O52+P52+Q52+R52 -> 1920.5414 | U52: =T52/$R$2 -> 71.131165 | V52: =+U52/8 -> 8.8913956 | X52: =A52 -> 46 | Y52: =B52 -> Diaz Chipana Walter | Z52: =AA52-S52 -> 496.39457 | AA52: =1925+140+125 -> 2190 | AB52: =T52+Z52 -> 2416.936 | AC52: =AB52/$R$2 -> 89.516149 | AD52: =+AC52/8 -> 11.189519 | AF52: =Z52/$R$1 -> 2.298123
A53: 47 | B53: Quispe Gutierrez Leonardo | C53: INT M | D53: =37.6666666666667*$R$3 -> 1167.6667 | G53: 94.16 | H53: =SUM(D53:G53) -> 1261.8267 | I53: =H53*$E$71 -> 143.46969 | J53: =H53-I53 -> 1118.357 | K53: =((D53+E53+F53)*(9.72%)) -> 113.4972 | L53: =(D53+E53+F53)*(16.66%) -> 194.53327 | M53: =L53*6% -> 11.671996 | N53: =(1130*30%)/(30)*30 -> 339 | O53: =H53*6% -> 75.7096 | P53: =((H53*(0.63%))*1.18) -> 9.3804194 | Q53: =(H53*(0.57%))*1.18 -> 8.4870462 | R53: =(H53*(0.55%))*1.18 -> 8.1892551 | S53: =J53+K53+L53+M53+N53 -> 1777.0594 | T53: =H53+K53+L53+M53+N53+O53+P53+Q53+R53 -> 2022.2955 | U53: =T53/$R$2 -> 74.899831 | V53: =+U53/8 -> 9.3624789 | X53: =A53 -> 47 | Y53: =B53 -> Quispe Gutierrez Leonardo | Z53: =AA53-S53 -> 370.94056 | AA53: =1923+100+125 -> 2148 | AB53: =T53+Z53 -> 2393.236 | AC53: =AB53/$R$2 -> 88.638371 | AD53: =+AC53/8 -> 11.079796 | AF53: =Z53/$R$1 -> 1.7173174
A54: 48 | B54: Santiago Espinoza Yovani | C54: INT M | D54: =37.6666666666667*$R$3 -> 1167.6667 | F54: 113 | G54: 103.58 | H54: =SUM(D54:G54) -> 1384.2467 | I54: =H54*$E$71 -> 157.38885 | J54: =H54-I54 -> 1226.8578 | K54: =((D54+E54+F54)*(9.72%)) -> 124.4808 | L54: =(D54+E54+F54)*(16.66%) -> 213.35907 | M54: =L54*6% -> 12.801544 | N54: =(1130*30%)/(30)*30 -> 339 | O54: =H54*6% -> 83.0548 | P54: =((H54*(0.63%))*1.18) -> 10.29049 | Q54: =(H54*(0.57%))*1.18 -> 9.3104431 | R54: =(H54*(0.55%))*1.18 -> 8.9837609 | S54: =J54+K54+L54+M54+N54 -> 1916.4992 | T54: =H54+K54+L54+M54+N54+O54+P54+Q54+R54 -> 2185.5276 | U54: =T54/$R$2 -> 80.945466 | V54: =+U54/8 -> 10.118183 | X54: =A54 -> 48 | Y54: =B54 -> Santiago Espinoza Yovani | Z54: =AA54-S54 -> 231.50077 | AA54: =1923+100+125 -> 2148 | AB54: =T54+Z54 -> 2417.0283 | AC54: =AB54/$R$2 -> 89.519568 | AD54: =+AC54/8 -> 11.189946 | AF54: =Z54/$R$1 -> 1.0717628
D58: =SUM(D7:D54) -> 56048 | E58: =SUM(E7:E54) -> 259.6699 | F58: =SUM(F7:F54) -> 2486 | G58: =SUM(G7:G54) -> 602.64 | H58: =SUM(H7:H54) -> 59396.31 | I58: =SUM(I7:I54) -> 6987.5645 | K58: =SUM(K7:K54) -> 5714.7447 | L58: =SUM(L7:L54) -> 9795.0254 | M58: =SUM(M7:M54) -> 587.70152 | N58: =SUM(N7:N54) -> 16260.7 | O58: =SUM(O7:O54) -> 3563.7786 | P58: =SUM(P7:P54) -> 441.55217 | Q58: =SUM(Q7:Q54) -> 399.49958 | R58: =SUM(R7:R54) -> 385.48205 | ... V58: =SUM(V7:V54) -> 446.96664 | Z58: =SUM(Z7:Z54) -> 18932.083 | AA58: =SUM(AA7:AA54) -> 103699 | AB58: =SUM(AB7:AB54) -> 115476.88 | AC58: =SUM(AC7:AC55) -> 4276.9214 | AD58: =SUM(AD7:AD55) -> 534.61517 | AF58: =SUM(AF7:AF54) -> 87.648532 | AG58: =SUM(AG7:AG54) -> 0
T60: =+T58 -> 96544.794
T61: =Z58 -> 18932.083
C62: Descuentos de AFP | T62: =AB58 -> 115476.88
C63: AFP | D63: Flujo | E63: Mixta
C64: INT F | D64: 0.1292
C65: prima F | D65: 0.1297
C66: PRO F | D66: 0.1306
C67: habitab F | D67: 0.1284
C68: HAB M | E68: 0.1137
C69: SNP | D69: 0.13 | E69: 0.13
C70: PRO M | E70: 0.1137
C71: INT M | E71: 0.1137
C72: PRI M | E72: 0.1137
C73: PRO F | D73: 0.1169 | E73: MAYOR DE 65 AÑOS EXONERADOS DE PRIMA
C74: INT M | D74: =11.84%-1.84% -> 0.1 | E74: MAYOR DE 65 AÑOS EXONERADOS DE PRIMA

Sheet PLAME
AP1: =AP2*8 -> 216 | AQ1: Horas
AP2: 27 | AQ2: Dias laborables
AP3: 31 | AQ3: Dias
A4: MES DE ENERO 2026
A5: Nº | B5: NOMBRES | C5: SPP o SNP | D5: INFORMACION | F5: SUSPENSION PERFECTA | N5: SUSPENSIÓN IMPERFECTA | Y5: INGRESOS | AH5: DESCUENTOS | AM5: NETO A PAGAR | AN5: APORTES DEL EMPLEADOR
D6: PENSIONISTA | E6: EDAD | F6: 01 - S.P. Sanción disciplinaria | G6: 02 - S.P. Ejercicio del derecho de huelga | H6: 03 - Detención del trabajador, salvo el caso de c | I6: 04 - Inhabilitación administrativa o judicial por | J6: 05 - Permiso o licencia concedidos por el emplea | K6: 06 - Caso fortuito o fuerza mayor | L6: 08 - Falta no justificada | M6: 08 - Por temporada o intermitente | N6: 20 - Enfermedad o accidente (primeros veinte días) | O6: 21 - Incapacidad temporal (invalidez, enfermeda | P6: 22 - Maternidad durante el descanso pre y post na | Q6: 23 - Descanso vacacional | R6: 24 - Licencia para desempeñar cargo cívico y p | S6: 25 - Permiso y licencia para el desempeño de carg | T6: 26 - Licencia con goce de haber | U6: 27 - Días compensados por horas trabajadas en so | V6: DIAS NO LABORADOS | W6: DIAS LABORADOS | X6: TOTAL HORAS | Y6: 0117 - COMP. VACACIONAL | Z6: 0118 - REM. VAC. | AA6: 0121 - REM. JORN. BAS. | AB6: 0201 - ASIG. FAMILIAR | AC6: REMUNERACION BRUTA | AD6: 0312 - BONIF. EXT. TEMP. | AE6: 0314 - BETA 30 % | AF6: 0406 - GRATIF. FIEST. P. NAV. | AG6: 0904 - CTS | AH6: 0601 - COMI. AFP % | AI6: 0605 - RENTA 5TA CAT. RET. | AJ6: 0606 - PRIMA DE SEG. AFP | AK6: 0607 - SNP | AL6: 0608 - SPP APORT. OBL. | AN6: 0803 - POLIZA | AO6: 0804 - ESSALUD | AP6: 0805 - SCTR | AQ6: 0810 - EPS
A7: 1 | B7: Apaza Tito Patricia | C7: PRO F | V7: =SUM(L7:Q7) -> 0 | W7: =$AP$3-V7 -> 31 | X7: ='REPORTE DIARIO'!AI7 -> 216 | Y7: =PROYECTADA!G7 -> 0 | Z7: =1130/30*Q7 -> 0 | AA7: =PROYECTADA!D7/$AP$1*PLAME!X7 -> 1167.6667 | AB7: =PROYECTADA!F7/$AP$3*($AP$3-L7) -> 0 | AC7: =SUM(Z7:AB7) -> 1167.6667 | AD7: =6%*AF7 -> 11.671996 | AE7: =((30%*1130)/$AP$3)*($AP$3-L7) -> 339 | AF7: =16.66%*AC7 -> 194.53327 | AG7: =9.72%*AC7 -> 113.4972 | AH7: =IF(OR(D7="SI", C7="SNP"), 0, VLOOKUP(C7, tbl_descuentos[], 2, FALSE) * SUM(Y7:AB7)) -> 19.733567 | AI7: 0 | AJ7: =IF(OR(D7="SI", C7="SNP"), 0, VLOOKUP(C7, tbl_descuentos[], IF(E7 > 65, 4, 3), FALSE) * SUM(Y7:AB7)) -> 15.997033 | AK7: =IF(D7="SI",0,IF(C7="SNP",13%*SUM(Y7:AB7),0)) -> 0 | AL7: =IF(C7="SNP",0,IF(D7="SI",0,10%*(AC7+Y7))) -> 116.76667 | AM7: =SUMPRODUCT(ROUND(Y7:AB7, 2)) + SUMPRODUCT(ROUND(AD7:AG7, 2)) - SUMPRODUCT(ROUND(AH7:AL7, 2)) -> 1673.87 | AN7: =PROYECTADA!P7 -> 9.609684 | AO7: =6%*SUM(Y7:AB7) -> 70.06 | AP7: =PROYECTADA!Q7 -> 8.694476 | AQ7: =PROYECTADA!R7 -> 8.3894067 | AX7: =IF(AND(AM7=AS7,AN7,AT7,AO7,AU7,AP7,AV7,AQ7,AW7),"OK","ERROR") -> ERROR
A8: 2 | B8: Aquino Gómez Basilia Isabel | C8: PRO F | V8: =SUM(L8:Q8) -> 0 | W8: =$AP$3-V8 -> 31 | X8: ='REPORTE DIARIO'!AI8 -> 216 | Y8: =PROYECTADA!G8 -> 0 | Z8: =1130/30*Q8 -> 0 | AA8: =PROYECTADA!D8/$AP$1*PLAME!X8 -> 1167.6667 | AB8: =PROYECTADA!F8/$AP$3*($AP$3-L8) -> 0 | AC8: =SUM(Z8:AB8) -> 1167.6667 | AD8: =6%*AF8 -> 11.671996 | AE8: =((30%*1130)/$AP$3)*($AP$3-L8) -> 339 | AF8: =16.66%*AC8 -> 194.53327 | AG8: =9.72%*AC8 -> 113.4972 | AH8: =IF(OR(D8="SI", C8="SNP"), 0, VLOOKUP(C8, tbl_descuentos[], 2, FALSE) * SUM(Y8:AB8)) -> 19.733567 | AI8: 0 | AJ8: =IF(OR(D8="SI", C8="SNP"), 0, VLOOKUP(C8, tbl_descuentos[], IF(E8 > 65, 4, 3), FALSE) * SUM(Y8:AB8)) -> 15.997033 | AK8: =IF(D8="SI",0,IF(C8="SNP",13%*SUM(Y8:AB8),0)) -> 0 | AL8: =IF(C8="SNP",0,IF(D8="SI",0,10%*(AC8+Y8))) -> 116.76667 | AM8: =SUMPRODUCT(ROUND(Y8:AB8, 2)) + SUMPRODUCT(ROUND(AD8:AG8, 2)) - SUMPRODUCT(ROUND(AH8:AL8, 2)) -> 1673.87 | AN8: =PROYECTADA!P8 -> 8.680434 | AO8: =6%*SUM(Y8:AB8) -> 70.06 | AP8: =PROYECTADA!Q8 -> 7.853726 | AQ8: =PROYECTADA!R8 -> 7.5781567 | AX8: =IF(AND(AM8=AS8,AN8,AT8,AO8,AU8,AP8,AV8,AQ8,AW8),"OK","ERROR") -> ERROR
A9: 3 | B9: Calla G Guillermina | C9: PRO F | V9: =SUM(L9:Q9) -> 0 | W9: =$AP$3-V9 -> 31 | X9: ='REPORTE DIARIO'!AI9 -> 216 | Y9: =PROYECTADA!G9 -> 0 | Z9: =1130/30*Q9 -> 0 | AA9: =PROYECTADA!D9/$AP$1*PLAME!X9 -> 1167.6667 | AB9: =PROYECTADA!F9/$AP$3*($AP$3-L9) -> 0 | AC9: =SUM(Z9:AB9) -> 1167.6667 | AD9: =6%*AF9 -> 11.671996 | AE9: =((30%*1130)/$AP$3)*($AP$3-L9) -> 339 | AF9: =16.66%*AC9 -> 194.53327 | AG9: =9.72%*AC9 -> 113.4972 | AH9: =IF(OR(D9="SI", C9="SNP"), 0, VLOOKUP(C9, tbl_descuentos[], 2, FALSE) * SUM(Y9:AB9)) -> 19.733567 | AI9: 0 | AJ9: =IF(OR(D9="SI", C9="SNP"), 0, VLOOKUP(C9, tbl_descuentos[], IF(E9 > 65, 4, 3), FALSE) * SUM(Y9:AB9)) -> 15.997033 | AK9: =IF(D9="SI",0,IF(C9="SNP",13%*SUM(Y9:AB9),0)) -> 0 | AL9: =IF(C9="SNP",0,IF(D9="SI",0,10%*(AC9+Y9))) -> 116.76667 | AM9: =SUMPRODUCT(ROUND(Y9:AB9, 2)) + SUMPRODUCT(ROUND(AD9:AG9, 2)) - SUMPRODUCT(ROUND(AH9:AL9, 2)) -> 1673.87 | AN9: =PROYECTADA!P9 -> 8.680434 | AO9: =6%*SUM(Y9:AB9) -> 70.06 | AP9: =PROYECTADA!Q9 -> 7.853726 | AQ9: =PROYECTADA!R9 -> 7.5781567 | AX9: =IF(AND(AM9=AS9,AN9,AT9,AO9,AU9,AP9,AV9,AQ9,AW9),"OK","ERROR") -> ERROR
A10: 4 | B10: Challco Laime, Gilberta | C10: HAB M | L10: 1 | V10: =SUM(L10:Q10) -> 1 | W10: =$AP$3-V10 -> 30 | X10: ='REPORTE DIARIO'!AI10 -> 208 | Y10: =PROYECTADA!G10 -> 0 | Z10: =1130/30*Q10 -> 0 | AA10: =PROYECTADA!D10/$AP$1*PLAME!X10 -> 1124.4198 | AB10: =PROYECTADA!F10/$AP$3*($AP$3-L10) -> 0 | AC10: =SUM(Z10:AB10) -> 1124.4198 | AD10: =6%*AF10 -> 11.2397 | AE10: =((30%*1130)/$AP$3)*($AP$3-L10) -> 328.06452 | AF10: =16.66%*AC10 -> 187.32833 | AG10: =9.72%*AC10 -> 109.2936 | AH10: =IF(OR(D10="SI", C10="SNP"), 0, VLOOKUP(C10, tbl_descuentos[], 2, FALSE) * SUM(Y10:AB10)) -> 0 | AI10: 0 | AJ10: =IF(OR(D10="SI", C10="SNP"), 0, VLOOKUP(C10, tbl_descuentos[], IF(E10 > 65, 4, 3), FALSE) * SUM(Y10:AB10)) -> 15.404551 | AK10: =IF(D10="SI",0,IF(C10="SNP",13%*SUM(Y10:AB10),0)) -> 0 | AL10: =IF(C10="SNP",0,IF(D10="SI",0,10%*(AC10+Y10))) -> 112.44198 | AM10: =SUMPRODUCT(ROUND(Y10:AB10, 2)) + SUMPRODUCT(ROUND(AD10:AG10, 2)) - SUMPRODUCT(ROUND(AH10:AL10, 2)) -> 1632.5 | AN10: =PROYECTADA!P10 -> 8.680434 | AO10: =6%*SUM(Y10:AB10) -> 67.465185 | AP10: =PROYECTADA!Q10 -> 7.853726 | AQ10: =PROYECTADA!R10 -> 7.5781567 | AS10: 1632.5 | AT10: 8.680434 | AU10: 67.465185 | AV10: 7.853726 | AW10: 7.5781567 | AX10: =IF(AND(AM10=AS10,AN10,AT10,AO10,AU10,AP10,AV10,AQ10,AW10),"OK","ERROR") -> OK
A11: 5 | B11: Choquehuayta Huallpa, Estefania | C11: PRO M | V11: =SUM(L11:Q11) -> 0 | W11: =$AP$3-V11 -> 31 | X11: ='REPORTE DIARIO'!AI11 -> 210 | Y11: =PROYECTADA!G11 -> 0 | Z11: =1130/30*Q11 -> 0 | AA11: =PROYECTADA!D11/$AP$1*PLAME!X11 -> 1135.2315 | AB11: =PROYECTADA!F11/$AP$3*($AP$3-L11) -> 113 | AC11: =SUM(Z11:AB11) -> 1248.2315 | AD11: =6%*AF11 -> 12.477322 | AE11: =((30%*1130)/$AP$3)*($AP$3-L11) -> 339 | AF11: =16.66%*AC11 -> 207.95536 | AG11: =9.72%*AC11 -> 121.3281 | AH11: =IF(OR(D11="SI", C11="SNP"), 0, VLOOKUP(C11, tbl_descuentos[], 2, FALSE) * SUM(Y11:AB11)) -> 0 | AI11: 0 | AJ11: =IF(OR(D11="SI", C11="SNP"), 0, VLOOKUP(C11, tbl_descuentos[], IF(E11 > 65, 4, 3), FALSE) * SUM(Y11:AB11)) -> 17.100771 | AK11: =IF(D11="SI",0,IF(C11="SNP",13%*SUM(Y11:AB11),0)) -> 0 | AL11: =IF(C11="SNP",0,IF(D11="SI",0,10%*(AC11+Y11))) -> 124.82315 | AM11: =SUMPRODUCT(ROUND(Y11:AB11, 2)) + SUMPRODUCT(ROUND(AD11:AG11, 2)) - SUMPRODUCT(ROUND(AH11:AL11, 2)) -> 1787.08 | AN11: =PROYECTADA!P11 -> 9.520476 | AO11: =6%*SUM(Y11:AB11) -> 74.893889 | AP11: =PROYECTADA!Q11 -> 8.613764 | AQ11: =PROYECTADA!R11 -> 8.3115267 | AX11: =IF(AND(AM11=AS11,AN11,AT11,AO11,AU11,AP11,AV11,AQ11,AW11),"OK","ERROR") -> ERROR
A12: 6 | B12: Idme Huaraccallo, Gladis | C12: SNP | V12: =SUM(L12:Q12) -> 0 | W12: =$AP$3-V12 -> 31 | X12: ='REPORTE DIARIO'!AI12 -> 216 | Y12: =PROYECTADA!G12 -> 0 | Z12: =1130/30*Q12 -> 0 | AA12: =PROYECTADA!D12/$AP$1*PLAME!X12 -> 1167.6667 | AB12: =PROYECTADA!F12/$AP$3*($AP$3-L12) -> 0 | AC12: =SUM(Z12:AB12) -> 1167.6667 | AD12: =6%*AF12 -> 11.671996 | AE12: =((30%*1130)/$AP$3)*($AP$3-L12) -> 339 | AF12: =16.66%*AC12 -> 194.53327 | AG12: =9.72%*AC12 -> 113.4972 | AH12: =IF(OR(D12="SI", C12="SNP"), 0, VLOOKUP(C12, tbl_descuentos[], 2, FALSE) * SUM(Y12:AB12)) -> 0 | AI12: 0 | AJ12: =IF(OR(D12="SI", C12="SNP"), 0, VLOOKUP(C12, tbl_descuentos[], IF(E12 > 65, 4, 3), FALSE) * SUM(Y12:AB12)) -> 0 | AK12: =IF(D12="SI",0,IF(C12="SNP",13%*SUM(Y12:AB12),0)) -> 151.79667 | AL12: =IF(C12="SNP",0,IF(D12="SI",0,10%*(AC12+Y12))) -> 0 | AM12: =SUMPRODUCT(ROUND(Y12:AB12, 2)) + SUMPRODUCT(ROUND(AD12:AG12, 2)) - SUMPRODUCT(ROUND(AH12:AL12, 2)) -> 1674.57 | AN12: =PROYECTADA!P12 -> 8.680434 | AO12: =6%*SUM(Y12:AB12) -> 70.06 | AP12: =PROYECTADA!Q12 -> 7.853726 | AQ12: =PROYECTADA!R12 -> 7.5781567 | AS12: 1674.57 | AT12: 8.680434 | AU12: 70.06 | AV12: 7.853726 | AW12: 7.5781567 | AX12: =IF(AND(AM12=AS12,AN12,AT12,AO12,AU12,AP12,AV12,AQ12,AW12),"OK","ERROR") -> OK
A13: 7 | B13: Jacha Gomez, Flavia | C13: INT F | V13: =SUM(L13:Q13) -> 0 | W13: =$AP$3-V13 -> 31 | X13: ='REPORTE DIARIO'!AI13 -> 184 | Y13: =PROYECTADA!G13 -> 0 | Z13: =1130/30*Q13 -> 0 | AA13: =PROYECTADA!D13/$AP$1*PLAME!X13 -> 994.67901 | AB13: =PROYECTADA!F13/$AP$3*($AP$3-L13) -> 0 | AC13: =SUM(Z13:AB13) -> 994.67901 | AD13: =6%*AF13 -> 9.9428114 | AE13: =((30%*1130)/$AP$3)*($AP$3-L13) -> 339 | AF13: =16.66%*AC13 -> 165.71352 | AG13: =9.72%*AC13 -> 96.6828 | AH13: =IF(OR(D13="SI", C13="SNP"), 0, VLOOKUP(C13, tbl_descuentos[], 2, FALSE) * SUM(Y13:AB13)) -> 15.417525 | AI13: 0 | AJ13: =IF(OR(D13="SI", C13="SNP"), 0, VLOOKUP(C13, tbl_descuentos[], IF(E13 > 65, 4, 3), FALSE) * SUM(Y13:AB13)) -> 13.627102 | AK13: =IF(D13="SI",0,IF(C13="SNP",13%*SUM(Y13:AB13),0)) -> 0 | AL13: =IF(C13="SNP",0,IF(D13="SI",0,10%*(AC13+Y13))) -> 99.467901 | AM13: =SUMPRODUCT(ROUND(Y13:AB13, 2)) + SUMPRODUCT(ROUND(AD13:AG13, 2)) - SUMPRODUCT(ROUND(AH13:AL13, 2)) -> 1477.49 | AN13: =PROYECTADA!P13 -> 8.680434 | AO13: =6%*SUM(Y13:AB13) -> 59.680741 | AP13: =PROYECTADA!Q13 -> 7.853726 | AQ13: =PROYECTADA!R13 -> 7.5781567 | AX13: =IF(AND(AM13=AS13,AN13,AT13,AO13,AU13,AP13,AV13,AQ13,AW13),"OK","ERROR") -> ERROR
A14: 8 | B14: Lerma Yanarico Elena | C14: PRO F | V14: =SUM(L14:Q14) -> 0 | W14: =$AP$3-V14 -> 31 | X14: ='REPORTE DIARIO'!AI14 -> 216 | Y14: =PROYECTADA!G14 -> 0 | Z14: =1130/30*Q14 -> 0 | AA14: =PROYECTADA!D14/$AP$1*PLAME!X14 -> 1167.6667 | AB14: =PROYECTADA!F14/$AP$3*($AP$3-L14) -> 113 | AC14: =SUM(Z14:AB14) -> 1280.6667 | AD14: =6%*AF14 -> 12.801544 | AE14: =((30%*1130)/$AP$3)*($AP$3-L14) -> 339 | AF14: =16.66%*AC14 -> 213.35907 | AG14: =9.72%*AC14 -> 124.4808 | AH14: =IF(OR(D14="SI", C14="SNP"), 0, VLOOKUP(C14, tbl_descuentos[], 2, FALSE) * SUM(Y14:AB14)) -> 21.643267 | AI14: 0 | AJ14: =IF(OR(D14="SI", C14="SNP"), 0, VLOOKUP(C14, tbl_descuentos[], IF(E14 > 65, 4, 3), FALSE) * SUM(Y14:AB14)) -> 17.545133 | AK14: =IF(D14="SI",0,IF(C14="SNP",13%*SUM(Y14:AB14),0)) -> 0 | AL14: =IF(C14="SNP",0,IF(D14="SI",0,10%*(AC14+Y14))) -> 128.06667 | AM14: =SUMPRODUCT(ROUND(Y14:AB14, 2)) + SUMPRODUCT(ROUND(AD14:AG14, 2)) - SUMPRODUCT(ROUND(AH14:AL14, 2)) -> 1803.05 | AN14: =PROYECTADA!P14 -> 9.520476 | AO14: =6%*SUM(Y14:AB14) -> 76.84 | AP14: =PROYECTADA!Q14 -> 8.613764 | AQ14: =PROYECTADA!R14 -> 8.3115267 | AX14: =IF(AND(AM14=AS14,AN14,AT14,AO14,AU14,AP14,AV14,AQ14,AW14),"OK","ERROR") -> ERROR
A15: 9 | B15: Machaca Calcina, Benedicta | C15: INT M | V15: =SUM(L15:Q15) -> 0 | W15: =$AP$3-V15 -> 31 | X15: ='REPORTE DIARIO'!AI15 -> 182 | Y15: =PROYECTADA!G15 -> 0 | Z15: =1130/30*Q15 -> 0 | AA15: =PROYECTADA!D15/$AP$1*PLAME!X15 -> 983.86728 | AB15: =PROYECTADA!F15/$AP$3*($AP$3-L15) -> 113 | AC15: =SUM(Z15:AB15) -> 1096.8673 | AD15: =6%*AF15 -> 10.964285 | AE15: =((30%*1130)/$AP$3)*($AP$3-L15) -> 339 | AF15: =16.66%*AC15 -> 182.73809 | AG15: =9.72%*AC15 -> 106.6155 | AH15: =IF(OR(D15="SI", C15="SNP"), 0, VLOOKUP(C15, tbl_descuentos[], 2, FALSE) * SUM(Y15:AB15)) -> 0 | AI15: 0 | AJ15: =IF(OR(D15="SI", C15="SNP"), 0, VLOOKUP(C15, tbl_descuentos[], IF(E15 > 65, 4, 3), FALSE) * SUM(Y15:AB15)) -> 15.027082 | AK15: =IF(D15="SI",0,IF(C15="SNP",13%*SUM(Y15:AB15),0)) -> 0 | AL15: =IF(C15="SNP",0,IF(D15="SI",0,10%*(AC15+Y15))) -> 109.68673 | AM15: =SUMPRODUCT(ROUND(Y15:AB15, 2)) + SUMPRODUCT(ROUND(AD15:AG15, 2)) - SUMPRODUCT(ROUND(AH15:AL15, 2)) -> 1611.47 | AN15: =PROYECTADA!P15 -> 9.520476 | AO15: =6%*SUM(Y15:AB15) -> 65.812037 | AP15: =PROYECTADA!Q15 -> 8.613764 | AQ15: =PROYECTADA!R15 -> 8.3115267 | AX15: =IF(AND(AM15=AS15,AN15,AT15,AO15,AU15,AP15,AV15,AQ15,AW15),"OK","ERROR") -> ERROR
A16: 10 | B16: Mamani Hancco, Elsa Teresa | C16: INT F | V16: =SUM(L16:Q16) -> 0 | W16: =$AP$3-V16 -> 31 | X16: ='REPORTE DIARIO'!AI16 -> 216 | Y16: =PROYECTADA!G16 -> 0 | Z16: =1130/30*Q16 -> 0 | AA16: =PROYECTADA!D16/$AP$1*PLAME!X16 -> 1167.6667 | AB16: =PROYECTADA!F16/$AP$3*($AP$3-L16) -> 113 | AC16: =SUM(Z16:AB16) -> 1280.6667 | AD16: =6%*AF16 -> 12.801544 | AE16: =((30%*1130)/$AP$3)*($AP$3-L16) -> 339 | AF16: =16.66%*AC16 -> 213.35907 | AG16: =9.72%*AC16 -> 124.4808 | AH16: =IF(OR(D16="SI", C16="SNP"), 0, VLOOKUP(C16, tbl_descuentos[], 2, FALSE) * SUM(Y16:AB16)) -> 19.850333 | AI16: 0 | AJ16: =IF(OR(D16="SI", C16="SNP"), 0, VLOOKUP(C16, tbl_descuentos[], IF(E16 > 65, 4, 3), FALSE) * SUM(Y16:AB16)) -> 17.545133 | AK16: =IF(D16="SI",0,IF(C16="SNP",13%*SUM(Y16:AB16),0)) -> 0 | AL16: =IF(C16="SNP",0,IF(D16="SI",0,10%*(AC16+Y16))) -> 128.06667 | AM16: =SUMPRODUCT(ROUND(Y16:AB16, 2)) + SUMPRODUCT(ROUND(AD16:AG16, 2)) - SUMPRODUCT(ROUND(AH16:AL16, 2)) -> 1804.84 | AN16: =PROYECTADA!P16 -> 9.520476 | AO16: =6%*SUM(Y16:AB16) -> 76.84 | AP16: =PROYECTADA!Q16 -> 8.613764 | AQ16: =PROYECTADA!R16 -> 8.3115267 | AX16: =IF(AND(AM16=AS16,AN16,AT16,AO16,AU16,AP16,AV16,AQ16,AW16),"OK","ERROR") -> ERROR
A17: 11 | B17: Mamani Itusaca de Perca Guzmila | C17: HAB M | V17: =SUM(L17:Q17) -> 0 | W17: =$AP$3-V17 -> 31 | X17: ='REPORTE DIARIO'!AI17 -> 208 | Y17: =PROYECTADA!G17 -> 0 | Z17: =1130/30*Q17 -> 0 | AA17: =PROYECTADA!D17/$AP$1*PLAME!X17 -> 1124.4198 | AB17: =PROYECTADA!F17/$AP$3*($AP$3-L17) -> 0 | AC17: =SUM(Z17:AB17) -> 1124.4198 | AD17: =6%*AF17 -> 11.2397 | AE17: =((30%*1130)/$AP$3)*($AP$3-L17) -> 339 | AF17: =16.66%*AC17 -> 187.32833 | AG17: =9.72%*AC17 -> 109.2936 | AH17: =IF(OR(D17="SI", C17="SNP"), 0, VLOOKUP(C17, tbl_descuentos[], 2, FALSE) * SUM(Y17:AB17)) -> 0 | AI17: 0 | AJ17: =IF(OR(D17="SI", C17="SNP"), 0, VLOOKUP(C17, tbl_descuentos[], IF(E17 > 65, 4, 3), FALSE) * SUM(Y17:AB17)) -> 15.404551 | AK17: =IF(D17="SI",0,IF(C17="SNP",13%*SUM(Y17:AB17),0)) -> 0 | AL17: =IF(C17="SNP",0,IF(D17="SI",0,10%*(AC17+Y17))) -> 112.44198 | AM17: =SUMPRODUCT(ROUND(Y17:AB17, 2)) + SUMPRODUCT(ROUND(AD17:AG17, 2)) - SUMPRODUCT(ROUND(AH17:AL17, 2)) -> 1643.44 | AN17: =PROYECTADA!P17 -> 8.680434 | AO17: =6%*SUM(Y17:AB17) -> 67.465185 | AP17: =PROYECTADA!Q17 -> 7.853726 | AQ17: =PROYECTADA!R17 -> 7.5781567 | AX17: =IF(AND(AM17=AS17,AN17,AT17,AO17,AU17,AP17,AV17,AQ17,AW17),"OK","ERROR") -> ERROR
A18: 12 | B18: Mayta Coaquira Janet Venancia | C18: INT M | Q18: 13 | V18: =SUM(L18:Q18) -> 13 | W18: =$AP$3-V18 -> 18 | X18: ='REPORTE DIARIO'!AI18 -> 120 | Y18: =PROYECTADA!G18 -> 0 | Z18: 489.63 | AA18: =PROYECTADA!D18/$AP$1*PLAME!X18 -> 648.7037 | AB18: =PROYECTADA!F18/$AP$3*($AP$3-L18) -> 0 | AC18: =SUM(Z18:AB18) -> 1138.3337 | AD18: =6%*AF18 -> 11.378784 | AE18: =((30%*1130)/$AP$3)*($AP$3-L18) -> 339 | AF18: =16.66%*AC18 -> 189.6464 | AG18: =9.72%*AC18 -> 110.64604 | AH18: =IF(OR(D18="SI", C18="SNP"), 0, VLOOKUP(C18, tbl_descuentos[], 2, FALSE) * SUM(Y18:AB18)) -> 0 | AI18: 0 | AJ18: =IF(OR(D18="SI", C18="SNP"), 0, VLOOKUP(C18, tbl_descuentos[], IF(E18 > 65, 4, 3), FALSE) * SUM(Y18:AB18)) -> 15.595172 | AK18: =IF(D18="SI",0,IF(C18="SNP",13%*SUM(Y18:AB18),0)) -> 0 | AL18: =IF(C18="SNP",0,IF(D18="SI",0,10%*(AC18+Y18))) -> 113.83337 | AM18: =SUMPRODUCT(ROUND(Y18:AB18, 2)) + SUMPRODUCT(ROUND(AD18:AG18, 2)) - SUMPRODUCT(ROUND(AH18:AL18, 2)) -> 1659.58 | AN18: =PROYECTADA!P18 -> 8.680434 | AO18: =6%*SUM(Y18:AB18) -> 68.300022 | AP18: =PROYECTADA!Q18 -> 7.853726 | AQ18: =PROYECTADA!R18 -> 7.5781567 | AS18: 1659.58 | AT18: 8.680434 | AU18: 68.300022 | AV18: 7.853726 | AW18: 7.5781567 | AX18: =IF(AND(AM18=AS18,AN18,AT18,AO18,AU18,AP18,AV18,AQ18,AW18),"OK","ERROR") -> OK
A19: 13 | B19: Parari Laura Teresa Lucy | C19: PRO M | V19: =SUM(L19:Q19) -> 0 | W19: =$AP$3-V19 -> 31 | X19: ='REPORTE DIARIO'!AI19 -> 216 | Y19: =PROYECTADA!G19 -> 0 | Z19: =1130/30*Q19 -> 0 | AA19: =PROYECTADA!D19/$AP$1*PLAME!X19 -> 1167.6667 | AB19: =PROYECTADA!F19/$AP$3*($AP$3-L19) -> 0 | AC19: =SUM(Z19:AB19) -> 1167.6667 | AD19: =6%*AF19 -> 11.671996 | AE19: =((30%*1130)/$AP$3)*($AP$3-L19) -> 339 | AF19: =16.66%*AC19 -> 194.53327 | AG19: =9.72%*AC19 -> 113.4972 | AH19: =IF(OR(D19="SI", C19="SNP"), 0, VLOOKUP(C19, tbl_descuentos[], 2, FALSE) * SUM(Y19:AB19)) -> 0 | AI19: 0 | AJ19: =IF(OR(D19="SI", C19="SNP"), 0, VLOOKUP(C19, tbl_descuentos[], IF(E19 > 65, 4, 3), FALSE) * SUM(Y19:AB19)) -> 15.997033 | AK19: =IF(D19="SI",0,IF(C19="SNP",13%*SUM(Y19:AB19),0)) -> 0 | AL19: =IF(C19="SNP",0,IF(D19="SI",0,10%*(AC19+Y19))) -> 116.76667 | AM19: =SUMPRODUCT(ROUND(Y19:AB19, 2)) + SUMPRODUCT(ROUND(AD19:AG19, 2)) - SUMPRODUCT(ROUND(AH19:AL19, 2)) -> 1693.6 | AN19: =PROYECTADA!P19 -> 8.680434 | AO19: =6%*SUM(Y19:AB19) -> 70.06 | AP19: =PROYECTADA!Q19 -> 7.853726 | AQ19: =PROYECTADA!R19 -> 7.5781567 | AX19: =IF(AND(AM19=AS19,AN19,AT19,AO19,AU19,AP19,AV19,AQ19,AW19),"OK","ERROR") -> ERROR
A20: 14 | B20: Pelinco Machaca, Monica | C20: PRI M | V20: =SUM(L20:Q20) -> 0 | W20: =$AP$3-V20 -> 31 | X20: ='REPORTE DIARIO'!AI20 -> 216 | Y20: =PROYECTADA!G20 -> 0 | Z20: =1130/30*Q20 -> 0 | AA20: =PROYECTADA!D20/$AP$1*PLAME!X20 -> 1167.6667 | AB20: =PROYECTADA!F20/$AP$3*($AP$3-L20) -> 0 | AC20: =SUM(Z20:AB20) -> 1167.6667 | AD20: =6%*AF20 -> 11.671996 | AE20: =((30%*1130)/$AP$3)*($AP$3-L20) -> 339 | AF20: =16.66%*AC20 -> 194.53327 | AG20: =9.72%*AC20 -> 113.4972 | AH20: =IF(OR(D20="SI", C20="SNP"), 0, VLOOKUP(C20, tbl_descuentos[], 2, FALSE) * SUM(Y20:AB20)) -> 0 | AI20: 0 | AJ20: =IF(OR(D20="SI", C20="SNP"), 0, VLOOKUP(C20, tbl_descuentos[], IF(E20 > 65, 4, 3), FALSE) * SUM(Y20:AB20)) -> 15.997033 | AK20: =IF(D20="SI",0,IF(C20="SNP",13%*SUM(Y20:AB20),0)) -> 0 | AL20: =IF(C20="SNP",0,IF(D20="SI",0,10%*(AC20+Y20))) -> 116.76667 | AM20: =SUMPRODUCT(ROUND(Y20:AB20, 2)) + SUMPRODUCT(ROUND(AD20:AG20, 2)) - SUMPRODUCT(ROUND(AH20:AL20, 2)) -> 1693.6 | AN20: =PROYECTADA!P20 -> 8.680434 | AO20: =6%*SUM(Y20:AB20) -> 70.06 | AP20: =PROYECTADA!Q20 -> 7.853726 | AQ20: =PROYECTADA!R20 -> 7.5781567 | AX20: =IF(AND(AM20=AS20,AN20,AT20,AO20,AU20,AP20,AV20,AQ20,AW20),"OK","ERROR") -> ERROR
A21: 15 | B21: Quispe Pacco Obita | C21: PRO F | V21: =SUM(L21:Q21) -> 0 | W21: =$AP$3-V21 -> 31 | X21: ='REPORTE DIARIO'!AI21 -> 216 | Y21: =PROYECTADA!G21 -> 0 | Z21: =1130/30*Q21 -> 0 | AA21: =PROYECTADA!D21/$AP$1*PLAME!X21 -> 1167.6667 | AB21: =PROYECTADA!F21/$AP$3*($AP$3-L21) -> 0 | AC21: =SUM(Z21:AB21) -> 1167.6667 | AD21: =6%*AF21 -> 11.671996 | AE21: =((30%*1130)/$AP$3)*($AP$3-L21) -> 339 | AF21: =16.66%*AC21 -> 194.53327 | AG21: =9.72%*AC21 -> 113.4972 | AH21: =IF(OR(D21="SI", C21="SNP"), 0, VLOOKUP(C21, tbl_descuentos[], 2, FALSE) * SUM(Y21:AB21)) -> 19.733567 | AI21: 0 | AJ21: =IF(OR(D21="SI", C21="SNP"), 0, VLOOKUP(C21, tbl_descuentos[], IF(E21 > 65, 4, 3), FALSE) * SUM(Y21:AB21)) -> 15.997033 | AK21: =IF(D21="SI",0,IF(C21="SNP",13%*SUM(Y21:AB21),0)) -> 0 | AL21: =IF(C21="SNP",0,IF(D21="SI",0,10%*(AC21+Y21))) -> 116.76667 | AM21: =SUMPRODUCT(ROUND(Y21:AB21, 2)) + SUMPRODUCT(ROUND(AD21:AG21, 2)) - SUMPRODUCT(ROUND(AH21:AL21, 2)) -> 1673.87 | AN21: =PROYECTADA!P21 -> 8.680434 | AO21: =6%*SUM(Y21:AB21) -> 70.06 | AP21: =PROYECTADA!Q21 -> 7.853726 | AQ21: =PROYECTADA!R21 -> 7.5781567 | AX21: =IF(AND(AM21=AS21,AN21,AT21,AO21,AU21,AP21,AV21,AQ21,AW21),"OK","ERROR") -> ERROR
A22: 16 | B22: Aragon Hancco Delia Jesusa | C22: INT M | V22: =SUM(L22:Q22) -> 0 | W22: =$AP$3-V22 -> 31 | X22: ='REPORTE DIARIO'!AI22 -> 189 | Y22: =PROYECTADA!G22 -> 103.58 | Z22: =1130/30*Q22 -> 0 | AA22: =PROYECTADA!D22/$AP$1*PLAME!X22 -> 1021.7083 | AB22: =PROYECTADA!F22/$AP$3*($AP$3-L22) -> 113 | AC22: =SUM(Z22:AB22) -> 1134.7083 | AD22: =6%*AF22 -> 11.342545 | AE22: =((30%*1130)/$AP$3)*($AP$3-L22) -> 339 | AF22: =16.66%*AC22 -> 189.04241 | AG22: =9.72%*AC22 -> 110.29365 | AH22: =IF(OR(D22="SI", C22="SNP"), 0, VLOOKUP(C22, tbl_descuentos[], 2, FALSE) * SUM(Y22:AB22)) -> 0 | AI22: 0 | AJ22: =IF(OR(D22="SI", C22="SNP"), 0, VLOOKUP(C22, tbl_descuentos[], IF(E22 > 65, 4, 3), FALSE) * SUM(Y22:AB22)) -> 16.96455 | AK22: =IF(D22="SI",0,IF(C22="SNP",13%*SUM(Y22:AB22),0)) -> 0 | AL22: =IF(C22="SNP",0,IF(D22="SI",0,10%*(AC22+Y22))) -> 123.82883 | AM22: =SUMPRODUCT(ROUND(Y22:AB22, 2)) + SUMPRODUCT(ROUND(AD22:AG22, 2)) - SUMPRODUCT(ROUND(AH22:AL22, 2)) -> 1747.17 | AN22: =PROYECTADA!P22 -> 10.29049 | AO22: =6%*SUM(Y22:AB22) -> 74.2973 | AP22: =PROYECTADA!Q22 -> 9.3104431 | AQ22: =PROYECTADA!R22 -> 8.9837609 | AX22: =IF(AND(AM22=AS22,AN22,AT22,AO22,AU22,AP22,AV22,AQ22,AW22),"OK","ERROR") -> ERROR
A23: 17 | B23: Gonzales Aparicio Lisbeth | C23: INT M | V23: =SUM(L23:Q23) -> 0 | W23: =$AP$3-V23 -> 31 | X23: ='REPORTE DIARIO'!AI23 -> 216 | Y23: =PROYECTADA!G23 -> 94.16 | Z23: =1130/30*Q23 -> 0 | AA23: =PROYECTADA!D23/$AP$1*PLAME!X23 -> 1167.6667 | AB23: =PROYECTADA!F23/$AP$3*($AP$3-L23) -> 0 | AC23: =SUM(Z23:AB23) -> 1167.6667 | AD23: =6%*AF23 -> 11.671996 | AE23: =((30%*1130)/$AP$3)*($AP$3-L23) -> 339 | AF23: =16.66%*AC23 -> 194.53327 | AG23: =9.72%*AC23 -> 113.4972 | AH23: =IF(OR(D23="SI", C23="SNP"), 0, VLOOKUP(C23, tbl_descuentos[], 2, FALSE) * SUM(Y23:AB23)) -> 0 | AI23: 0 | AJ23: =IF(OR(D23="SI", C23="SNP"), 0, VLOOKUP(C23, tbl_descuentos[], IF(E23 > 65, 4, 3), FALSE) * SUM(Y23:AB23)) -> 17.287025 | AK23: =IF(D23="SI",0,IF(C23="SNP",13%*SUM(Y23:AB23),0)) -> 0 | AL23: =IF(C23="SNP",0,IF(D23="SI",0,10%*(AC23+Y23))) -> 126.18267 | AM23: =SUMPRODUCT(ROUND(Y23:AB23, 2)) + SUMPRODUCT(ROUND(AD23:AG23, 2)) - SUMPRODUCT(ROUND(AH23:AL23, 2)) -> 1777.06 | AN23: =PROYECTADA!P23 -> 9.3804194 | AO23: =6%*SUM(Y23:AB23) -> 75.7096 | AP23: =PROYECTADA!Q23 -> 8.4870462 | AQ23: =PROYECTADA!R23 -> 8.1892551 | AX23: =IF(AND(AM23=AS23,AN23,AT23,AO23,AU23,AP23,AV23,AQ23,AW23),"OK","ERROR") -> ERROR
A24: 18 | B24: Sánchez Huanca María Luisa | C24: PRO M | V24: =SUM(L24:Q24) -> 0 | W24: =$AP$3-V24 -> 31 | X24: ='REPORTE DIARIO'!AI24 -> 216 | Y24: =PROYECTADA!G24 -> 103.58 | Z24: =1130/30*Q24 -> 0 | AA24: =PROYECTADA!D24/$AP$1*PLAME!X24 -> 1167.6667 | AB24: =PROYECTADA!F24/$AP$3*($AP$3-L24) -> 113 | AC24: =SUM(Z24:AB24) -> 1280.6667 | AD24: =6%*AF24 -> 12.801544 | AE24: =((30%*1130)/$AP$3)*($AP$3-L24) -> 339 | AF24: =16.66%*AC24 -> 213.35907 | AG24: =9.72%*AC24 -> 124.4808 | AH24: =IF(OR(D24="SI", C24="SNP"), 0, VLOOKUP(C24, tbl_descuentos[], 2, FALSE) * SUM(Y24:AB24)) -> 0 | AI24: 0 | AJ24: =IF(OR(D24="SI", C24="SNP"), 0, VLOOKUP(C24, tbl_descuentos[], IF(E24 > 65, 4, 3), FALSE) * SUM(Y24:AB24)) -> 18.964179 | AK24: =IF(D24="SI",0,IF(C24="SNP",13%*SUM(Y24:AB24),0)) -> 0 | AL24: =IF(C24="SNP",0,IF(D24="SI",0,10%*(AC24+Y24))) -> 138.42467 | AM24: =SUMPRODUCT(ROUND(Y24:AB24, 2)) + SUMPRODUCT(ROUND(AD24:AG24, 2)) - SUMPRODUCT(ROUND(AH24:AL24, 2)) -> 1916.51 | AN24: =PROYECTADA!P24 -> 10.29049 | AO24: =6%*SUM(Y24:AB24) -> 83.0548 | AP24: =PROYECTADA!Q24 -> 9.3104431 | AQ24: =PROYECTADA!R24 -> 8.9837609 | AX24: =IF(AND(AM24=AS24,AN24,AT24,AO24,AU24,AP24,AV24,AQ24,AW24),"OK","ERROR") -> ERROR
A25: 19 | B25: Alvarez Chavez, Richard | C25: PRO F | V25: =SUM(L25:Q25) -> 0 | W25: =$AP$3-V25 -> 31 | X25: ='REPORTE DIARIO'!AI25 -> 208 | Y25: =PROYECTADA!G25 -> 0 | Z25: =1130/30*Q25 -> 0 | AA25: =PROYECTADA!D25/$AP$1*PLAME!X25 -> 1124.4198 | AB25: =PROYECTADA!F25/$AP$3*($AP$3-L25) -> 113 | AC25: =SUM(Z25:AB25) -> 1237.4198 | AD25: =6%*AF25 -> 12.369248 | AE25: =((30%*1130)/$AP$3)*($AP$3-L25) -> 339 | AF25: =16.66%*AC25 -> 206.15413 | AG25: =9.72%*AC25 -> 120.2772 | AH25: =IF(OR(D25="SI", C25="SNP"), 0, VLOOKUP(C25, tbl_descuentos[], 2, FALSE) * SUM(Y25:AB25)) -> 20.912394 | AI25: 0 | AJ25: =IF(OR(D25="SI", C25="SNP"), 0, VLOOKUP(C25, tbl_descuentos[], IF(E25 > 65, 4, 3), FALSE) * SUM(Y25:AB25)) -> 16.952651 | AK25: =IF(D25="SI",0,IF(C25="SNP",13%*SUM(Y25:AB25),0)) -> 0 | AL25: =IF(C25="SNP",0,IF(D25="SI",0,10%*(AC25+Y25))) -> 123.74198 | AM25: =SUMPRODUCT(ROUND(Y25:AB25, 2)) + SUMPRODUCT(ROUND(AD25:AG25, 2)) - SUMPRODUCT(ROUND(AH25:AL25, 2)) -> 1753.62 | AN25: =PROYECTADA!P25 -> 9.520476 | AO25: =6%*SUM(Y25:AB25) -> 74.245185 | AP25: =PROYECTADA!Q25 -> 8.613764 | AQ25: =PROYECTADA!R25 -> 8.3115267 | AX25: =IF(AND(AM25=AS25,AN25,AT25,AO25,AU25,AP25,AV25,AQ25,AW25),"OK","ERROR") -> ERROR
A26: 20 | B26: Aparicio Ch Claver | C26: PRO F | V26: =SUM(L26:Q26) -> 0 | W26: =$AP$3-V26 -> 31 | X26: ='REPORTE DIARIO'!AI26 -> 216 | Y26: =PROYECTADA!G26 -> 0 | Z26: =1130/30*Q26 -> 0 | AA26: =PROYECTADA!D26/$AP$1*PLAME!X26 -> 1167.6667 | AB26: =PROYECTADA!F26/$AP$3*($AP$3-L26) -> 113 | AC26: =SUM(Z26:AB26) -> 1280.6667 | AD26: =6%*AF26 -> 12.801544 | AE26: =((30%*1130)/$AP$3)*($AP$3-L26) -> 339 | AF26: =16.66%*AC26 -> 213.35907 | AG26: =9.72%*AC26 -> 124.4808 | AH26: =IF(OR(D26="SI", C26="SNP"), 0, VLOOKUP(C26, tbl_descuentos[], 2, FALSE) * SUM(Y26:AB26)) -> 21.643267 | AI26: 0 | AJ26: =IF(OR(D26="SI", C26="SNP"), 0, VLOOKUP(C26, tbl_descuentos[], IF(E26 > 65, 4, 3), FALSE) * SUM(Y26:AB26)) -> 17.545133 | AK26: =IF(D26="SI",0,IF(C26="SNP",13%*SUM(Y26:AB26),0)) -> 0 | AL26: =IF(C26="SNP",0,IF(D26="SI",0,10%*(AC26+Y26))) -> 128.06667 | AM26: =SUMPRODUCT(ROUND(Y26:AB26, 2)) + SUMPRODUCT(ROUND(AD26:AG26, 2)) - SUMPRODUCT(ROUND(AH26:AL26, 2)) -> 1803.05 | AN26: =PROYECTADA!P26 -> 9.520476 | AO26: =6%*SUM(Y26:AB26) -> 76.84 | AP26: =PROYECTADA!Q26 -> 8.613764 | AQ26: =PROYECTADA!R26 -> 8.3115267 | AX26: =IF(AND(AM26=AS26,AN26,AT26,AO26,AU26,AP26,AV26,AQ26,AW26),"OK","ERROR") -> ERROR
A27: 21 | B27: Aquino Gomez Carmelo | C27: PRO F | V27: =SUM(L27:Q27) -> 0 | W27: =$AP$3-V27 -> 31 | X27: ='REPORTE DIARIO'!AI27 -> 216 | Y27: =PROYECTADA!G27 -> 0 | Z27: =1130/30*Q27 -> 0 | AA27: =PROYECTADA!D27/$AP$1*PLAME!X27 -> 1167.6667 | AB27: =PROYECTADA!F27/$AP$3*($AP$3-L27) -> 113 | AC27: =SUM(Z27:AB27) -> 1280.6667 | AD27: =6%*AF27 -> 12.801544 | AE27: =((30%*1130)/$AP$3)*($AP$3-L27) -> 339 | AF27: =16.66%*AC27 -> 213.35907 | AG27: =9.72%*AC27 -> 124.4808 | AH27: =IF(OR(D27="SI", C27="SNP"), 0, VLOOKUP(C27, tbl_descuentos[], 2, FALSE) * SUM(Y27:AB27)) -> 21.643267 | AI27: 0 | AJ27: =IF(OR(D27="SI", C27="SNP"), 0, VLOOKUP(C27, tbl_descuentos[], IF(E27 > 65, 4, 3), FALSE) * SUM(Y27:AB27)) -> 17.545133 | AK27: =IF(D27="SI",0,IF(C27="SNP",13%*SUM(Y27:AB27),0)) -> 0 | AL27: =IF(C27="SNP",0,IF(D27="SI",0,10%*(AC27+Y27))) -> 128.06667 | AM27: =SUMPRODUCT(ROUND(Y27:AB27, 2)) + SUMPRODUCT(ROUND(AD27:AG27, 2)) - SUMPRODUCT(ROUND(AH27:AL27, 2)) -> 1803.05 | AN27: =PROYECTADA!P27 -> 9.520476 | AO27: =6%*SUM(Y27:AB27) -> 76.84 | AP27: =PROYECTADA!Q27 -> 8.613764 | AQ27: =PROYECTADA!R27 -> 8.3115267 | AX27: =IF(AND(AM27=AS27,AN27,AT27,AO27,AU27,AP27,AV27,AQ27,AW27),"OK","ERROR") -> ERROR
A28: 22 | B28: Ayamamani Chura Elver Emilio | C28: PRO F | V28: =SUM(F28:U28) -> 0 | W28: =$AP$3-V28 -> 31 | X28: ='REPORTE DIARIO'!AI28 -> 216 | Y28: =PROYECTADA!G28 -> 0 | Z28: =1130/30*Q28 -> 0 | AA28: =PROYECTADA!D28/$AP$1*PLAME!X28 -> 1167.6667 | AB28: =PROYECTADA!F28/$AP$3*($AP$3-L28) -> 113 | AC28: =SUM(Z28:AB28) -> 1280.6667 | AD28: =6%*AF28 -> 12.801544 | AE28: =((30%*1130)/$AP$3)*($AP$3-L28) -> 339 | AF28: =16.66%*AC28 -> 213.35907 | AG28: =9.72%*AC28 -> 124.4808 | AH28: =IF(OR(D28="SI", C28="SNP"), 0, VLOOKUP(C28, tbl_descuentos[], 2, FALSE) * SUM(Y28:AB28)) -> 21.643267 | AI28: 0 | AJ28: =IF(OR(D28="SI", C28="SNP"), 0, VLOOKUP(C28, tbl_descuentos[], IF(E28 > 65, 4, 3), FALSE) * SUM(Y28:AB28)) -> 17.545133 | AK28: =IF(D28="SI",0,IF(C28="SNP",13%*SUM(Y28:AB28),0)) -> 0 | AL28: =IF(C28="SNP",0,IF(D28="SI",0,10%*(AC28+Y28))) -> 128.06667 | AM28: =SUMPRODUCT(ROUND(Y28:AB28, 2)) + SUMPRODUCT(ROUND(AD28:AG28, 2)) - SUMPRODUCT(ROUND(AH28:AL28, 2)) -> 1803.05 | AN28: =PROYECTADA!P28 -> 9.7269182 | AO28: =6%*SUM(Y28:AB28) -> 76.84 | AP28: =PROYECTADA!Q28 -> 8.800545 | AQ28: =PROYECTADA!R28 -> 8.491754 | AX28: =IF(AND(AM28=AS28,AN28,AT28,AO28,AU28,AP28,AV28,AQ28,AW28),"OK","ERROR") -> ERROR
A29: 23 | B29: Cañari Pucho, Guillermo | C29: INT F | V29: =SUM(F29:U29) -> 0 | W29: =$AP$3-V29 -> 31 | X29: ='REPORTE DIARIO'!AI29 -> 208 | Y29: =PROYECTADA!G29 -> 0 | Z29: =1130/30*Q29 -> 0 | AA29: =PROYECTADA!D29/$AP$1*PLAME!X29 -> 1124.4198 | AB29: =PROYECTADA!F29/$AP$3*($AP$3-L29) -> 0 | AC29: =SUM(Z29:AB29) -> 1124.4198 | AD29: =6%*AF29 -> 11.2397 | AE29: =((30%*1130)/$AP$3)*($AP$3-L29) -> 339 | AF29: =16.66%*AC29 -> 187.32833 | AG29: =9.72%*AC29 -> 109.2936 | AH29: =IF(OR(D29="SI", C29="SNP"), 0, VLOOKUP(C29, tbl_descuentos[], 2, FALSE) * SUM(Y29:AB29)) -> 17.428506 | AI29: 0 | AJ29: =IF(OR(D29="SI", C29="SNP"), 0, VLOOKUP(C29, tbl_descuentos[], IF(E29 > 65, 4, 3), FALSE) * SUM(Y29:AB29)) -> 15.404551 | AK29: =IF(D29="SI",0,IF(C29="SNP",13%*SUM(Y29:AB29),0)) -> 0 | AL29: =IF(C29="SNP",0,IF(D29="SI",0,10%*(AC29+Y29))) -> 112.44198 | AM29: =SUMPRODUCT(ROUND(Y29:AB29, 2)) + SUMPRODUCT(ROUND(AD29:AG29, 2)) - SUMPRODUCT(ROUND(AH29:AL29, 2)) -> 1626.01 | AN29: =PROYECTADA!P29 -> 8.680434 | AO29: =6%*SUM(Y29:AB29) -> 67.465185 | AP29: =PROYECTADA!Q29 -> 7.853726 | AQ29: =PROYECTADA!R29 -> 7.5781567 | AX29: =IF(AND(AM29=AS29,AN29,AT29,AO29,AU29,AP29,AV29,AQ29,AW29),"OK","ERROR") -> ERROR
A30: 24 | B30: Ccanchi Neira, Juan Lorenzo | C30: PRO F | V30: =SUM(F30:U30) -> 0 | W30: =$AP$3-V30 -> 31 | X30: ='REPORTE DIARIO'!AI30 -> 216 | Y30: =PROYECTADA!G30 -> 0 | Z30: =1130/30*Q30 -> 0 | AA30: =PROYECTADA!D30/$AP$1*PLAME!X30 -> 1167.6667 | AB30: =PROYECTADA!F30/$AP$3*($AP$3-L30) -> 0 | AC30: =SUM(Z30:AB30) -> 1167.6667 | AD30: =6%*AF30 -> 11.671996 | AE30: =((30%*1130)/$AP$3)*($AP$3-L30) -> 339 | AF30: =16.66%*AC30 -> 194.53327 | AG30: =9.72%*AC30 -> 113.4972 | AH30: =IF(OR(D30="SI", C30="SNP"), 0, VLOOKUP(C30, tbl_descuentos[], 2, FALSE) * SUM(Y30:AB30)) -> 19.733567 | AI30: 0 | AJ30: =IF(OR(D30="SI", C30="SNP"), 0, VLOOKUP(C30, tbl_descuentos[], IF(E30 > 65, 4, 3), FALSE) * SUM(Y30:AB30)) -> 15.997033 | AK30: =IF(D30="SI",0,IF(C30="SNP",13%*SUM(Y30:AB30),0)) -> 0 | AL30: =IF(C30="SNP",0,IF(D30="SI",0,10%*(AC30+Y30))) -> 116.76667 | AM30: =SUMPRODUCT(ROUND(Y30:AB30, 2)) + SUMPRODUCT(ROUND(AD30:AG30, 2)) - SUMPRODUCT(ROUND(AH30:AL30, 2)) -> 1673.87 | AN30: =PROYECTADA!P30 -> 8.680434 | AO30: =6%*SUM(Y30:AB30) -> 70.06 | AP30: =PROYECTADA!Q30 -> 7.853726 | AQ30: =PROYECTADA!R30 -> 7.5781567 | AX30: =IF(AND(AM30=AS30,AN30,AT30,AO30,AU30,AP30,AV30,AQ30,AW30),"OK","ERROR") -> ERROR
A31: 25 | B31: Gamarra Chambi, Ernesto | C31: SNP | V31: =SUM(F31:U31) -> 0 | W31: =$AP$3-V31 -> 31 | X31: ='REPORTE DIARIO'!AI31 -> 216 | Y31: =PROYECTADA!G31 -> 0 | Z31: =1130/30*Q31 -> 0 | AA31: =PROYECTADA!D31/$AP$1*PLAME!X31 -> 1167.6667 | AB31: =PROYECTADA!F31/$AP$3*($AP$3-L31) -> 0 | AC31: =SUM(Z31:AB31) -> 1167.6667 | AD31: =6%*AF31 -> 11.671996 | AE31: =((30%*1130)/$AP$3)*($AP$3-L31) -> 339 | AF31: =16.66%*AC31 -> 194.53327 | AG31: =9.72%*AC31 -> 113.4972 | AH31: =IF(OR(D31="SI", C31="SNP"), 0, VLOOKUP(C31, tbl_descuentos[], 2, FALSE) * SUM(Y31:AB31)) -> 0 | AI31: 0 | AJ31: =IF(OR(D31="SI", C31="SNP"), 0, VLOOKUP(C31, tbl_descuentos[], IF(E31 > 65, 4, 3), FALSE) * SUM(Y31:AB31)) -> 0 | AK31: =IF(D31="SI",0,IF(C31="SNP",13%*SUM(Y31:AB31),0)) -> 151.79667 | AL31: =IF(C31="SNP",0,IF(D31="SI",0,10%*(AC31+Y31))) -> 0 | AM31: =SUMPRODUCT(ROUND(Y31:AB31, 2)) + SUMPRODUCT(ROUND(AD31:AG31, 2)) - SUMPRODUCT(ROUND(AH31:AL31, 2)) -> 1674.57 | AN31: =PROYECTADA!P31 -> 8.680434 | AO31: =6%*SUM(Y31:AB31) -> 70.06 | AP31: =PROYECTADA!Q31 -> 7.853726 | AQ31: =PROYECTADA!R31 -> 7.5781567 | AX31: =IF(AND(AM31=AS31,AN31,AT31,AO31,AU31,AP31,AV31,AQ31,AW31),"OK","ERROR") -> ERROR
A32: 26 | B32: Huaynacho Otazu, Donar | C32: PRO M | V32: =SUM(F32:U32) -> 0 | W32: =$AP$3-V32 -> 31 | X32: ='REPORTE DIARIO'!AI32 -> 216 | Y32: =PROYECTADA!G32 -> 0 | Z32: =1130/30*Q32 -> 0 | AA32: =PROYECTADA!D32/$AP$1*PLAME!X32 -> 1167.6667 | AB32: =PROYECTADA!F32/$AP$3*($AP$3-L32) -> 113 | AC32: =SUM(Z32:AB32) -> 1280.6667 | AD32: =6%*AF32 -> 12.801544 | AE32: =((30%*1130)/$AP$3)*($AP$3-L32) -> 339 | AF32: =16.66%*AC32 -> 213.35907 | AG32: =9.72%*AC32 -> 124.4808 | AH32: =IF(OR(D32="SI", C32="SNP"), 0, VLOOKUP(C32, tbl_descuentos[], 2, FALSE) * SUM(Y32:AB32)) -> 0 | AI32: 0 | AJ32: =IF(OR(D32="SI", C32="SNP"), 0, VLOOKUP(C32, tbl_descuentos[], IF(E32 > 65, 4, 3), FALSE) * SUM(Y32:AB32)) -> 17.545133 | AK32: =IF(D32="SI",0,IF(C32="SNP",13%*SUM(Y32:AB32),0)) -> 0 | AL32: =IF(C32="SNP",0,IF(D32="SI",0,10%*(AC32+Y32))) -> 128.06667 | AM32: =SUMPRODUCT(ROUND(Y32:AB32, 2)) + SUMPRODUCT(ROUND(AD32:AG32, 2)) - SUMPRODUCT(ROUND(AH32:AL32, 2)) -> 1824.69 | AN32: =PROYECTADA!P32 -> 9.520476 | AO32: =6%*SUM(Y32:AB32) -> 76.84 | AP32: =PROYECTADA!Q32 -> 8.613764 | AQ32: =PROYECTADA!R32 -> 8.3115267 | AX32: =IF(AND(AM32=AS32,AN32,AT32,AO32,AU32,AP32,AV32,AQ32,AW32),"OK","ERROR") -> ERROR
A33: 27 | B33: Huaynapata Itusaca Yoni Angel | C33: PRI M | V33: =SUM(F33:U33) -> 0 | W33: =$AP$3-V33 -> 31 | X33: ='REPORTE DIARIO'!AI33 -> 216 | Y33: =PROYECTADA!G33 -> 0 | Z33: =1130/30*Q33 -> 0 | AA33: =PROYECTADA!D33/$AP$1*PLAME!X33 -> 1167.6667 | AB33: =PROYECTADA!F33/$AP$3*($AP$3-L33) -> 113 | AC33: =SUM(Z33:AB33) -> 1280.6667 | AD33: =6%*AF33 -> 12.801544 | AE33: =((30%*1130)/$AP$3)*($AP$3-L33) -> 339 | AF33: =16.66%*AC33 -> 213.35907 | AG33: =9.72%*AC33 -> 124.4808 | AH33: =IF(OR(D33="SI", C33="SNP"), 0, VLOOKUP(C33, tbl_descuentos[], 2, FALSE) * SUM(Y33:AB33)) -> 0 | AI33: 0 | AJ33: =IF(OR(D33="SI", C33="SNP"), 0, VLOOKUP(C33, tbl_descuentos[], IF(E33 > 65, 4, 3), FALSE) * SUM(Y33:AB33)) -> 17.545133 | AK33: =IF(D33="SI",0,IF(C33="SNP",13%*SUM(Y33:AB33),0)) -> 0 | AL33: =IF(C33="SNP",0,IF(D33="SI",0,10%*(AC33+Y33))) -> 128.06667 | AM33: =SUMPRODUCT(ROUND(Y33:AB33, 2)) + SUMPRODUCT(ROUND(AD33:AG33, 2)) - SUMPRODUCT(ROUND(AH33:AL33, 2)) -> 1824.69 | AN33: =PROYECTADA!P33 -> 9.520476 | AO33: =6%*SUM(Y33:AB33) -> 76.84 | AP33: =PROYECTADA!Q33 -> 8.613764 | AQ33: =PROYECTADA!R33 -> 8.3115267 | AX33: =IF(AND(AM33=AS33,AN33,AT33,AO33,AU33,AP33,AV33,AQ33,AW33),"OK","ERROR") -> ERROR
A34: 28 | B34: Idme Huaraccallo, Agustin | C34: PRO F | V34: =SUM(F34:U34) -> 0 | W34: =$AP$3-V34 -> 31 | X34: ='REPORTE DIARIO'!AI34 -> 8 | Y34: =PROYECTADA!G34 -> 0 | Z34: =1130/30*Q34 -> 0 | AA34: =PROYECTADA!D34/$AP$1*PLAME!X34 -> 43.246914 | AB34: =PROYECTADA!F34/$AP$3*($AP$3-L34) -> 0 | AC34: =SUM(Z34:AB34) -> 43.246914 | AD34: =6%*AF34 -> 0.43229615 | AE34: =((30%*1130)/$AP$3)*($AP$3-L34) -> 339 | AF34: =16.66%*AC34 -> 7.2049358 | AG34: =9.72%*AC34 -> 4.2036 | AH34: =IF(OR(D34="SI", C34="SNP"), 0, VLOOKUP(C34, tbl_descuentos[], 2, FALSE) * SUM(Y34:AB34)) -> 0.73087284 | AI34: 0 | AJ34: =IF(OR(D34="SI", C34="SNP"), 0, VLOOKUP(C34, tbl_descuentos[], IF(E34 > 65, 4, 3), FALSE) * SUM(Y34:AB34)) -> 0.59248272 | AK34: =IF(D34="SI",0,IF(C34="SNP",13%*SUM(Y34:AB34),0)) -> 0 | AL34: =IF(C34="SNP",0,IF(D34="SI",0,10%*(AC34+Y34))) -> 4.3246914 | AM34: =SUMPRODUCT(ROUND(Y34:AB34, 2)) + SUMPRODUCT(ROUND(AD34:AG34, 2)) - SUMPRODUCT(ROUND(AH34:AL34, 2)) -> 388.44 | AN34: =PROYECTADA!P34 -> 8.680434 | AO34: =6%*SUM(Y34:AB34) -> 2.5948148 | AP34: =PROYECTADA!Q34 -> 7.853726 | AQ34: =PROYECTADA!R34 -> 7.5781567 | AX34: =IF(AND(AM34=AS34,AN34,AT34,AO34,AU34,AP34,AV34,AQ34,AW34),"OK","ERROR") -> ERROR
A35: 29 | B35: Lope Choquehuanca, Cirilo | C35: PROF | D35: SI | L35: 2 | V35: =SUM(F35:U35) -> 2 | W35: =$AP$3-V35 -> 29 | X35: ='REPORTE DIARIO'!AI35 -> 202 | Y35: =PROYECTADA!G35 -> 0 | Z35: =1130/30*Q35 -> 0 | AA35: =PROYECTADA!D35/$AP$1*PLAME!X35 -> 1091.9846 | AB35: =PROYECTADA!F35/$AP$3*($AP$3-L35) -> 0 | AC35: =SUM(Z35:AB35) -> 1091.9846 | AD35: =6%*AF35 -> 10.915478 | AE35: =((30%*1130)/$AP$3)*($AP$3-L35) -> 317.12903 | AF35: =16.66%*AC35 -> 181.92463 | AG35: =9.72%*AC35 -> 106.1409 | AH35: =IF(OR(D35="SI", C35="SNP"), 0, VLOOKUP(C35, tbl_descuentos[], 2, FALSE) * SUM(Y35:AB35)) -> 0 | AI35: 0 | AJ35: =IF(OR(D35="SI", C35="SNP"), 0, VLOOKUP(C35, tbl_descuentos[], IF(E35 > 65, 4, 3), FALSE) * SUM(Y35:AB35)) -> 0 | AK35: =IF(D35="SI",0,IF(C35="SNP",13%*SUM(Y35:AB35),0)) -> 0 | AL35: =IF(C35="SNP",0,IF(D35="SI",0,10%*(AC35+Y35))) -> 0 | AM35: =SUMPRODUCT(ROUND(Y35:AB35, 2)) + SUMPRODUCT(ROUND(AD35:AG35, 2)) - SUMPRODUCT(ROUND(AH35:AL35, 2)) -> 1708.09 | AN35: =PROYECTADA!P35 -> 8.680434 | AO35: =6%*SUM(Y35:AB35) -> 65.519074 | AP35: =PROYECTADA!Q35 -> 7.853726 | AQ35: =PROYECTADA!R35 -> 7.5781567 | AS35: 1708.09 | AT35: 8.680434 | AU35: 65.519074 | AV35: 7.853726 | AW35: 7.5781567 | AX35: =IF(AND(AM35=AS35,AN35,AT35,AO35,AU35,AP35,AV35,AQ35,AW35),"OK","ERROR") -> OK
A36: 30 | B36: Lope Choquehuanca, Luis | C36: SNP | D36: SI | V36: =SUM(F36:U36) -> 0 | W36: =$AP$3-V36 -> 31 | X36: ='REPORTE DIARIO'!AI36 -> 216 | Y36: =PROYECTADA!G36 -> 0 | Z36: =1130/30*Q36 -> 0 | AA36: =PROYECTADA!D36/$AP$1*PLAME!X36 -> 1167.6667 | AB36: =PROYECTADA!F36/$AP$3*($AP$3-L36) -> 0 | AC36: =SUM(Z36:AB36) -> 1167.6667 | AD36: =6%*AF36 -> 11.671996 | AE36: =((30%*1130)/$AP$3)*($AP$3-L36) -> 339 | AF36: =16.66%*AC36 -> 194.53327 | AG36: =9.72%*AC36 -> 113.4972 | AH36: =IF(OR(D36="SI", C36="SNP"), 0, VLOOKUP(C36, tbl_descuentos[], 2, FALSE) * SUM(Y36:AB36)) -> 0 | AI36: 0 | AJ36: =IF(OR(D36="SI", C36="SNP"), 0, VLOOKUP(C36, tbl_descuentos[], IF(E36 > 65, 4, 3), FALSE) * SUM(Y36:AB36)) -> 0 | AK36: =IF(D36="SI",0,IF(C36="SNP",13%*SUM(Y36:AB36),0)) -> 0 | AL36: =IF(C36="SNP",0,IF(D36="SI",0,10%*(AC36+Y36))) -> 0 | AM36: =SUMPRODUCT(ROUND(Y36:AB36, 2)) + SUMPRODUCT(ROUND(AD36:AG36, 2)) - SUMPRODUCT(ROUND(AH36:AL36, 2)) -> 1826.37 | AN36: =PROYECTADA!P36 -> 8.680434 | AO36: =6%*SUM(Y36:AB36) -> 70.06 | AP36: =PROYECTADA!Q36 -> 7.853726 | AQ36: =PROYECTADA!R36 -> 7.5781567 | AS36: 1826.37 | AT36: 8.680434 | AU36: 70.06 | AV36: 7.853726 | AW36: 7.5781567 | AX36: =IF(AND(AM36=AS36,AN36,AT36,AO36,AU36,AP36,AV36,AQ36,AW36),"OK","ERROR") -> OK
A37: 31 | B37: Lopez Mamani, Nestor | C37: SNP | V37: =SUM(F37:U37) -> 0 | W37: =$AP$3-V37 -> 31 | X37: ='REPORTE DIARIO'!AI37 -> 216 | Y37: =PROYECTADA!G37 -> 0 | Z37: =1130/30*Q37 -> 0 | AA37: =PROYECTADA!D37/$AP$1*PLAME!X37 -> 1167.6667 | AB37: =PROYECTADA!F37/$AP$3*($AP$3-L37) -> 113 | AC37: =SUM(Z37:AB37) -> 1280.6667 | AD37: =6%*AF37 -> 12.801544 | AE37: =((30%*1130)/$AP$3)*($AP$3-L37) -> 339 | AF37: =16.66%*AC37 -> 213.35907 | AG37: =9.72%*AC37 -> 124.4808 | AH37: =IF(OR(D37="SI", C37="SNP"), 0, VLOOKUP(C37, tbl_descuentos[], 2, FALSE) * SUM(Y37:AB37)) -> 0 | AI37: 0 | AJ37: =IF(OR(D37="SI", C37="SNP"), 0, VLOOKUP(C37, tbl_descuentos[], IF(E37 > 65, 4, 3), FALSE) * SUM(Y37:AB37)) -> 0 | AK37: =IF(D37="SI",0,IF(C37="SNP",13%*SUM(Y37:AB37),0)) -> 166.48667 | AL37: =IF(C37="SNP",0,IF(D37="SI",0,10%*(AC37+Y37))) -> 0 | AM37: =SUMPRODUCT(ROUND(Y37:AB37, 2)) + SUMPRODUCT(ROUND(AD37:AG37, 2)) - SUMPRODUCT(ROUND(AH37:AL37, 2)) -> 1803.82 | AN37: =PROYECTADA!P37 -> 9.520476 | AO37: =6%*SUM(Y37:AB37) -> 76.84 | AP37: =PROYECTADA!Q37 -> 8.613764 | AQ37: =PROYECTADA!R37 -> 8.3115267 | AS37: 1803.82 | AT37: 9.520476 | AU37: 76.84 | AV37: 8.613764 | AW37: 8.3115267 | AX37: =IF(AND(AM37=AS37,AN37,AT37,AO37,AU37,AP37,AV37,AQ37,AW37),"OK","ERROR") -> OK
A38: 32 | B38: Mamani Anconaira, Santo Domingo | C38: SNP | V38: =SUM(F38:U38) -> 0 | W38: =$AP$3-V38 -> 31 | X38: ='REPORTE DIARIO'!AI38 -> 216 | Y38: =PROYECTADA!G38 -> 0 | Z38: =1130/30*Q38 -> 0 | AA38: =PROYECTADA!D38/$AP$1*PLAME!X38 -> 1167.6667 | AB38: =PROYECTADA!F38/$AP$3*($AP$3-L38) -> 113 | AC38: =SUM(Z38:AB38) -> 1280.6667 | AD38: =6%*AF38 -> 12.801544 | AE38: =((30%*1130)/$AP$3)*($AP$3-L38) -> 339 | AF38: =16.66%*AC38 -> 213.35907 | AG38: =9.72%*AC38 -> 124.4808 | AH38: =IF(OR(D38="SI", C38="SNP"), 0, VLOOKUP(C38, tbl_descuentos[], 2, FALSE) * SUM(Y38:AB38)) -> 0 | AI38: 0 | AJ38: =IF(OR(D38="SI", C38="SNP"), 0, VLOOKUP(C38, tbl_descuentos[], IF(E38 > 65, 4, 3), FALSE) * SUM(Y38:AB38)) -> 0 | AK38: =IF(D38="SI",0,IF(C38="SNP",13%*SUM(Y38:AB38),0)) -> 166.48667 | AL38: =IF(C38="SNP",0,IF(D38="SI",0,10%*(AC38+Y38))) -> 0 | AM38: =SUMPRODUCT(ROUND(Y38:AB38, 2)) + SUMPRODUCT(ROUND(AD38:AG38, 2)) - SUMPRODUCT(ROUND(AH38:AL38, 2)) -> 1803.82 | AN38: =PROYECTADA!P38 -> 9.520476 | AO38: =6%*SUM(Y38:AB38) -> 76.84 | AP38: =PROYECTADA!Q38 -> 8.613764 | AQ38: =PROYECTADA!R38 -> 8.3115267 | AX38: =IF(AND(AM38=AS38,AN38,AT38,AO38,AU38,AP38,AV38,AQ38,AW38),"OK","ERROR") -> ERROR
A39: 33 | B39: Mamani Idme, Vicente | C39: PRO F | V39: =SUM(F39:U39) -> 0 | W39: =$AP$3-V39 -> 31 | X39: ='REPORTE DIARIO'!AI39 -> 216 | Y39: =PROYECTADA!G39 -> 0 | Z39: =1130/30*Q39 -> 0 | AA39: =PROYECTADA!D39/$AP$1*PLAME!X39 -> 1167.6667 | AB39: =PROYECTADA!F39/$AP$3*($AP$3-L39) -> 113 | AC39: =SUM(Z39:AB39) -> 1280.6667 | AD39: =6%*AF39 -> 12.801544 | AE39: =((30%*1130)/$AP$3)*($AP$3-L39) -> 339 | AF39: =16.66%*AC39 -> 213.35907 | AG39: =9.72%*AC39 -> 124.4808 | AH39: =IF(OR(D39="SI", C39="SNP"), 0, VLOOKUP(C39, tbl_descuentos[], 2, FALSE) * SUM(Y39:AB39)) -> 21.643267 | AI39: 0 | AJ39: =IF(OR(D39="SI", C39="SNP"), 0, VLOOKUP(C39, tbl_descuentos[], IF(E39 > 65, 4, 3), FALSE) * SUM(Y39:AB39)) -> 17.545133 | AK39: =IF(D39="SI",0,IF(C39="SNP",13%*SUM(Y39:AB39),0)) -> 0 | AL39: =IF(C39="SNP",0,IF(D39="SI",0,10%*(AC39+Y39))) -> 128.06667 | AM39: =SUMPRODUCT(ROUND(Y39:AB39, 2)) + SUMPRODUCT(ROUND(AD39:AG39, 2)) - SUMPRODUCT(ROUND(AH39:AL39, 2)) -> 1803.05 | AN39: =PROYECTADA!P39 -> 10.31517 | AO39: =6%*SUM(Y39:AB39) -> 76.84 | AP39: =PROYECTADA!Q39 -> 9.3327727 | AQ39: =PROYECTADA!R39 -> 9.005307 | AX39: =IF(AND(AM39=AS39,AN39,AT39,AO39,AU39,AP39,AV39,AQ39,AW39),"OK","ERROR") -> ERROR
A40: 34 | B40: Mamani Mamani, Alejandro | C40: PRO M | V40: =SUM(F40:U40) -> 0 | W40: =$AP$3-V40 -> 31 | X40: ='REPORTE DIARIO'!AI40 -> 216 | Y40: =PROYECTADA!G40 -> 0 | Z40: =1130/30*Q40 -> 0 | AA40: =PROYECTADA!D40/$AP$1*PLAME!X40 -> 1167.6667 | AB40: =PROYECTADA!F40/$AP$3*($AP$3-L40) -> 0 | AC40: =SUM(Z40:AB40) -> 1167.6667 | AD40: =6%*AF40 -> 11.671996 | AE40: =((30%*1130)/$AP$3)*($AP$3-L40) -> 339 | AF40: =16.66%*AC40 -> 194.53327 | AG40: =9.72%*AC40 -> 113.4972 | AH40: =IF(OR(D40="SI", C40="SNP"), 0, VLOOKUP(C40, tbl_descuentos[], 2, FALSE) * SUM(Y40:AB40)) -> 0 | AI40: 0 | AJ40: =IF(OR(D40="SI", C40="SNP"), 0, VLOOKUP(C40, tbl_descuentos[], IF(E40 > 65, 4, 3), FALSE) * SUM(Y40:AB40)) -> 15.997033 | AK40: =IF(D40="SI",0,IF(C40="SNP",13%*SUM(Y40:AB40),0)) -> 0 | AL40: =IF(C40="SNP",0,IF(D40="SI",0,10%*(AC40+Y40))) -> 116.76667 | AM40: =SUMPRODUCT(ROUND(Y40:AB40, 2)) + SUMPRODUCT(ROUND(AD40:AG40, 2)) - SUMPRODUCT(ROUND(AH40:AL40, 2)) -> 1693.6 | AN40: =PROYECTADA!P40 -> 8.680434 | AO40: =6%*SUM(Y40:AB40) -> 70.06 | AP40: =PROYECTADA!Q40 -> 7.853726 | AQ40: =PROYECTADA!R40 -> 7.5781567 | AX40: =IF(AND(AM40=AS40,AN40,AT40,AO40,AU40,AP40,AV40,AQ40,AW40),"OK","ERROR") -> ERROR
A41: 35 | B41: Palaco Retamozo Alberto Gilberto | C41: PRO F | V41: =SUM(F41:U41) -> 0 | W41: =$AP$3-V41 -> 31 | X41: ='REPORTE DIARIO'!AI41 -> 216 | Y41: =PROYECTADA!G41 -> 0 | Z41: =1130/30*Q41 -> 0 | AA41: =PROYECTADA!D41/$AP$1*PLAME!X41 -> 1167.6667 | AB41: =PROYECTADA!F41/$AP$3*($AP$3-L41) -> 113 | AC41: =SUM(Z41:AB41) -> 1280.6667 | AD41: =6%*AF41 -> 12.801544 | AE41: =((30%*1130)/$AP$3)*($AP$3-L41) -> 339 | AF41: =16.66%*AC41 -> 213.35907 | AG41: =9.72%*AC41 -> 124.4808 | AH41: =IF(OR(D41="SI", C41="SNP"), 0, VLOOKUP(C41, tbl_descuentos[], 2, FALSE) * SUM(Y41:AB41)) -> 21.643267 | AI41: 0 | AJ41: =IF(OR(D41="SI", C41="SNP"), 0, VLOOKUP(C41, tbl_descuentos[], IF(E41 > 65, 4, 3), FALSE) * SUM(Y41:AB41)) -> 17.545133 | AK41: =IF(D41="SI",0,IF(C41="SNP",13%*SUM(Y41:AB41),0)) -> 0 | AL41: =IF(C41="SNP",0,IF(D41="SI",0,10%*(AC41+Y41))) -> 128.06667 | AM41: =SUMPRODUCT(ROUND(Y41:AB41, 2)) + SUMPRODUCT(ROUND(AD41:AG41, 2)) - SUMPRODUCT(ROUND(AH41:AL41, 2)) -> 1803.05 | AN41: =PROYECTADA!P41 -> 9.520476 | AO41: =6%*SUM(Y41:AB41) -> 76.84 | AP41: =PROYECTADA!Q41 -> 8.613764 | AQ41: =PROYECTADA!R41 -> 8.3115267 | AX41: =IF(AND(AM41=AS41,AN41,AT41,AO41,AU41,AP41,AV41,AQ41,AW41),"OK","ERROR") -> ERROR
A42: 36 | B42: Perca Mamani Julio Alberto | C42: INT M | V42: =SUM(F42:U42) -> 0 | W42: =$AP$3-V42 -> 31 | X42: ='REPORTE DIARIO'!AI42 -> 216 | Y42: =PROYECTADA!G42 -> 0 | Z42: =1130/30*Q42 -> 0 | AA42: =PROYECTADA!D42/$AP$1*PLAME!X42 -> 1167.6667 | AB42: =PROYECTADA!F42/$AP$3*($AP$3-L42) -> 0 | AC42: =SUM(Z42:AB42) -> 1167.6667 | AD42: =6%*AF42 -> 11.671996 | AE42: =((30%*1130)/$AP$3)*($AP$3-L42) -> 339 | AF42: =16.66%*AC42 -> 194.53327 | AG42: =9.72%*AC42 -> 113.4972 | AH42: =IF(OR(D42="SI", C42="SNP"), 0, VLOOKUP(C42, tbl_descuentos[], 2, FALSE) * SUM(Y42:AB42)) -> 0 | AI42: 0 | AJ42: =IF(OR(D42="SI", C42="SNP"), 0, VLOOKUP(C42, tbl_descuentos[], IF(E42 > 65, 4, 3), FALSE) * SUM(Y42:AB42)) -> 15.997033 | AK42: =IF(D42="SI",0,IF(C42="SNP",13%*SUM(Y42:AB42),0)) -> 0 | AL42: =IF(C42="SNP",0,IF(D42="SI",0,10%*(AC42+Y42))) -> 116.76667 | AM42: =SUMPRODUCT(ROUND(Y42:AB42, 2)) + SUMPRODUCT(ROUND(AD42:AG42, 2)) - SUMPRODUCT(ROUND(AH42:AL42, 2)) -> 1693.6 | AN42: =PROYECTADA!P42 -> 8.680434 | AO42: =6%*SUM(Y42:AB42) -> 70.06 | AP42: =PROYECTADA!Q42 -> 7.853726 | AQ42: =PROYECTADA!R42 -> 7.5781567 | AX42: =IF(AND(AM42=AS42,AN42,AT42,AO42,AU42,AP42,AV42,AQ42,AW42),"OK","ERROR") -> ERROR
A43: 37 | B43: Quispe Belizario Alvaro | C43: PRI M | V43: =SUM(F43:U43) -> 0 | W43: =$AP$3-V43 -> 31 | X43: ='REPORTE DIARIO'!AI43 -> 216 | Y43: =PROYECTADA!G43 -> 0 | Z43: =1130/30*Q43 -> 0 | AA43: =PROYECTADA!D43/$AP$1*PLAME!X43 -> 1167.6667 | AB43: =PROYECTADA!F43/$AP$3*($AP$3-L43) -> 0 | AC43: =SUM(Z43:AB43) -> 1167.6667 | AD43: =6%*AF43 -> 11.671996 | AE43: =((30%*1130)/$AP$3)*($AP$3-L43) -> 339 | AF43: =16.66%*AC43 -> 194.53327 | AG43: =9.72%*AC43 -> 113.4972 | AH43: =IF(OR(D43="SI", C43="SNP"), 0, VLOOKUP(C43, tbl_descuentos[], 2, FALSE) * SUM(Y43:AB43)) -> 0 | AI43: 0 | AJ43: =IF(OR(D43="SI", C43="SNP"), 0, VLOOKUP(C43, tbl_descuentos[], IF(E43 > 65, 4, 3), FALSE) * SUM(Y43:AB43)) -> 15.997033 | AK43: =IF(D43="SI",0,IF(C43="SNP",13%*SUM(Y43:AB43),0)) -> 0 | AL43: =IF(C43="SNP",0,IF(D43="SI",0,10%*(AC43+Y43))) -> 116.76667 | AM43: =SUMPRODUCT(ROUND(Y43:AB43, 2)) + SUMPRODUCT(ROUND(AD43:AG43, 2)) - SUMPRODUCT(ROUND(AH43:AL43, 2)) -> 1693.6 | AN43: =PROYECTADA!P43 -> 8.680434 | AO43: =6%*SUM(Y43:AB43) -> 70.06 | AP43: =PROYECTADA!Q43 -> 7.853726 | AQ43: =PROYECTADA!R43 -> 7.5781567 | AX43: =IF(AND(AM43=AS43,AN43,AT43,AO43,AU43,AP43,AV43,AQ43,AW43),"OK","ERROR") -> ERROR
A44: 38 | B44: Quispe Quispe Luis | C44: PRO F | V44: =SUM(F44:U44) -> 0 | W44: =$AP$3-V44 -> 31 | X44: ='REPORTE DIARIO'!AI44 -> 216 | Y44: =PROYECTADA!G44 -> 0 | Z44: =1130/30*Q44 -> 0 | AA44: =PROYECTADA!D44/$AP$1*PLAME!X44 -> 1167.6667 | AB44: =PROYECTADA!F44/$AP$3*($AP$3-L44) -> 0 | AC44: =SUM(Z44:AB44) -> 1167.6667 | AD44: =6%*AF44 -> 11.671996 | AE44: =((30%*1130)/$AP$3)*($AP$3-L44) -> 339 | AF44: =16.66%*AC44 -> 194.53327 | AG44: =9.72%*AC44 -> 113.4972 | AH44: =IF(OR(D44="SI", C44="SNP"), 0, VLOOKUP(C44, tbl_descuentos[], 2, FALSE) * SUM(Y44:AB44)) -> 19.733567 | AI44: 0 | AJ44: =IF(OR(D44="SI", C44="SNP"), 0, VLOOKUP(C44, tbl_descuentos[], IF(E44 > 65, 4, 3), FALSE) * SUM(Y44:AB44)) -> 15.997033 | AK44: =IF(D44="SI",0,IF(C44="SNP",13%*SUM(Y44:AB44),0)) -> 0 | AL44: =IF(C44="SNP",0,IF(D44="SI",0,10%*(AC44+Y44))) -> 116.76667 | AM44: =SUMPRODUCT(ROUND(Y44:AB44, 2)) + SUMPRODUCT(ROUND(AD44:AG44, 2)) - SUMPRODUCT(ROUND(AH44:AL44, 2)) -> 1673.87 | AN44: =PROYECTADA!P44 -> 8.680434 | AO44: =6%*SUM(Y44:AB44) -> 70.06 | AP44: =PROYECTADA!Q44 -> 7.853726 | AQ44: =PROYECTADA!R44 -> 7.5781567 | AX44: =IF(AND(AM44=AS44,AN44,AT44,AO44,AU44,AP44,AV44,AQ44,AW44),"OK","ERROR") -> ERROR
A45: 39 | B45: Reynoso Gamero Rufino | C45: PRO F | V45: =SUM(F45:U45) -> 0 | W45: =$AP$3-V45 -> 31 | X45: ='REPORTE DIARIO'!AI45 -> 207 | Y45: =PROYECTADA!G45 -> 0 | Z45: =1130/30*Q45 -> 0 | AA45: =PROYECTADA!D45/$AP$1*PLAME!X45 -> 1119.0139 | AB45: =PROYECTADA!F45/$AP$3*($AP$3-L45) -> 0 | AC45: =SUM(Z45:AB45) -> 1119.0139 | AD45: =6%*AF45 -> 11.185663 | AE45: =((30%*1130)/$AP$3)*($AP$3-L45) -> 339 | AF45: =16.66%*AC45 -> 186.42771 | AG45: =9.72%*AC45 -> 108.76815 | AH45: =IF(OR(D45="SI", C45="SNP"), 0, VLOOKUP(C45, tbl_descuentos[], 2, FALSE) * SUM(Y45:AB45)) -> 18.911335 | AI45: 0 | AJ45: =IF(OR(D45="SI", C45="SNP"), 0, VLOOKUP(C45, tbl_descuentos[], IF(E45 > 65, 4, 3), FALSE) * SUM(Y45:AB45)) -> 15.33049 | AK45: =IF(D45="SI",0,IF(C45="SNP",13%*SUM(Y45:AB45),0)) -> 0 | AL45: =IF(C45="SNP",0,IF(D45="SI",0,10%*(AC45+Y45))) -> 111.90139 | AM45: =SUMPRODUCT(ROUND(Y45:AB45, 2)) + SUMPRODUCT(ROUND(AD45:AG45, 2)) - SUMPRODUCT(ROUND(AH45:AL45, 2)) -> 1618.26 | AN45: =PROYECTADA!P45 -> 8.680434 | AO45: =6%*SUM(Y45:AB45) -> 67.140833 | AP45: =PROYECTADA!Q45 -> 7.853726 | AQ45: =PROYECTADA!R45 -> 7.5781567 | AX45: =IF(AND(AM45=AS45,AN45,AT45,AO45,AU45,AP45,AV45,AQ45,AW45),"OK","ERROR") -> ERROR
A46: 40 | B46: Rivera Ramos Elmer Delis | C46: INT F | V46: =SUM(F46:U46) -> 0 | W46: =$AP$3-V46 -> 31 | X46: ='REPORTE DIARIO'!AI46 -> 216 | Y46: =PROYECTADA!G46 -> 0 | Z46: =1130/30*Q46 -> 0 | AA46: =PROYECTADA!D46/$AP$1*PLAME!X46 -> 1167.6667 | AB46: =PROYECTADA!F46/$AP$3*($AP$3-L46) -> 113 | AC46: =SUM(Z46:AB46) -> 1280.6667 | AD46: =6%*AF46 -> 12.801544 | AE46: =((30%*1130)/$AP$3)*($AP$3-L46) -> 339 | AF46: =16.66%*AC46 -> 213.35907 | AG46: =9.72%*AC46 -> 124.4808 | AH46: =IF(OR(D46="SI", C46="SNP"), 0, VLOOKUP(C46, tbl_descuentos[], 2, FALSE) * SUM(Y46:AB46)) -> 19.850333 | AI46: 0 | AJ46: =IF(OR(D46="SI", C46="SNP"), 0, VLOOKUP(C46, tbl_descuentos[], IF(E46 > 65, 4, 3), FALSE) * SUM(Y46:AB46)) -> 17.545133 | AK46: =IF(D46="SI",0,IF(C46="SNP",13%*SUM(Y46:AB46),0)) -> 0 | AL46: =IF(C46="SNP",0,IF(D46="SI",0,10%*(AC46+Y46))) -> 128.06667 | AM46: =SUMPRODUCT(ROUND(Y46:AB46, 2)) + SUMPRODUCT(ROUND(AD46:AG46, 2)) - SUMPRODUCT(ROUND(AH46:AL46, 2)) -> 1804.84 | AN46: =PROYECTADA!P46 -> 9.520476 | AO46: =6%*SUM(Y46:AB46) -> 76.84 | AP46: =PROYECTADA!Q46 -> 8.613764 | AQ46: =PROYECTADA!R46 -> 8.3115267 | AX46: =IF(AND(AM46=AS46,AN46,AT46,AO46,AU46,AP46,AV46,AQ46,AW46),"OK","ERROR") -> ERROR
A47: 41 | B47: Soncco Soncco, Santos Evaristo | C47: PRO F | E47: 66 | V47: =SUM(F47:U47) -> 0 | W47: =$AP$3-V47 -> 31 | X47: ='REPORTE DIARIO'!AI47 -> 216 | Y47: =PROYECTADA!G47 -> 0 | Z47: =1130/30*Q47 -> 0 | AA47: =PROYECTADA!D47/$AP$1*PLAME!X47 -> 1167.6667 | AB47: =PROYECTADA!F47/$AP$3*($AP$3-L47) -> 0 | AC47: =SUM(Z47:AB47) -> 1167.6667 | AD47: =6%*AF47 -> 11.671996 | AE47: =((30%*1130)/$AP$3)*($AP$3-L47) -> 339 | AF47: =16.66%*AC47 -> 194.53327 | AG47: =9.72%*AC47 -> 113.4972 | AH47: =IF(OR(D47="SI", C47="SNP"), 0, VLOOKUP(C47, tbl_descuentos[], 2, FALSE) * SUM(Y47:AB47)) -> 19.733567 | AI47: 0 | AJ47: =IF(OR(D47="SI", C47="SNP"), 0, VLOOKUP(C47, tbl_descuentos[], IF(E47 > 65, 4, 3), FALSE) * SUM(Y47:AB47)) -> 0 | AK47: =IF(D47="SI",0,IF(C47="SNP",13%*SUM(Y47:AB47),0)) -> 0 | AL47: =IF(C47="SNP",0,IF(D47="SI",0,10%*(AC47+Y47))) -> 116.76667 | AM47: =SUMPRODUCT(ROUND(Y47:AB47, 2)) + SUMPRODUCT(ROUND(AD47:AG47, 2)) - SUMPRODUCT(ROUND(AH47:AL47, 2)) -> 1689.87 | AN47: =PROYECTADA!P47 -> 8.680434 | AO47: =6%*SUM(Y47:AB47) -> 70.06 | AP47: =PROYECTADA!Q47 -> 7.853726 | AQ47: =PROYECTADA!R47 -> 7.5781567 | AS47: 1689.87 | AT47: 8.680434 | AU47: 70.06 | AV47: 7.853726 | AW47: 7.5781567 | AX47: =IF(AND(AM47=AS47,AN47,AT47,AO47,AU47,AP47,AV47,AQ47,AW47),"OK","ERROR") -> OK
A48: 42 | B48: Ttito Tapara, Jose Pascual | C48: SNP | V48: =SUM(F48:U48) -> 0 | W48: =$AP$3-V48 -> 31 | X48: ='REPORTE DIARIO'!AI48 -> 216 | Y48: =PROYECTADA!G48 -> 0 | Z48: =1130/30*Q48 -> 0 | AA48: =PROYECTADA!D48/$AP$1*PLAME!X48 -> 1167.6667 | AB48: =PROYECTADA!F48/$AP$3*($AP$3-L48) -> 113 | AC48: =SUM(Z48:AB48) -> 1280.6667 | AD48: =6%*AF48 -> 12.801544 | AE48: =((30%*1130)/$AP$3)*($AP$3-L48) -> 339 | AF48: =16.66%*AC48 -> 213.35907 | AG48: =9.72%*AC48 -> 124.4808 | AH48: =IF(OR(D48="SI", C48="SNP"), 0, VLOOKUP(C48, tbl_descuentos[], 2, FALSE) * SUM(Y48:AB48)) -> 0 | AI48: 0 | AJ48: =IF(OR(D48="SI", C48="SNP"), 0, VLOOKUP(C48, tbl_descuentos[], IF(E48 > 65, 4, 3), FALSE) * SUM(Y48:AB48)) -> 0 | AK48: =IF(D48="SI",0,IF(C48="SNP",13%*SUM(Y48:AB48),0)) -> 166.48667 | AL48: =IF(C48="SNP",0,IF(D48="SI",0,10%*(AC48+Y48))) -> 0 | AM48: =SUMPRODUCT(ROUND(Y48:AB48, 2)) + SUMPRODUCT(ROUND(AD48:AG48, 2)) - SUMPRODUCT(ROUND(AH48:AL48, 2)) -> 1803.82 | AN48: =PROYECTADA!P48 -> 9.520476 | AO48: =6%*SUM(Y48:AB48) -> 76.84 | AP48: =PROYECTADA!Q48 -> 8.613764 | AQ48: =PROYECTADA!R48 -> 8.3115267 | AX48: =IF(AND(AM48=AS48,AN48,AT48,AO48,AU48,AP48,AV48,AQ48,AW48),"OK","ERROR") -> ERROR
A49: 43 | B49: Turpo Quispe Yury | C49: INT M | V49: =SUM(F49:U49) -> 0 | W49: =$AP$3-V49 -> 31 | X49: ='REPORTE DIARIO'!AI49 -> 216 | Y49: =PROYECTADA!G49 -> 0 | Z49: =1130/30*Q49 -> 0 | AA49: =PROYECTADA!D49/$AP$1*PLAME!X49 -> 1167.6667 | AB49: =PROYECTADA!F49/$AP$3*($AP$3-L49) -> 113 | AC49: =SUM(Z49:AB49) -> 1280.6667 | AD49: =6%*AF49 -> 12.801544 | AE49: =((30%*1130)/$AP$3)*($AP$3-L49) -> 339 | AF49: =16.66%*AC49 -> 213.35907 | AG49: =9.72%*AC49 -> 124.4808 | AH49: =IF(OR(D49="SI", C49="SNP"), 0, VLOOKUP(C49, tbl_descuentos[], 2, FALSE) * SUM(Y49:AB49)) -> 0 | AI49: 0 | AJ49: =IF(OR(D49="SI", C49="SNP"), 0, VLOOKUP(C49, tbl_descuentos[], IF(E49 > 65, 4, 3), FALSE) * SUM(Y49:AB49)) -> 17.545133 | AK49: =IF(D49="SI",0,IF(C49="SNP",13%*SUM(Y49:AB49),0)) -> 0 | AL49: =IF(C49="SNP",0,IF(D49="SI",0,10%*(AC49+Y49))) -> 128.06667 | AM49: =SUMPRODUCT(ROUND(Y49:AB49, 2)) + SUMPRODUCT(ROUND(AD49:AG49, 2)) - SUMPRODUCT(ROUND(AH49:AL49, 2)) -> 1824.69 | AN49: =PROYECTADA!P49 -> 9.520476 | AO49: =6%*SUM(Y49:AB49) -> 76.84 | AP49: =PROYECTADA!Q49 -> 8.613764 | AQ49: =PROYECTADA!R49 -> 8.3115267 | AX49: =IF(AND(AM49=AS49,AN49,AT49,AO49,AU49,AP49,AV49,AQ49,AW49),"OK","ERROR") -> ERROR
A50: 44 | B50: Zea Mamani, Ignacio | C50: PRO F | V50: =SUM(F50:U50) -> 0 | W50: =$AP$3-V50 -> 31 | X50: ='REPORTE DIARIO'!AI50 -> 216 | Y50: =PROYECTADA!G50 -> 0 | Z50: =1130/30*Q50 -> 0 | AA50: =PROYECTADA!D50/$AP$1*PLAME!X50 -> 1167.6667 | AB50: =PROYECTADA!F50/$AP$3*($AP$3-L50) -> 113 | AC50: =SUM(Z50:AB50) -> 1280.6667 | AD50: =6%*AF50 -> 12.801544 | AE50: =((30%*1130)/$AP$3)*($AP$3-L50) -> 339 | AF50: =16.66%*AC50 -> 213.35907 | AG50: =9.72%*AC50 -> 124.4808 | AH50: =IF(OR(D50="SI", C50="SNP"), 0, VLOOKUP(C50, tbl_descuentos[], 2, FALSE) * SUM(Y50:AB50)) -> 21.643267 | AI50: 0 | AJ50: =IF(OR(D50="SI", C50="SNP"), 0, VLOOKUP(C50, tbl_descuentos[], IF(E50 > 65, 4, 3), FALSE) * SUM(Y50:AB50)) -> 17.545133 | AK50: =IF(D50="SI",0,IF(C50="SNP",13%*SUM(Y50:AB50),0)) -> 0 | AL50: =IF(C50="SNP",0,IF(D50="SI",0,10%*(AC50+Y50))) -> 128.06667 | AM50: =SUMPRODUCT(ROUND(Y50:AB50, 2)) + SUMPRODUCT(ROUND(AD50:AG50, 2)) - SUMPRODUCT(ROUND(AH50:AL50, 2)) -> 1803.05 | AN50: =PROYECTADA!P50 -> 9.520476 | AO50: =6%*SUM(Y50:AB50) -> 76.84 | AP50: =PROYECTADA!Q50 -> 8.613764 | AQ50: =PROYECTADA!R50 -> 8.3115267 | AX50: =IF(AND(AM50=AS50,AN50,AT50,AO50,AU50,AP50,AV50,AQ50,AW50),"OK","ERROR") -> ERROR
A51: 45 | B51: Chile Yareta Justino | C51: INT M | L51: 10 | V51: =SUM(F51:U51) -> 10 | W51: =$AP$3-V51 -> 21 | X51: ='REPORTE DIARIO'!AI51 -> 153 | Y51: =PROYECTADA!G51 -> 103.58 | Z51: =1130/30*Q51 -> 0 | AA51: =PROYECTADA!D51/$AP$1*PLAME!X51 -> 827.09722 | AB51: =PROYECTADA!F51/$AP$3*($AP$3-L51) -> 76.548387 | AC51: =SUM(Z51:AB51) -> 903.64561 | AD51: =6%*AF51 -> 9.0328415 | AE51: =((30%*1130)/$AP$3)*($AP$3-L51) -> 229.64516 | AF51: =16.66%*AC51 -> 150.54736 | AG51: =9.72%*AC51 -> 87.834353 | AH51: =IF(OR(D51="SI", C51="SNP"), 0, VLOOKUP(C51, tbl_descuentos[], 2, FALSE) * SUM(Y51:AB51)) -> 0 | AI51: 0 | AJ51: =IF(OR(D51="SI", C51="SNP"), 0, VLOOKUP(C51, tbl_descuentos[], IF(E51 > 65, 4, 3), FALSE) * SUM(Y51:AB51)) -> 13.798991 | AK51: =IF(D51="SI",0,IF(C51="SNP",13%*SUM(Y51:AB51),0)) -> 0 | AL51: =IF(C51="SNP",0,IF(D51="SI",0,10%*(AC51+Y51))) -> 100.72256 | AM51: =SUMPRODUCT(ROUND(Y51:AB51, 2)) + SUMPRODUCT(ROUND(AD51:AG51, 2)) - SUMPRODUCT(ROUND(AH51:AL51, 2)) -> 1369.77 | AN51: =PROYECTADA!P51 -> 10.29049 | AO51: =6%*SUM(Y51:AB51) -> 60.433537 | AP51: =PROYECTADA!Q51 -> 9.3104431 | AQ51: =PROYECTADA!R51 -> 8.9837609 | AS51: 1369.77 | AT51: 10.29049 | AU51: 60.433537 | AV51: 9.3104431 | AW51: 8.9837609 | AX51: =IF(AND(AM51=AS51,AN51,AT51,AO51,AU51,AP51,AV51,AQ51,AW51),"OK","ERROR") -> OK
A52: 46 | B52: Diaz Chipana Walter | C52: INT M | V52: =SUM(F52:U52) -> 0 | W52: =$AP$3-V52 -> 31 | X52: ='REPORTE DIARIO'!AI52 -> 108.5 | Y52: =PROYECTADA!G52 -> 0 | Z52: =1130/30*Q52 -> 0 | AA52: =PROYECTADA!D52/$AP$1*PLAME!X52 -> 586.53627 | AB52: =PROYECTADA!F52/$AP$3*($AP$3-L52) -> 0 | AC52: =SUM(Z52:AB52) -> 586.53627 | AD52: =6%*AF52 -> 5.8630165 | AE52: =((30%*1130)/$AP$3)*($AP$3-L52) -> 339 | AF52: =16.66%*AC52 -> 97.716942 | AG52: =9.72%*AC52 -> 57.011325 | AH52: =IF(OR(D52="SI", C52="SNP"), 0, VLOOKUP(C52, tbl_descuentos[], 2, FALSE) * SUM(Y52:AB52)) -> 0 | AI52: 0 | AJ52: =IF(OR(D52="SI", C52="SNP"), 0, VLOOKUP(C52, tbl_descuentos[], IF(E52 > 65, 4, 3), FALSE) * SUM(Y52:AB52)) -> 8.0355468 | AK52: =IF(D52="SI",0,IF(C52="SNP",13%*SUM(Y52:AB52),0)) -> 0 | AL52: =IF(C52="SNP",0,IF(D52="SI",0,10%*(AC52+Y52))) -> 58.653627 | AM52: =SUMPRODUCT(ROUND(Y52:AB52, 2)) + SUMPRODUCT(ROUND(AD52:AG52, 2)) - SUMPRODUCT(ROUND(AH52:AL52, 2)) -> 1019.44 | AN52: =PROYECTADA!P52 -> 8.680434 | AO52: =6%*SUM(Y52:AB52) -> 35.192176 | AP52: =PROYECTADA!Q52 -> 7.853726 | AQ52: =PROYECTADA!R52 -> 7.5781567 | AX52: =IF(AND(AM52=AS52,AN52,AT52,AO52,AU52,AP52,AV52,AQ52,AW52),"OK","ERROR") -> ERROR
A53: 47 | B53: Quispe Gutierrez Leonardo | C53: INT M | V53: =SUM(F53:U53) -> 0 | W53: =$AP$3-V53 -> 31 | X53: ='REPORTE DIARIO'!AI53 -> 195 | Y53: =PROYECTADA!G53 -> 94.16 | Z53: =1130/30*Q53 -> 0 | AA53: =PROYECTADA!D53/$AP$1*PLAME!X53 -> 1054.1435 | AB53: =PROYECTADA!F53/$AP$3*($AP$3-L53) -> 0 | AC53: =SUM(Z53:AB53) -> 1054.1435 | AD53: =6%*AF53 -> 10.537219 | AE53: =((30%*1130)/$AP$3)*($AP$3-L53) -> 339 | AF53: =16.66%*AC53 -> 175.62031 | AG53: =9.72%*AC53 -> 102.46275 | AH53: =IF(OR(D53="SI", C53="SNP"), 0, VLOOKUP(C53, tbl_descuentos[], 2, FALSE) * SUM(Y53:AB53)) -> 0 | AI53: 0 | AJ53: =IF(OR(D53="SI", C53="SNP"), 0, VLOOKUP(C53, tbl_descuentos[], IF(E53 > 65, 4, 3), FALSE) * SUM(Y53:AB53)) -> 15.731758 | AK53: =IF(D53="SI",0,IF(C53="SNP",13%*SUM(Y53:AB53),0)) -> 0 | AL53: =IF(C53="SNP",0,IF(D53="SI",0,10%*(AC53+Y53))) -> 114.83035 | AM53: =SUMPRODUCT(ROUND(Y53:AB53, 2)) + SUMPRODUCT(ROUND(AD53:AG53, 2)) - SUMPRODUCT(ROUND(AH53:AL53, 2)) -> 1645.36 | AN53: =PROYECTADA!P53 -> 9.3804194 | AO53: =6%*SUM(Y53:AB53) -> 68.898211 | AP53: =PROYECTADA!Q53 -> 8.4870462 | AQ53: =PROYECTADA!R53 -> 8.1892551 | AX53: =IF(AND(AM53=AS53,AN53,AT53,AO53,AU53,AP53,AV53,AQ53,AW53),"OK","ERROR") -> ERROR
A54: 48 | B54: Santiago Espinoza Yovani | C54: INT M | V54: =SUM(F54:U54) -> 0 | W54: =$AP$3-V54 -> 31 | X54: ='REPORTE DIARIO'!AI54 -> 200 | Y54: =PROYECTADA!G54 -> 103.58 | Z54: =1130/30*Q54 -> 0 | AA54: =PROYECTADA!D54/$AP$1*PLAME!X54 -> 1081.1728 | AB54: =PROYECTADA!F54/$AP$3*($AP$3-L54) -> 113 | AC54: =SUM(Z54:AB54) -> 1194.1728 | AD54: =6%*AF54 -> 11.936952 | AE54: =((30%*1130)/$AP$3)*($AP$3-L54) -> 339 | AF54: =16.66%*AC54 -> 198.9492 | AG54: =9.72%*AC54 -> 116.0736 | AH54: =IF(OR(D54="SI", C54="SNP"), 0, VLOOKUP(C54, tbl_descuentos[], 2, FALSE) * SUM(Y54:AB54)) -> 0 | AI54: 0 | AJ54: =IF(OR(D54="SI", C54="SNP"), 0, VLOOKUP(C54, tbl_descuentos[], IF(E54 > 65, 4, 3), FALSE) * SUM(Y54:AB54)) -> 17.779214 | AK54: =IF(D54="SI",0,IF(C54="SNP",13%*SUM(Y54:AB54),0)) -> 0 | AL54: =IF(C54="SNP",0,IF(D54="SI",0,10%*(AC54+Y54))) -> 129.77528 | AM54: =SUMPRODUCT(ROUND(Y54:AB54, 2)) + SUMPRODUCT(ROUND(AD54:AG54, 2)) - SUMPRODUCT(ROUND(AH54:AL54, 2)) -> 1816.15 | AN54: =PROYECTADA!P54 -> 10.29049 | AO54: =6%*SUM(Y54:AB54) -> 77.86517 | AP54: =PROYECTADA!Q54 -> 9.3104431 | AQ54: =PROYECTADA!R54 -> 8.9837609 | AX54: =IF(AND(AM54=AS54,AN54,AT54,AO54,AU54,AP54,AV54,AQ54,AW54),"OK","ERROR") -> ERROR
AB58: SEGURO | AC58: % DESC | AD58: % PRIMA | AE58: % PRIMA > 65
AB59: HAB F | AC59: ='DESCUENTO AFP'!B4 -> 0.0147 | AD59: ='DESCUENTO AFP'!D4 -> 0.0137 | AE59: 0
AB60: INT F | AC60: ='DESCUENTO AFP'!B5 -> 0.0155 | AD60: ='DESCUENTO AFP'!D5 -> 0.0137 | AE60: 0
AB61: PRI F | AC61: ='DESCUENTO AFP'!B6 -> 0.016 | AD61: ='DESCUENTO AFP'!D6 -> 0.0137 | AE61: 0
AB62: PRO F | AC62: ='DESCUENTO AFP'!B7 -> 0.0169 | AD62: ='DESCUENTO AFP'!D7 -> 0.0137 | AE62: 0
AB63: SNP | AC63: 0
AB64: HAB M | AC64: 0 | AD64: ='DESCUENTO AFP'!D4 -> 0.0137 | AE64: 0
AB65: INT M | AC65: 0 | AD65: ='DESCUENTO AFP'!D5 -> 0.0137 | AE65: 0
AB66: PRI M | AC66: 0 | AD66: ='DESCUENTO AFP'!D6 -> 0.0137 | AE66: 0
AB67: PRO M | AC67: 0 | AD67: ='DESCUENTO AFP'!D7 -> 0.0137 | AE67: 0

Sheet REPORTE DIARIO
A2: PLANILLA ESPECIAL TIERRA SANTA HOLDING SAC - ENERO 2026
AN3: 125
C4: recuento personas trabajando | D4: =COUNTIF(D7:D52,">7") -> 46 | E4: =COUNTIF(E7:E52,">7") -> 44 | F4: =COUNTIF(F7:F52,">7") -> 6 | G4: =COUNTIF(G7:G52,">7") -> 0 | H4: =COUNTIF(H7:H52,">7") -> 45 | I4: =COUNTIF(I7:I52,">7") -> 44 | J4: =COUNTIF(J7:J52,">7") -> 42 | K4: =COUNTIF(K7:K52,">7") -> 42 | ... U4: =COUNTIF(U7:U52,">7") -> 0 | V4: =COUNTIF(V7:V52,">=6") -> 40 | W4: =COUNTIF(W7:W52,">7") -> 43 | X4: =COUNTIF(X7:X52,">7") -> 42 | Y4: =COUNTIF(Y7:Y52,">7") -> 41 | Z4: =COUNTIF(Z7:Z52,">7") -> 42 | AA4: =COUNTIF(AA7:AA52,">7") -> 5 | AB4: =COUNTIF(AB7:AB52,">7") -> 0 | AC4: =COUNTIF(AC7:AC52,">7") -> 39 | AD4: =COUNTIF(AD7:AD52,">7") -> 42 | AE4: =COUNTIF(AE7:AE52,">7") -> 43 | AG4: =COUNTIF(AG7:AG52,">7") -> 42 | AI4: =MAX(AI7:AI54) -> 216 | AK4: =COUNTIF(AK7:AK52,">48") -> 0 | AL4: =COUNTIF(AL7:AL52,">7") -> 1
A5: Nº | B5: Nº ORDEN | C5: NOMBRES | D5: J | E5: V | F5: S | G5: D | H5: L | I5: M | J5: M | K5: J | L5: V | M5: S | N5: D | O5: L | P5: M | Q5: M | R5: J | S5: V | T5: S | U5: D | V5: L | W5: M | X5: M | Y5: J | Z5: V | AA5: S | AB5: D | AC5: L | AD5: M | AE5: M | AF5: J | AG5: V | AH5: S | AI5: D
D6: 1 | E6: 2 | F6: 3 | G6: 4 | H6: 5 | I6: 6 | J6: 7 | K6: 8 | L6: 9 | M6: 10 | N6: 11 | O6: 12 | P6: 13 | Q6: 14 | R6: 15 | S6: 16 | T6: 17 | U6: 18 | V6: 19 | W6: 20 | X6: 21 | Y6: 22 | Z6: 23 | AA6: 24 | AB6: 25 | AC6: 26 | AD6: 27 | AE6: 28 | AF6: 29 | AG6: 30 | AH6: 31 | AI6: HORAS | AL6: Faltas
A7: 1 | B7: Captz. 2 | C7: Apaza Tito Patricia | D7: 8 | E7: 9 | F7: 7 | H7: 8 | I7: 8 | J7: 8 | K7: 9 | L7: 9 | M7: 6 | O7: 8 | P7: 8 | Q7: 8 | R7: 9 | S7: 9 | T7: 6 | V7: 8 | W7: 8 | X7: 8 | Y7: 9 | Z7: 9 | AA7: 6 | AC7: 8 | AD7: 8 | AE7: 8 | AF7: 9 | AG7: 9 | AH7: 6 | AI7: =SUM(D7:AH7) -> 216 | AJ7: =IF(AI7=208,"A. Perfecta","Faltó") -> Faltó | AK7: =SUM(D7:D7) -> 8 | AL7: =COUNTIF(D7:AH7,"F") -> 0 | AM7: =IF(AND(COUNTIF(D7:U7,"F")<14,COUNTIF(Q7:U7,"F")<=3),"SI","NO CORRESPONDE") -> SI | AN7: =2400+AN3 -> 2525 | AO7: 100 | AP7: =AN7+AO7 -> 2625 | AQ7: =AP7/27 -> 97.222222 | AR7: =AQ7/8 -> 12.152778 | AS7: =AR7*AI7 -> 2625
A8: 2 | B8: Campo | C8: Aquino Gómez Basilia Isabel | D8: 8 | E8: 9 | F8: 7 | H8: 8 | I8: 8 | J8: 8 | K8: 9 | L8: 9 | M8: 6 | O8: 8 | P8: 8 | Q8: 8 | R8: 9 | S8: 9 | T8: 6 | V8: 8 | W8: 8 | X8: 8 | Y8: 9 | Z8: 9 | AA8: 6 | AC8: 8 | AD8: 8 | AE8: 8 | AF8: 9 | AG8: 9 | AH8: 6 | AI8: =SUM(D8:AH8) -> 216 | AJ8: =IF(AI8=208,"A. Perfecta","Faltó") -> Faltó | AK8: =SUM(D8:D8) -> 8 | AL8: =COUNTIF(D8:AH8,"F") -> 0 | AM8: =IF(AND(COUNTIF(D8:U8,"F")<14,COUNTIF(Q8:U8,"F")<=3),"SI","NO CORRESPONDE") -> SI | AN8: =1875+$AN$3 -> 2000 | AP8: =AN8+AO8 -> 2000 | AQ8: =AP8/27 -> 74.074074 | AR8: =AQ8/8 -> 9.2592593 | AS8: =AR8*AI8 -> 2000
A9: 3 | B9: Campo | C9: Calla G Guillermina | D9: 8 | E9: 9 | F9: 7 | H9: 8 | I9: 8 | J9: 8 | K9: 9 | L9: 9 | M9: 6 | O9: 8 | P9: 8 | Q9: 8 | R9: 9 | S9: 9 | T9: 6 | V9: 8 | W9: 8 | X9: 8 | Y9: 9 | Z9: 9 | AA9: 6 | AC9: 8 | AD9: 8 | AE9: 8 | AF9: 9 | AG9: 9 | AH9: 6 | AI9: =SUM(D9:AH9) -> 216 | AJ9: =IF(AI9=208,"A. Perfecta","Faltó") -> Faltó | AK9: =SUM(D9:D9) -> 8 | AL9: =COUNTIF(D9:AH9,"F") -> 0 | AM9: =IF(AND(COUNTIF(D9:U9,"F")<14,COUNTIF(Q9:U9,"F")<=3),"SI","NO CORRESPONDE") -> SI | AN9: =1875+$AN$3 -> 2000 | AO9: 100 | AP9: =AN9+AO9 -> 2100 | AQ9: =AP9/27 -> 77.777778 | AR9: =AQ9/8 -> 9.7222222 | AS9: =AR9*AI9 -> 2100
A10: 4 | B10: Campo | C10: Challco Laime, Gilberta | D10: 8 | E10: 9 | F10: 7 | H10: 8 | I10: 8 | J10: 8 | K10: 9 | L10: 9 | M10: 6 | O10: 8 | P10: 8 | Q10: 8 | R10: 9 | S10: 9 | T10: 6 | V10: 8 | W10: 8 | X10: 8 | Y10: 9 | Z10: 9 | AA10: 6 | AC10: F | AD10: 8 | AE10: 8 | AF10: 9 | AG10: 9 | AH10: 6 | AI10: =SUM(D10:AH10) -> 208 | AJ10: =IF(AI10=208,"A. Perfecta","Faltó") -> A. Perfecta | AK10: =SUM(D10:D10) -> 8 | AL10: =COUNTIF(D10:AH10,"F") -> 1 | AM10: =IF(AND(COUNTIF(D10:U10,"F")<14,COUNTIF(Q10:U10,"F")<=3),"SI","NO CORRESPONDE") -> SI | AN10: =1875+$AN$3 -> 2000 | AO10: 100 | AP10: =AN10+AO10 -> 2100 | AQ10: =AP10/27 -> 77.777778 | AR10: =AQ10/8 -> 9.7222222 | AS10: 2100
A11: 5 | B11: Campo | C11: Choquehuayta Huallpa, Estefania | D11: 8 | E11: 9 | F11: 7 | H11: 8 | I11: 8 | J11: 8 | K11: 9 | L11: 9 | M11: 6 | O11: 8 | P11: 8 | Q11: 8 | R11: 9 | S11: 9 | T11: 6 | V11: 8 | W11: 8 | X11: 8 | Y11: 9 | Z11: 9 | AA11: F | AC11: 8 | AD11: 8 | AE11: 8 | AF11: 9 | AG11: 9 | AH11: 6 | AI11: =SUM(D11:AH11) -> 210 | AJ11: =IF(AI11=208,"A. Perfecta","Faltó") -> Faltó | AK11: =SUM(D11:D11) -> 8 | AL11: =COUNTIF(D11:AH11,"F") -> 1 | AM11: =IF(AND(COUNTIF(D11:U11,"F")<14,COUNTIF(Q11:U11,"F")<=3),"SI","NO CORRESPONDE") -> SI | AN11: =1875+$AN$3 -> 2000 | AP11: =AN11+AO11 -> 2000 | AQ11: =AP11/27 -> 74.074074 | AR11: =AQ11/8 -> 9.2592593 | AS11: =AR11*AI11 -> 1944.4444
A12: 6 | B12: Campo | C12: Idme Huaraccallo, Gladis | D12: 8 | E12: 9 | F12: 7 | H12: 8 | I12: 8 | J12: 8 | K12: 9 | L12: 9 | M12: 6 | O12: 8 | P12: 8 | Q12: 8 | R12: 9 | S12: 9 | T12: 6 | V12: 8 | W12: 8 | X12: 8 | Y12: 9 | Z12: 9 | AA12: 6 | AC12: 8 | AD12: 8 | AE12: 8 | AF12: 9 | AG12: 9 | AH12: 6 | AI12: =SUM(D12:AH12) -> 216 | AJ12: =IF(AI12=208,"A. Perfecta","Faltó") -> Faltó | AK12: =SUM(D12:D12) -> 8 | AL12: =COUNTIF(D12:AH12,"F") -> 0 | AM12: =IF(AND(COUNTIF(D12:U12,"F")<14,COUNTIF(Q12:U12,"F")<=3),"SI","NO CORRESPONDE") -> SI | AN12: =1875+$AN$3 -> 2000 | AP12: =AN12+AO12 -> 2000 | AQ12: =AP12/27 -> 74.074074 | AR12: =AQ12/8 -> 9.2592593 | AS12: =AR12*AI12 -> 2000
A13: 7 | B13: Ast. Adm campo | C13: Jacha Gomez, Flavia | D13: 8 | E13: 9 | F13: 7 | H13: 8 | I13: 8 | J13: 8 | K13: 9 | L13: 9 | M13: 6 | O13: 8 | P13: 8 | Q13: 8 | R13: 9 | S13: 9 | T13: 6 | V13: 8 | W13: 8 | X13: 8 | Y13: 8 | AE13: 8 | AF13: 9 | AG13: 9 | AH13: 6 | AI13: =SUM(D13:AH13) -> 184 | AJ13: =IF(AI13=208,"A. Perfecta","Faltó") -> Faltó | AK13: =SUM(D13:D13) -> 8 | AL13: =COUNTIF(D13:AH13,"F") -> 0 | AM13: =IF(AND(COUNTIF(D13:U13,"F")<14,COUNTIF(Q13:U13,"F")<=3),"SI","NO CORRESPONDE") -> SI | AN13: =2025+AN3 -> 2150 | AO13: 100 | AP13: =AN13+AO13 -> 2250 | AQ13: =AP13/27 -> 83.333333 | AR13: =AQ13/8 -> 10.416667 | AS13: =AR13*AI13 -> 1916.6667
A14: 8 | B14: Campo | C14: Lerma Yanarico Elena | D14: 8 | E14: 9 | F14: 7 | H14: 8 | I14: 8 | J14: 8 | K14: 9 | L14: 9 | M14: 6 | O14: 8 | P14: 8 | Q14: 8 | R14: 9 | S14: 9 | T14: 6 | V14: 8 | W14: 8 | X14: 8 | Y14: 9 | Z14: 9 | AA14: 6 | AC14: 8 | AD14: 8 | AE14: 8 | AF14: 9 | AG14: 9 | AH14: 6 | AI14: =SUM(D14:AH14) -> 216 | AJ14: =IF(AI14=208,"A. Perfecta","Faltó") -> Faltó | AK14: =SUM(D14:D14) -> 8 | AL14: =COUNTIF(D14:AH14,"F") -> 0 | AM14: =IF(AND(COUNTIF(D14:U14,"F")<14,COUNTIF(Q14:U14,"F")<=3),"SI","NO CORRESPONDE") -> SI | AN14: =1875+$AN$3 -> 2000 | AP14: =AN14+AO14 -> 2000 | AQ14: =AP14/27 -> 74.074074 | AR14: =AQ14/8 -> 9.2592593 | AS14: =AR14*AI14 -> 2000
A15: 9 | B15: Campo | C15: Machaca Calcina, Benedicta | D15: 8 | E15: F | F15: 7 | H15: 8 | I15: 8 | J15: F | K15: 9 | L15: 9 | M15: 6 | O15: 8 | P15: 8 | Q15: 8 | R15: 9 | S15: 9 | T15: 6 | V15: F | W15: 8 | X15: 8 | Y15: 9 | Z15: 9 | AA15: 6 | AC15: 8 | AD15: 8 | AE15: 8 | AF15: 9 | AG15: F | AH15: 6 | AI15: =SUM(D15:AH15) -> 182 | AJ15: =IF(AI15=208,"A. Perfecta","Faltó") -> Faltó | AK15: =SUM(D15:D15) -> 8 | AL15: =COUNTIF(D15:AH15,"F") -> 4 | AM15: =IF(AND(COUNTIF(D15:U15,"F")<14,COUNTIF(Q15:U15,"F")<=3),"SI","NO CORRESPONDE") -> SI | AN15: =1875+$AN$3 -> 2000 | AP15: =AN15+AO15 -> 2000 | AQ15: =AP15/27 -> 74.074074 | AR15: =AQ15/8 -> 9.2592593 | AS15: 1851.8519
A16: 10 | B16: Campo | C16: Mamani Hancco, Elsa Teresa | D16: 8 | E16: 9 | F16: 7 | H16: 8 | I16: 8 | J16: 8 | K16: 9 | L16: 9 | M16: 6 | O16: 8 | P16: 8 | Q16: 8 | R16: 9 | S16: 9 | T16: 6 | V16: 8 | W16: 8 | X16: 8 | Y16: 9 | Z16: 9 | AA16: 6 | AC16: 8 | AD16: 8 | AE16: 8 | AF16: 9 | AG16: 9 | AH16: 6 | AI16: =SUM(D16:AH16) -> 216 | AJ16: =IF(AI16=208,"A. Perfecta","Faltó") -> Faltó | AK16: =SUM(D16:D16) -> 8 | AL16: =COUNTIF(D16:AH16,"F") -> 0 | AM16: =IF(AND(COUNTIF(D16:U16,"F")<14,COUNTIF(Q16:U16,"F")<=3),"SI","NO CORRESPONDE") -> SI | AN16: =1875+$AN$3 -> 2000 | AP16: =AN16+AO16 -> 2000 | AQ16: =AP16/27 -> 74.074074 | AR16: =AQ16/8 -> 9.2592593 | AS16: 1916.6667
A17: 11 | B17: Campo | C17: Mamani Itusaca de Perca Guzmila | D17: 8 | E17: 9 | F17: 7 | H17: 8 | I17: 8 | J17: 8 | K17: 9 | L17: 9 | M17: 6 | O17: 8 | P17: 8 | Q17: 8 | R17: 9 | S17: 9 | T17: 6 | V17: F | W17: 8 | X17: 8 | Y17: 9 | Z17: 9 | AA17: 6 | AC17: 8 | AD17: 8 | AE17: 8 | AF17: 9 | AG17: 9 | AH17: 6 | AI17: =SUM(D17:AH17) -> 208 | AJ17: =IF(AI17=208,"A. Perfecta","Faltó") -> A. Perfecta | AK17: =SUM(D17:D17) -> 8 | AL17: =COUNTIF(D17:AH17,"F") -> 1 | AM17: =IF(AND(COUNTIF(D17:U17,"F")<14,COUNTIF(Q17:U17,"F")<=3),"SI","NO CORRESPONDE") -> SI | AN17: =1875+$AN$3 -> 2000 | AO17: 100 | AP17: =AN17+AO17 -> 2100 | AQ17: =AP17/27 -> 77.777778 | AR17: =AQ17/8 -> 9.7222222 | AS17: =AR17*AI17 -> 2022.2222
A18: 12 | B18: Cocinera | C18: Mayta Coaquira Janet Venancia | D18: 8 | E18: 9 | F18: 7 | H18: 8 | I18: 8 | J18: 8 | K18: 9 | L18: 9 | M18: 6 | O18: 8 | P18: 8 | Q18: 8 | R18: 9 | S18: 9 | T18: 6 | AI18: =SUM(D18:AH18) -> 120 | AL18: =COUNTIF(D18:AH18,"F") -> 0 | AM18: =IF(AND(COUNTIF(D18:U18,"F")<14,COUNTIF(Q18:U18,"F")<=3),"SI","NO CORRESPONDE") -> SI | AN18: =1875+$AN$3 -> 2000 | AO18: 100 | AP18: =AN18+AO18 -> 2100 | AQ18: =AP18/27 -> 77.777778 | AR18: =AQ18/8 -> 9.7222222 | AS18: =AR18*AI18 -> 1166.6667
A19: 13 | B19: Campo | C19: Parari Laura Teresa Lucy | D19: 8 | E19: 9 | F19: 7 | H19: 8 | I19: 8 | J19: 8 | K19: 9 | L19: 9 | M19: 6 | O19: 8 | P19: 8 | Q19: 8 | R19: 9 | S19: 9 | T19: 6 | V19: 8 | W19: 8 | X19: 8 | Y19: 9 | Z19: 9 | AA19: 6 | AC19: 8 | AD19: 8 | AE19: 8 | AF19: 9 | AG19: 9 | AH19: 6 | AI19: =SUM(D19:AH19) -> 216 | AJ19: =IF(AI19=208,"A. Perfecta","Faltó") -> Faltó | AK19: =SUM(D19:D19) -> 8 | AL19: =COUNTIF(D19:AH19,"F") -> 0 | AM19: =IF(AND(COUNTIF(D19:U19,"F")<14,COUNTIF(Q19:U19,"F")<=3),"SI","NO CORRESPONDE") -> SI | AN19: =1875+$AN$3 -> 2000 | AP19: =AN19+AO19 -> 2000 | AQ19: =AP19/27 -> 74.074074 | AR19: =AQ19/8 -> 9.2592593 | AS19: =AR19*AI19 -> 2000
A20: 14 | B20: Campo | C20: Pelinco Machaca, Monica | D20: 8 | E20: 9 | F20: 7 | H20: 8 | I20: 8 | J20: 8 | K20: 9 | L20: 9 | M20: 6 | O20: 8 | P20: 8 | Q20: 8 | R20: 9 | S20: 9 | T20: 6 | V20: 8 | W20: 8 | X20: 8 | Y20: 9 | Z20: 9 | AA20: 6 | AC20: 8 | AD20: 8 | AE20: 8 | AF20: 9 | AG20: 9 | AH20: 6 | AI20: =SUM(D20:AH20) -> 216 | AJ20: =IF(AI20=208,"A. Perfecta","Faltó") -> Faltó | AK20: =SUM(D20:D20) -> 8 | AL20: =COUNTIF(D20:AH20,"F") -> 0 | AM20: =IF(AND(COUNTIF(D20:U20,"F")<14,COUNTIF(Q20:U20,"F")<=3),"SI","NO CORRESPONDE") -> SI | AN20: =1875+$AN$3 -> 2000 | AP20: =AN20+AO20 -> 2000 | AQ20: =AP20/27 -> 74.074074 | AR20: =AQ20/8 -> 9.2592593 | AS20: =AR20*AI20 -> 2000
A21: 15 | B21: Campo | C21: Quispe Pacco Obita | D21: 8 | E21: 9 | F21: 7 | H21: 8 | I21: 8 | J21: 8 | K21: 9 | L21: 9 | M21: 6 | O21: 8 | P21: 8 | Q21: 8 | R21: 9 | S21: 9 | T21: 6 | V21: 8 | W21: 8 | X21: 8 | Y21: 9 | Z21: 9 | AA21: 6 | AC21: 8 | AD21: 8 | AE21: 8 | AF21: 9 | AG21: 9 | AH21: 6 | AI21: =SUM(D21:AH21) -> 216 | AJ21: =IF(AI21=208,"A. Perfecta","Faltó") -> Faltó | AK21: =SUM(D21:D21) -> 8 | AL21: =COUNTIF(D21:AH21,"F") -> 0 | AM21: =IF(AND(COUNTIF(D21:U21,"F")<14,COUNTIF(Q21:U21,"F")<=3),"SI","NO CORRESPONDE") -> SI | AN21: =1875+$AN$3 -> 2000 | AO21: 100 | AP21: =AN21+AO21 -> 2100 | AQ21: =AP21/27 -> 77.777778 | AR21: =AQ21/8 -> 9.7222222 | AS21: =AR21*AI21 -> 2100
A22: 16 | B22: Campo | C22: Aragon Hancco Delia Jesusa | D22: 8 | E22: 9 | F22: 7 | H22: 8 | I22: 8 | J22: 4 | K22: 9 | L22: 9 | M22: 6 | O22: 8 | P22: 8 | Q22: 8 | R22: F | S22: 9 | T22: 6 | V22: F | W22: 8 | X22: 8 | Y22: 9 | Z22: 9 | AA22: F | AC22: 8 | AD22: 8 | AE22: 8 | AF22: 9 | AG22: 9 | AH22: 6 | AI22: =SUM(D22:AH22) -> 189 | AJ22: =IF(AI22=208,"A. Perfecta","Faltó") -> Faltó | AK22: =SUM(D22:D22) -> 8 | AL22: =COUNTIF(D22:AH22,"F") -> 3 | AM22: =IF(AND(COUNTIF(D22:U22,"F")<14,COUNTIF(Q22:U22,"F")<=3),"SI","NO CORRESPONDE") -> SI | AN22: =2023+$AN$3 -> 2148 | AP22: =AN22+AO22 -> 2148 | AQ22: =AP22/27 -> 79.555556 | AR22: =AQ22/8 -> 9.9444444 | AS22: =AR22*AI22 -> 1879.5
A23: 17 | B23: Campo | C23: Gonzales Aparicio Lisbeth | D23: 8 | E23: 9 | F23: 7 | H23: 8 | I23: 8 | J23: 8 | K23: 9 | L23: 9 | M23: 6 | O23: 8 | P23: 8 | Q23: 8 | R23: 9 | S23: 9 | T23: 6 | V23: 8 | W23: 8 | X23: 8 | Y23: 9 | Z23: 9 | AA23: 6 | AC23: 8 | AD23: 8 | AE23: 8 | AF23: 9 | AG23: 9 | AH23: 6 | AI23: =SUM(D23:AH23) -> 216 | AJ23: =IF(AI23=208,"A. Perfecta","Faltó") -> Faltó | AL23: =COUNTIF(D23:AH23,"F") -> 0 | AM23: =IF(AND(COUNTIF(D23:U23,"F")<14,COUNTIF(Q23:U23,"F")<=3),"SI","NO CORRESPONDE") -> SI | AN23: =2023+$AN$3 -> 2148 | AP23: =AN23+AO23 -> 2148 | AQ23: =AP23/27 -> 79.555556 | AR23: =AQ23/8 -> 9.9444444 | AS23: =AR23*AI23 -> 2148
A24: 18 | B24: Campo | C24: Sánchez Huanca María Luisa | D24: 8 | E24: 9 | F24: 7 | H24: 8 | I24: 8 | J24: 8 | K24: 9 | L24: 9 | M24: 6 | O24: 8 | P24: 8 | Q24: 8 | R24: 9 | S24: 9 | T24: 6 | V24: 8 | W24: 8 | X24: 8 | Y24: 9 | Z24: 9 | AA24: 6 | AC24: 8 | AD24: 8 | AE24: 8 | AF24: 9 | AG24: 9 | AH24: 6 | AI24: =SUM(D24:AH24) -> 216 | AJ24: =IF(AI24=208,"A. Perfecta","Faltó") -> Faltó | AK24: =SUM(D24:D24) -> 8 | AL24: =COUNTIF(D24:AH24,"F") -> 0 | AM24: =IF(AND(COUNTIF(D24:U24,"F")<14,COUNTIF(Q24:U24,"F")<=3),"SI","NO CORRESPONDE") -> SI | AN24: =2023+$AN$3 -> 2148 | AO24: 100 | AP24: =AN24+AO24 -> 2248 | AQ24: =AP24/27 -> 83.259259 | AR24: =AQ24/8 -> 10.407407 | AS24: =AR24*AI24 -> 2248
A25: 19 | B25: Riego | C25: Alvarez Chavez, Richard | D25: 8 | E25: 9 | F25: 7 | H25: 8 | I25: 8 | J25: F | K25: 8.5 | L25: 10 | M25: 7 | O25: 8 | P25: 8 | Q25: 9 | R25: 8 | S25: 10 | T25: 0 | V25: 8.5 | W25: 9.5 | X25: 9.5 | Y25: 9.5 | Z25: 9.5 | AA25: 7 | AC25: 9.5 | AD25: 9.5 | AE25: 8 | AF25: 8 | AG25: 8 | AH25: 3 | AI25: =SUM(D25:AH25) -> 208 | AJ25: =IF(AI25=208,"A. Perfecta","Faltó") -> A. Perfecta | AL25: =COUNTIF(D25:AH25,"F") -> 1 | AM25: =IF(AND(COUNTIF(D25:U25,"F")<14,COUNTIF(Q25:U25,"F")<=3),"SI","NO CORRESPONDE") -> SI | AN25: =2065+$AN$3 -> 2190 | AO25: 100 | AP25: =AN25+AO25 -> 2290 | AQ25: =AP25/27 -> 84.814815 | AR25: =AQ25/8 -> 10.601852 | AS25: =AR25*AI25 -> 2205.1852
A26: 20 | B26: Riego | C26: Aparicio Ch Claver | D26: 8 | E26: 9.5 | F26: 7 | H26: 8.5 | I26: 8.5 | J26: 8.5 | K26: 8 | L26: 9.5 | M26: 7 | O26: 8.5 | P26: 8.5 | Q26: 9.5 | R26: 9.5 | S26: 9 | T26: 7 | V26: 8.5 | W26: 8.5 | X26: 8.5 | Y26: 9 | Z26: 9.5 | AA26: 7 | AC26: 0 | AD26: 8.5 | AE26: 8 | AF26: 8 | AG26: 9.5 | AH26: 4.5 | AI26: =SUM(D26:AH26) -> 216 | AJ26: =IF(AI26=208,"A. Perfecta","Faltó") -> Faltó | AL26: =COUNTIF(D26:AH26,"F") -> 0 | AM26: =IF(AND(COUNTIF(D26:U26,"F")<14,COUNTIF(Q26:U26,"F")<=3),"SI","NO CORRESPONDE") -> SI | AN26: =2065+$AN$3 -> 2190 | AO26: 100 | AP26: =AN26+AO26 -> 2290 | AQ26: =AP26/27 -> 84.814815 | AR26: =AQ26/8 -> 10.601852 | AS26: 2290
A27: 21 | B27: Fitro | C27: Aquino Gomez Carmelo | D27: 8 | E27: 9 | F27: 7 | H27: 8 | I27: 8 | J27: 8 | K27: 9 | L27: 9 | M27: 6 | O27: 8 | P27: 8 | Q27: 8 | R27: 9 | S27: 9 | T27: 6 | V27: 8 | W27: 8 | X27: 8 | Y27: 9 | Z27: 9 | AA27: 6 | AC27: 8 | AD27: 8 | AE27: 8 | AF27: 9 | AG27: 9 | AH27: 6 | AI27: =SUM(D27:AH27) -> 216 | AJ27: =IF(AI27=208,"A. Perfecta","Faltó") -> Faltó | AL27: =COUNTIF(D27:AH27,"F") -> 0 | AM27: =IF(AND(COUNTIF(D27:U27,"F")<14,COUNTIF(Q27:U27,"F")<=3),"SI","NO CORRESPONDE") -> SI | AN27: =1925+$AN$3 -> 2050 | AP27: =AN27+AO27 -> 2050 | AQ27: =AP27/27 -> 75.925926 | AR27: =AQ27/8 -> 9.4907407 | AS27: =AR27*AI27 -> 2050
A28: 22 | B28: Ast. Prod. | C28: Ayamamani Chura Elver Emilio | D28: 8 | E28: 9 | F28: 7 | H28: 8 | I28: 8 | J28: 8 | K28: 9 | L28: 9 | M28: 6 | O28: 8 | P28: 8 | Q28: 8 | R28: 9 | S28: 9 | T28: 6 | V28: 8 | W28: 8 | X28: 8 | Y28: 9 | Z28: 9 | AA28: 6 | AC28: 8 | AD28: 8 | AE28: 8 | AF28: 9 | AG28: 9 | AH28: 6 | AI28: =SUM(D28:AH28) -> 216 | AJ28: =IF(AI28=208,"A. Perfecta","Faltó") -> Faltó | AL28: =COUNTIF(D28:AH28,"F") -> 0 | AM28: =IF(AND(COUNTIF(D28:U28,"F")<14,COUNTIF(Q28:U28,"F")<=3),"SI","NO CORRESPONDE") -> SI | AN28: =2400+AN3 -> 2525 | AO28: 100 | AP28: =AN28+AO28 -> 2625 | AQ28: =AP28/27 -> 97.222222 | AR28: =AQ28/8 -> 12.152778 | AS28: 2625
A29: 23 | B29: Campo | C29: Cañari Pucho, Guillermo | D29: 8 | E29: 9 | F29: 7 | H29: 8 | I29: F | J29: 8 | K29: 9 | L29: 9 | M29: 6 | O29: 8 | P29: 8 | Q29: 8 | R29: 9 | S29: 9 | T29: 6 | V29: 8 | W29: 8 | X29: 8 | Y29: 9 | Z29: 9 | AA29: 6 | AC29: 8 | AD29: 8 | AE29: 8 | AF29: 9 | AG29: 9 | AH29: 6 | AI29: =SUM(D29:AH29) -> 208 | AJ29: =IF(AI29=208,"A. Perfecta","Faltó") -> A. Perfecta | AL29: =COUNTIF(D29:AH29,"F") -> 1 | AM29: =IF(AND(COUNTIF(D29:U29,"F")<14,COUNTIF(Q29:U29,"F")<=3),"SI","NO CORRESPONDE") -> SI | AN29: =1875+$AN$3 -> 2000 | AO29: 100 | AP29: =AN29+AO29 -> 2100 | AQ29: =AP29/27 -> 77.777778 | AR29: =AQ29/8 -> 9.7222222 | AS29: 2100
A30: 24 | B30: Funigación | C30: Ccanchi Neira, Juan Lorenzo | D30: 8 | E30: 9 | F30: 7 | H30: 8 | I30: 8 | J30: 8 | K30: 9 | L30: 9 | M30: 6 | O30: 8 | P30: 8 | Q30: 8 | R30: 9 | S30: 9 | T30: 6 | V30: 8 | W30: 8 | X30: 8 | Y30: 9 | Z30: 9 | AA30: 6 | AC30: 8 | AD30: 8 | AE30: 8 | AF30: 9 | AG30: 9 | AH30: 6 | AI30: =SUM(D30:AH30) -> 216 | AJ30: =IF(AI30=208,"A. Perfecta","Faltó") -> Faltó | AN30: =1875+$AN$3 -> 2000 | AO30: 100 | AP30: =AN30+AO30 -> 2100 | AQ30: =AP30/27 -> 77.777778 | AR30: =AQ30/8 -> 9.7222222 | AS30: =AR30*AI30 -> 2100
A31: 25 | B31: Funigación | C31: Gamarra Chambi, Ernesto | D31: 8 | E31: 9 | F31: 7 | H31: 8 | I31: 8 | J31: 8 | K31: 9 | L31: 9 | M31: 6 | O31: 8 | P31: 8 | Q31: 8 | R31: 9 | S31: 9 | T31: 6 | V31: 8 | W31: 8 | X31: 8 | Y31: 9 | Z31: 9 | AA31: 6 | AC31: 8 | AD31: 8 | AE31: 8 | AF31: 9 | AG31: 9 | AH31: 6 | AI31: =SUM(D31:AH31) -> 216 | AJ31: =IF(AI31=208,"A. Perfecta","Faltó") -> Faltó | AN31: =1875+$AN$3 -> 2000 | AP31: =AN31+AO31 -> 2000 | AQ31: =AP31/27 -> 74.074074 | AR31: =AQ31/8 -> 9.2592593 | AS31: =AR31*AI31 -> 2000
A32: 26 | B32: Evaluador | C32: Huaynacho Otazu, Donar | D32: 8 | E32: 9 | F32: 7 | H32: 8 | I32: 8 | J32: 8 | K32: 9 | L32: 9 | M32: 6 | O32: 8 | P32: 8 | Q32: 8 | R32: 9 | S32: 9 | T32: 6 | V32: 8 | W32: 8 | X32: 8 | Y32: 9 | Z32: 9 | AA32: 6 | AC32: 8 | AD32: 8 | AE32: 8 | AF32: 9 | AG32: 9 | AH32: 6 | AI32: =SUM(D32:AH32) -> 216 | AJ32: =IF(AI32=208,"A. Perfecta","Faltó") -> Faltó | AN32: =1925+$AN$3 -> 2050 | AO32: 100 | AP32: =AN32+AO32 -> 2150 | AQ32: =AP32/27 -> 79.62963 | AR32: =AQ32/8 -> 9.9537037 | AS32: =AR32*AI32 -> 2150
A33: 27 | B33: Evaluador | C33: Huaynapata Itusaca Yoni Angel | D33: 8 | E33: 9 | F33: 7 | H33: 8 | I33: 8 | J33: 8 | K33: 9 | L33: 9 | M33: 6 | O33: 8 | P33: 8 | Q33: 8 | R33: 9 | S33: 9 | T33: 6 | V33: 8 | W33: 8 | X33: 8 | Y33: 9 | Z33: 9 | AA33: 6 | AC33: 8 | AD33: 8 | AE33: 8 | AF33: 9 | AG33: 9 | AH33: 6 | AI33: =SUM(D33:AH33) -> 216 | AN33: =1925+$AN$3 -> 2050 | AO33: 100 | AP33: =AN33+AO33 -> 2150 | AQ33: =AP33/27 -> 79.62963 | AR33: =AQ33/8 -> 9.9537037 | AS33: =AR33*AI33 -> 2150
A34: 28 | B34: Varios | C34: Idme Huaraccallo, Agustin | D34: 8 | AI34: =SUM(D34:AH34) -> 8 | AJ34: =IF(AI34=208,"A. Perfecta","Faltó") -> Faltó | AN34: =1925+$AN$3 -> 2050 | AO34: 100 | AP34: =AN34+AO34 -> 2150 | AQ34: =AP34/27 -> 79.62963 | AR34: =AQ34/8 -> 9.9537037 | AS34: =AR34*AI34 -> 79.62963
A35: 29 | B35: Fitro | C35: Lope Choquehuanca, Cirilo | D35: 8 | E35: 9 | F35: 7 | H35: 8 | I35: 8 | J35: 8 | K35: 9 | L35: 9 | M35: 6 | O35: 8 | P35: 8 | Q35: 8 | R35: 9 | S35: 9 | T35: 6 | V35: 8 | W35: 8 | X35: 8 | Y35: 9 | Z35: 9 | AA35: F | AC35: F | AD35: 8 | AE35: 8 | AF35: 9 | AG35: 9 | AH35: 6 | AI35: =SUM(D35:AH35) -> 202 | AJ35: =IF(AI35=208,"A. Perfecta","Faltó") -> Faltó | AL35: =COUNTIF(D35:AH35,"F") -> 2 | AM35: =IF(AND(COUNTIF(D35:U35,"F")<14,COUNTIF(Q35:U35,"F")<=3),"SI","NO CORRESPONDE") -> SI | AN35: =2586+$AN$3 -> 2711 | AO35: 100 | AP35: =AN35+AO35 -> 2811 | AQ35: =AP35/27 -> 104.11111 | AR35: =AQ35/8 -> 13.013889 | AS35: 2811
A36: 30 | B36: Tractorista | C36: Lope Choquehuanca, Luis | D36: 8 | E36: 9 | F36: 7 | H36: 8 | I36: 8 | J36: 8 | K36: 9 | L36: 9 | M36: 6 | O36: 8 | P36: 8 | Q36: 8 | R36: 9 | S36: 9 | T36: 6 | V36: 8 | W36: 8 | X36: 8 | Y36: 9 | Z36: 9 | AA36: 6 | AC36: 8 | AD36: 8 | AE36: 8 | AF36: 9 | AG36: 9 | AH36: 6 | AI36: =SUM(D36:AH36) -> 216 | AJ36: =IF(AI36=208,"A. Perfecta","Faltó") -> Faltó | AL36: =COUNTIF(D36:AH36,"F") -> 0 | AM36: =IF(AND(COUNTIF(D36:U36,"F")<14,COUNTIF(Q36:U36,"F")<=3),"SI","NO CORRESPONDE") -> SI | AN36: =2125+$AN$3 -> 2250 | AO36: 100 | AP36: =AN36+AO36 -> 2350 | AQ36: =AP36/27 -> 87.037037 | AR36: =AQ36/8 -> 10.87963 | AS36: =AR36*AI36 -> 2350
A37: 31 | B37: Vigilancia | C37: Lopez Mamani, Nestor | D37: 8 | E37: 8 | F37: 8 | H37: 8 | I37: 8 | J37: 8 | K37: 8 | L37: 8 | M37: 8 | O37: 8 | P37: 8 | Q37: 8 | R37: 8 | S37: 8 | T37: 8 | V37: 8 | W37: 8 | X37: 8 | Y37: 8 | Z37: 8 | AA37: 8 | AC37: 8 | AD37: 8 | AE37: 8 | AF37: 8 | AG37: 8 | AH37: 8 | AI37: =SUM(D37:AH37) -> 216 | AJ37: =IF(AI37=208,"A. Perfecta","Faltó") -> Faltó | AL37: =COUNTIF(D37:AH37,"F") -> 0 | AM37: =IF(AND(COUNTIF(D37:U37,"F")<14,COUNTIF(Q37:U37,"F")<=3),"SI","NO CORRESPONDE") -> SI | AN37: =2065+$AN$3 -> 2190 | AO37: 100 | AP37: =AN37+AO37 -> 2290 | AQ37: =AP37/27 -> 84.814815 | AR37: =AQ37/8 -> 10.601852 | AS37: =AR37*AI37 -> 2290
A38: 32 | B38: Campo | C38: Mamani Anconaira, Santo Domingo | D38: 8 | E38: 9 | F38: 7 | H38: 8 | I38: 8 | J38: 8 | K38: 9 | L38: 9 | M38: 6 | O38: 8 | P38: 8 | Q38: 8 | R38: 9 | S38: 9 | T38: 6 | V38: 8 | W38: 8 | X38: 8 | Y38: 9 | Z38: 9 | AA38: 6 | AC38: 8 | AD38: 8 | AE38: 8 | AF38: 9 | AG38: 9 | AH38: 6 | AI38: =SUM(D38:AH38) -> 216 | AJ38: =IF(AI38=208,"A. Perfecta","Faltó") -> Faltó | AL38: =COUNTIF(D38:AH38,"F") -> 0 | AM38: =IF(AND(COUNTIF(D38:U38,"F")<14,COUNTIF(Q38:U38,"F")<=3),"SI","NO CORRESPONDE") -> SI | AN38: =1875+$AN$3 -> 2000 | AO38: 100 | AP38: =AN38+AO38 -> 2100 | AQ38: =AP38/27 -> 77.777778 | AR38: =AQ38/8 -> 9.7222222 | AS38: =AR38*AI38 -> 2100
A39: 33 | B39: Captz. Grl | C39: Mamani Idme, Vicente | D39: 8 | E39: 9 | F39: 7 | H39: 8 | I39: 8 | J39: 8 | K39: 9 | L39: 9 | M39: 6 | O39: 8 | P39: 8 | Q39: 8 | R39: 9 | S39: 9 | T39: 6 | V39: 8 | W39: 8 | X39: 8 | Y39: 9 | Z39: 9 | AA39: 6 | AC39: 8 | AD39: 8 | AE39: 8 | AF39: 9 | AG39: 9 | AH39: 6 | AI39: =SUM(D39:AH39) -> 216 | AJ39: =IF(AI39=208,"A. Perfecta","Faltó") -> Faltó | AL39: =COUNTIF(D39:AH39,"F") -> 0 | AM39: =IF(AND(COUNTIF(D39:U39,"F")<14,COUNTIF(Q39:U39,"F")<=3),"SI","NO CORRESPONDE") -> SI | AN39: =3725+AN3 -> 3850 | AO39: 100 | AP39: =AN39+AO39 -> 3950 | AQ39: =AP39/27 -> 146.2963 | AR39: =AQ39/8 -> 18.287037 | AS39: =AR39*AI39 -> 3950
A40: 34 | B40: Vigilancia | C40: Mamani Mamani, Alejandro | D40: 8 | E40: 8 | F40: 8 | H40: 8 | I40: 8 | J40: 8 | K40: 8 | L40: 8 | M40: 8 | O40: 8 | P40: 8 | Q40: 8 | R40: 8 | S40: 8 | T40: 8 | V40: 8 | W40: 8 | X40: 8 | Y40: 8 | Z40: 8 | AA40: 8 | AC40: 8 | AD40: 8 | AE40: 8 | AF40: 8 | AG40: 8 | AH40: 8 | AI40: =SUM(D40:AH40) -> 216 | AJ40: =IF(AI40=208,"A. Perfecta","Faltó") -> Faltó | AL40: =COUNTIF(D40:AH40,"F") -> 0 | AM40: =IF(AND(COUNTIF(D40:U40,"F")<14,COUNTIF(Q40:U40,"F")<=3),"SI","NO CORRESPONDE") -> SI | AN40: =2165+AN3 -> 2290 | AO40: 100 | AP40: =AN40+AO40 -> 2390 | AQ40: =AP40/27 -> 88.518519 | AR40: =AQ40/8 -> 11.064815 | AS40: =AR40*AI40 -> 2390
A41: 35 | B41: Riego | C41: Palaco Retamozo Alberto Gilberto | D41: 8 | E41: 9.5 | F41: 7 | H41: 8.5 | I41: 8.5 | J41: 8.5 | K41: 8.5 | L41: 7 | M41: 7 | O41: 8.5 | P41: 8.5 | Q41: 8.5 | R41: 9.5 | S41: 9.5 | T41: 7 | V41: 8.5 | W41: 8.5 | X41: 8.5 | Y41: 0 | Z41: 9.5 | AA41: 7 | AC41: 9.5 | AD41: 8.5 | AE41: 8 | AF41: 8 | AG41: 9.5 | AH41: 6.5 | AI41: =SUM(D41:AH41) -> 216 | AJ41: =IF(AI41=208,"A. Perfecta","Faltó") -> Faltó | AL41: =COUNTIF(D41:AH41,"F") -> 0 | AM41: =IF(AND(COUNTIF(D41:U41,"F")<14,COUNTIF(Q41:U41,"F")<=3),"SI","NO CORRESPONDE") -> SI | AN41: =2065+$AN$3 -> 2190 | AO41: 100 | AP41: =AN41+AO41 -> 2290 | AQ41: =AP41/27 -> 84.814815 | AR41: =AQ41/8 -> 10.601852 | AS41: =AR41*AI41 -> 2290
A42: 36 | B42: Vigilancia | C42: Perca Mamani Julio Alberto | D42: 8 | E42: 8 | F42: 8 | H42: 8 | I42: 8 | J42: 8 | K42: 8 | L42: 8 | M42: 8 | O42: 8 | P42: 8 | Q42: 8 | R42: 8 | S42: 8 | T42: 8 | V42: 8 | W42: 8 | X42: 8 | Y42: 8 | Z42: 8 | AA42: 8 | AC42: 8 | AD42: 8 | AE42: 8 | AF42: 8 | AG42: 8 | AH42: 8 | AI42: =SUM(D42:AH42) -> 216 | AL42: =COUNTIF(D42:AH42,"F") -> 0 | AN42: =2065+$AN$3 -> 2190 | AO42: 100 | AP42: =AN42+AO42 -> 2290 | AQ42: =AP42/27 -> 84.814815 | AR42: =AQ42/8 -> 10.601852 | AS42: =AR42*AI42 -> 2290
A43: 37 | B43: Riego | C43: Quispe Belizario Alvaro | D43: 8 | E43: 9.5 | F43: 7 | H43: 8.5 | I43: 8.5 | J43: 8.5 | K43: 8.5 | L43: 10.5 | M43: 5 | O43: 8.5 | P43: 8.5 | Q43: 8.5 | R43: 9.5 | S43: 9.5 | T43: 7 | V43: 8.5 | W43: 8.5 | X43: 8.5 | Y43: 3 | Z43: 9 | AA43: 0 | AC43: 8.5 | AD43: 8.5 | AE43: 8 | AF43: 7 | AG43: 9 | AH43: 12 | AI43: =SUM(D43:AH43) -> 216 | AL43: =COUNTIF(D43:AH43,"F") -> 0 | AN43: =2065+$AN$3 -> 2190 | AO43: 100 | AP43: =AN43+AO43 -> 2290 | AQ43: =AP43/27 -> 84.814815 | AR43: =AQ43/8 -> 10.601852 | AS43: =AR43*AI43 -> 2290
A44: 38 | B44: Campo | C44: Quispe Quispe Luis | D44: 8 | E44: 9 | F44: 7 | H44: 8 | I44: 8 | J44: 8 | K44: 9 | L44: 9 | M44: 6 | O44: 8 | P44: 8 | Q44: 8 | R44: 9 | S44: 9 | T44: 6 | V44: 8 | W44: 8 | X44: 8 | Y44: 9 | Z44: 9 | AA44: 6 | AC44: 8 | AD44: 8 | AE44: 8 | AF44: 9 | AG44: 9 | AH44: 6 | AI44: =SUM(D44:AH44) -> 216 | AJ44: =IF(AI44=208,"A. Perfecta","Faltó") -> Faltó | AL44: =COUNTIF(D44:AH44,"F") -> 0 | AM44: =IF(AND(COUNTIF(D44:U44,"F")<14,COUNTIF(Q44:U44,"F")<=3),"SI","NO CORRESPONDE") -> SI | AN44: =1875+$AN$3 -> 2000 | AO44: 100 | AP44: =AN44+AO44 -> 2100 | AQ44: =AP44/27 -> 77.777778 | AR44: =AQ44/8 -> 9.7222222 | AS44: =AR44*AI44 -> 2100
A45: 39 | B45: Funigación | C45: Reynoso Gamero Rufino | D45: 8 | E45: 9 | F45: 7 | H45: 8 | I45: 8 | J45: 8 | K45: F | L45: 9 | M45: 6 | O45: 8 | P45: 8 | Q45: 8 | R45: 9 | S45: 9 | T45: 6 | V45: 8 | W45: 8 | X45: 8 | Y45: 9 | Z45: 9 | AA45: 6 | AC45: 8 | AD45: 8 | AE45: 8 | AF45: 9 | AG45: 9 | AH45: 6 | AI45: =SUM(D45:AH45) -> 207 | AJ45: =IF(AI45=208,"A. Perfecta","Faltó") -> Faltó | AL45: =COUNTIF(D45:AH45,"F") -> 1 | AM45: =IF(AND(COUNTIF(D45:U45,"F")<14,COUNTIF(Q45:U45,"F")<=3),"SI","NO CORRESPONDE") -> SI | AN45: =1875+$AN$3 -> 2000 | AP45: =AN45+AO45 -> 2000 | AQ45: =AP45/27 -> 74.074074 | AR45: =AQ45/8 -> 9.2592593 | AS45: =AR45*AI45 -> 1916.6667
A46: 40 | B46: Vigilancia | C46: Rivera Ramos Elmer Delis | D46: 8 | E46: 8 | F46: 8 | H46: 8 | I46: 8 | J46: 8 | K46: 8 | L46: 8 | M46: 8 | O46: 8 | P46: 8 | Q46: 8 | R46: 8 | S46: 8 | T46: 8 | V46: 8 | W46: 8 | X46: 8 | Y46: 8 | Z46: 8 | AA46: 8 | AC46: 8 | AD46: 8 | AE46: 8 | AF46: 8 | AG46: 8 | AH46: 8 | AI46: =SUM(D46:AH46) -> 216 | AJ46: =IF(AI46=208,"A. Perfecta","Faltó") -> Faltó | AL46: =COUNTIF(D46:AH46,"F") -> 0 | AM46: =IF(AND(COUNTIF(D46:U46,"F")<14,COUNTIF(Q46:U46,"F")<=3),"SI","NO CORRESPONDE") -> SI | AN46: =2065+$AN$3 -> 2190 | AO46: 100 | AP46: =AN46+AO46 -> 2290 | AQ46: =AP46/27 -> 84.814815 | AR46: =AQ46/8 -> 10.601852 | AS46: =AR46*AI46 -> 2290
A47: 41 | B47: Vigilancia | C47: Soncco Soncco, Santos Evaristo | D47: 8 | E47: 8 | F47: 8 | H47: 8 | I47: 8 | J47: 8 | K47: 8 | L47: 8 | M47: 8 | O47: 8 | P47: 8 | Q47: 8 | R47: 8 | S47: 8 | T47: 8 | V47: 8 | W47: 8 | X47: 8 | Y47: 8 | Z47: 8 | AA47: 8 | AC47: 8 | AD47: 8 | AE47: 8 | AF47: 8 | AG47: 8 | AH47: 8 | AI47: =SUM(D47:AH47) -> 216 | AJ47: =IF(AI47=208,"A. Perfecta","Faltó") -> Faltó | AK47: =SUM(D47:D47) -> 8 | AL47: =COUNTIF(D47:AH47,"F") -> 0 | AM47: =IF(AND(COUNTIF(D47:U47,"F")<14,COUNTIF(Q47:U47,"F")<=3),"SI","NO CORRESPONDE") -> SI | AN47: =2025+$AN$3 -> 2150 | AO47: 100 | AP47: =AN47+AO47 -> 2250 | AQ47: =AP47/27 -> 83.333333 | AR47: =AQ47/8 -> 10.416667 | AS47: 2250
A48: 42 | B48: Tractorista | C48: Ttito Tapara, Jose Pascual | D48: 8 | E48: 9 | F48: 7 | H48: 8 | I48: 8 | J48: 8 | K48: 9 | L48: 9 | M48: 6 | O48: 8 | P48: 8 | Q48: 8 | R48: 9 | S48: 9 | T48: 6 | V48: 8 | W48: 8 | X48: 8 | Y48: 9 | Z48: 9 | AA48: 6 | AC48: 8 | AD48: 8 | AE48: 8 | AF48: 9 | AG48: 9 | AH48: 6 | AI48: =SUM(D48:AH48) -> 216 | AJ48: =IF(AI48=208,"A. Perfecta","Faltó") -> Faltó | AK48: =SUM(D48:D48) -> 8 | AL48: =COUNTIF(D48:AH48,"F") -> 0 | AM48: =IF(AND(COUNTIF(D48:U48,"F")<14,COUNTIF(Q48:U48,"F")<=3),"SI","NO CORRESPONDE") -> SI | AN48: =2025+$AN$3 -> 2150 | AO48: 100 | AP48: =AN48+AO48 -> 2250 | AQ48: =AP48/27 -> 83.333333 | AR48: =AQ48/8 -> 10.416667 | AS48: =AR48*AI48 -> 2250
A49: 43 | B49: Albañil | C49: Turpo Quispe Yury | D49: 8 | E49: 9 | F49: 7 | H49: 8 | I49: 8 | J49: 8 | K49: 9 | L49: 9 | M49: 6 | O49: 8 | P49: 8 | Q49: 8 | R49: 9 | S49: 9 | T49: 6 | V49: 8 | W49: 8 | X49: 8 | Y49: 9 | Z49: 9 | AA49: 6 | AC49: 8 | AD49: 8 | AE49: 8 | AF49: 9 | AG49: 9 | AH49: 6 | AI49: =SUM(D49:AH49) -> 216 | AJ49: =IF(AI49=208,"A. Perfecta","Faltó") -> Faltó | AK49: =SUM(D49:D49) -> 8 | AL49: =COUNTIF(D49:AH49,"F") -> 0 | AM49: =IF(AND(COUNTIF(D49:U49,"F")<14,COUNTIF(Q49:U49,"F")<=3),"SI","NO CORRESPONDE") -> SI | AN49: =2025+$AN$3 -> 2150 | AO49: 100 | AP49: =AN49+AO49 -> 2250 | AQ49: =AP49/27 -> 83.333333 | AR49: =AQ49/8 -> 10.416667 | AS49: =AR49*AI49 -> 2250
A50: 44 | B50: Riego | C50: Zea Mamani, Ignacio | D50: 8 | E50: 9 | F50: 9 | H50: 8 | I50: 8 | J50: 8 | K50: 0 | L50: 10 | M50: 7 | O50: 8 | P50: 8 | Q50: 8 | R50: 9 | S50: 9.5 | T50: 7 | V50: 8 | W50: 8.5 | X50: 4 | Y50: 9.5 | Z50: 9.5 | AA50: 7 | AC50: 9 | AD50: 8 | AE50: 8 | AF50: 8 | AG50: 9 | AH50: 11 | AI50: =SUM(D50:AH50) -> 216 | AJ50: =IF(AI50=208,"A. Perfecta","Faltó") -> Faltó | AK50: =SUM(D50:D50) -> 8 | AL50: =COUNTIF(D50:AH50,"F") -> 0 | AM50: =IF(AND(COUNTIF(D50:U50,"F")<14,COUNTIF(Q50:U50,"F")<=3),"SI","NO CORRESPONDE") -> SI | AN50: =2065+$AN$3 -> 2190 | AO50: 100 | AP50: =AN50+AO50 -> 2290 | AQ50: =AP50/27 -> 84.814815 | AR50: =AQ50/8 -> 10.601852 | AS50: =AR50*AI50 -> 2290
A51: 45 | B51: Campo | C51: Chile Yareta Justino | D51: 8 | E51: 9 | F51: 7 | H51: 8 | I51: 8 | J51: 8 | K51: 9 | L51: F | M51: F | O51: F | P51: F | Q51: F | R51: F | S51: F | T51: F | V51: 8 | W51: 8 | X51: 8 | Y51: 9 | Z51: 9 | AA51: 6 | AC51: 8 | AD51: 8 | AE51: 8 | AF51: 9 | AG51: 9 | AH51: 6 | AI51: =SUM(D51:AH51) -> 153 | AJ51: =IF(AI51=208,"A. Perfecta","Faltó") -> Faltó | AK51: =SUM(D51:D51) -> 8 | AL51: =COUNTIF(D51:AH51,"F") -> 8 | AM51: =IF(AND(COUNTIF(D51:U51,"F")<14,COUNTIF(Q51:U51,"F")<=3),"SI","NO CORRESPONDE") -> NO CORRESPONDE | AN51: =2023+$AN$3 -> 2148 | AO51: 100 | AP51: =AN51+AO51 -> 2248 | AQ51: =AP51/27 -> 83.259259 | AR51: =AQ51/8 -> 10.407407 | AS51: =AR51*AI51 -> 1592.3333
A52: 46 | B52: Riego | C52: Diaz Chipana Walter | D52: 8 | E52: 9.5 | F52: 7 | H52: 8.5 | I52: 8.5 | J52: 8.5 | K52: F | L52: 10.5 | M52: 7 | O52: 8.5 | P52: 8.5 | Q52: 8.5 | R52: 0 | S52: 9.5 | T52: 6 | AI52: =SUM(D52:AH52) -> 108.5 | AJ52: =IF(AI52=208,"A. Perfecta","Faltó") -> Faltó | AK52: =SUM(D52:D52) -> 8 | AL52: =COUNTIF(D52:AH52,"F") -> 1 | AM52: =IF(AND(COUNTIF(D52:U52,"F")<14,COUNTIF(Q52:U52,"F")<=3),"SI","NO CORRESPONDE") -> SI | AN52: =2065+$AN$3 -> 2190 | AO52: 100 | AP52: =AN52+AO52 -> 2290 | AQ52: =AP52/27 -> 84.814815 | AR52: =AQ52/8 -> 10.601852 | AS52: =AR52*AI52 -> 1150.3009
A53: 47 | B53: Campo | C53: Quispe Gutierrez Leonardo | D53: 8 | E53: 9 | F53: 7 | H53: 8 | I53: 8 | J53: 8 | K53: 9 | L53: 4.5 | M53: 6 | O53: 4 | P53: F | Q53: 8 | R53: 9 | S53: 4.5 | T53: 6 | V53: 8 | W53: 8 | X53: 8 | Y53: 9 | Z53: 9 | AA53: 6 | AC53: 8 | AD53: 8 | AE53: 8 | AF53: 9 | AG53: 9 | AH53: 6 | AI53: =SUM(D53:AH53) -> 195 | AJ53: =IF(AI53=208,"A. Perfecta","Faltó") -> Faltó | AK53: =SUM(D53:D53) -> 8 | AL53: =COUNTIF(D53:AH53,"F") -> 1 | AM53: =IF(AND(COUNTIF(D53:U53,"F")<14,COUNTIF(Q53:U53,"F")<=3),"SI","NO CORRESPONDE") -> SI | AN53: =2023+$AN$3 -> 2148 | AP53: =AN53+AO53 -> 2148 | AQ53: =AP53/27 -> 79.555556 | AR53: =AQ53/8 -> 9.9444444 | AS53: =AR53*AI53 -> 1939.1667
A54: 48 | B54: Campo | C54: Santiago Espinoza Yovani | D54: 8 | H54: 8 | I54: 8 | J54: 8 | K54: 9 | L54: 9 | M54: 6 | O54: 8 | P54: 8 | Q54: 8 | R54: 9 | S54: 9 | T54: 6 | V54: 8 | W54: 8 | X54: 8 | Y54: 9 | Z54: 9 | AA54: 6 | AC54: 8 | AD54: 8 | AE54: 8 | AF54: 9 | AG54: 9 | AH54: 6 | AI54: =SUM(D54:AH54) -> 200 | AJ54: =IF(AI54=208,"A. Perfecta","Faltó") -> Faltó | AK54: =SUM(D54:D54) -> 8 | AL54: =COUNTIF(D54:AH54,"F") -> 0 | AM54: =IF(AND(COUNTIF(D54:U54,"F")<14,COUNTIF(Q54:U54,"F")<=3),"SI","NO CORRESPONDE") -> SI | AN54: =2023+$AN$3 -> 2148 | AP54: =AN54+AO54 -> 2148 | AQ54: =AP54/27 -> 79.555556 | AR54: =AQ54/8 -> 9.9444444 | AS54: =AR54*AI54 -> 1988.8889
D55: =SUM(D7:D54) -> 384 | E55: =SUM(E7:E54) -> 402 | F55: =SUM(F7:F54) -> 329 | G55: =SUM(G7:G54) -> 0 | H55: =SUM(H7:H54) -> 378 | I55: =SUM(I7:I54) -> 370 | J55: =SUM(J7:J54) -> 358 | K55: =SUM(K7:K54) -> 388.5 | ... T55: =SUM(T7:T54) -> 284 | V55: =SUM(V7:V54) -> 338 | W55: =SUM(W7:W54) -> 363.5 | X55: =SUM(X7:X54) -> 359 | Y55: =SUM(Y7:Y54) -> 385 | Z55: =SUM(Z7:Z54) -> 393 | AA55: =SUM(AA7:AA54) -> 254 | AB55: =SUM(AB7:AB54) -> 0 | AC55: =SUM(AC7:AC54) -> 332.5 | ... AI55: =SUM(AI7:AI54) -> 9702.5 | AN55: =SUM(AN7:AN54) -> 103549 | AO55: =SUM(AO7:AO54) -> 3300 | AP55: =SUM(AP7:AP54) -> 106849 | AQ55: =SUM(AQ7:AQ54) -> 3957.3704 | AR55: =SUM(AR7:AR54) -> 494.6713 | AS55: =SUM(AS7:AS54) -> 100547.19 | AT55: =SUM(AT7:AT54) -> 0
A57: Nº | B57: Nº ORDEN | C57: NOMBRES | D57: J | E57: V | F57: S | G57: D | H57: L | I57: M | J57: M | K57: J | L57: V | M57: S | N57: D | O57: L | P57: M | Q57: M | R57: J | S57: V | T57: S | U57: D | V57: L | W57: M | X57: M | Y57: J | Z57: V | AA57: S | AB57: D | AC57: L | AD57: M | AE57: M | AF57: J | AG57: V | AH57: S | AI57: TOTAL
D58: 1 | E58: 2 | F58: 3 | G58: 4 | H58: 5 | I58: 6 | J58: 7 | K58: 8 | L58: 9 | M58: 10 | N58: 11 | O58: 12 | P58: 13 | Q58: 14 | R58: 15 | S58: 16 | T58: 17 | U58: 18 | V58: 19 | W58: 20 | X58: 21 | Y58: 22 | Z58: 23 | AA58: 24 | AB58: 25 | AC58: 26 | AD58: 27 | AE58: 28 | AF58: 29 | AG58: 30 | AH58: 31 | AI58: Monto S/. | AS58: =+AS55-3600 -> 96947.19
A59: 1 | B59: =VLOOKUP(C59,PROYECTADA!$Y$7:$AD$54,6,0) -> 12.954055 | C59: =C7 -> Apaza Tito Patricia | D59: =IF(D7="F",0,+$B59*D7) -> 103.63244 | E59: =IF(E7="F",0,+$B59*E7) -> 116.58649 | F59: =IF(F7="F",0,+$B59*F7) -> 90.678383 | H59: =IF(H7="F",0,+$B59*H7) -> 103.63244 | I59: =IF(I7="F",0,+$B59*I7) -> 103.63244 | J59: =IF(J7="F",0,+$B59*J7) -> 103.63244 | K59: =IF(K7="F",0,+$B59*K7) -> 116.58649 | L59: =IF(L7="F",0,+$B59*L7) -> 116.58649 | M59: =IF(M7="F",0,+$B59*M7) -> 77.724329 | O59: =IF(O7="F",0,+$B59*O7) -> 103.63244 | P59: =IF(P7="F",0,+$B59*P7) -> 103.63244 | Q59: =IF(Q7="F",0,+$B59*Q7) -> 103.63244 | R59: =IF(R7="F",0,+$B59*R7) -> 116.58649 | S59: =IF(S7="F",0,+$B59*S7) -> 116.58649 | T59: =IF(T7="F",0,+$B59*T7) -> 77.724329 | U59: =IF(U7="F",0,+$B59*U7) -> 0 | V59: =IF(V7="F",0,+$B59*V7) -> 103.63244 | ... AA59: =IF(AA7="F",0,+$B59*AA7) -> 77.724329 | AC59: =IF(AC7="F",0,+$B59*AC7) -> 103.63244 | AD59: =IF(AD7="F",0,+$B59*AD7) -> 103.63244 | AE59: =IF(AE7="F",0,+$B59*AE7) -> 103.63244 | AF59: =IF(AF7="F",0,+$B59*AF7) -> 116.58649 | AG59: =IF(AG7="F",0,+$B59*AG7) -> 116.58649 | AH59: =IF(AH7="F",0,+$B59*AH7) -> 77.724329 | AI59: =SUM(D59:AH59) -> 2798.0758 | AO59: 100143.86 | AQ59: 105662.96
A60: 2 | B60: =VLOOKUP(C60,PROYECTADA!$Y$7:$AD$54,6,0) -> 10.401248 | C60: =C8 -> Aquino Gómez Basilia Isabel | D60: =IF(D8="F",0,+$B60*D8) -> 83.209985 | E60: =IF(E8="F",0,+$B60*E8) -> 93.611233 | F60: =IF(F8="F",0,+$B60*F8) -> 72.808736 | H60: =IF(H8="F",0,+$B60*H8) -> 83.209985 | I60: =IF(I8="F",0,+$B60*I8) -> 83.209985 | J60: =IF(J8="F",0,+$B60*J8) -> 83.209985 | K60: =IF(K8="F",0,+$B60*K8) -> 93.611233 | L60: =IF(L8="F",0,+$B60*L8) -> 93.611233 | M60: =IF(M8="F",0,+$B60*M8) -> 62.407488 | O60: =IF(O8="F",0,+$B60*O8) -> 83.209985 | P60: =IF(P8="F",0,+$B60*P8) -> 83.209985 | Q60: =IF(Q8="F",0,+$B60*Q8) -> 83.209985 | R60: =IF(R8="F",0,+$B60*R8) -> 93.611233 | S60: =IF(S8="F",0,+$B60*S8) -> 93.611233 | T60: =IF(T8="F",0,+$B60*T8) -> 62.407488 | U60: =IF(U8="F",0,+$B60*U8) -> 0 | V60: =IF(V8="F",0,+$B60*V8) -> 83.209985 | ... AA60: =IF(AA8="F",0,+$B60*AA8) -> 62.407488 | AC60: =IF(AC8="F",0,+$B60*AC8) -> 83.209985 | AD60: =IF(AD8="F",0,+$B60*AD8) -> 83.209985 | AE60: =IF(AE8="F",0,+$B60*AE8) -> 83.209985 | AF60: =IF(AF8="F",0,+$B60*AF8) -> 93.611233 | AG60: =IF(AG8="F",0,+$B60*AG8) -> 93.611233 | AH60: =IF(AH8="F",0,+$B60*AH8) -> 62.407488 | AI60: =SUM(D60:AH60) -> 2246.6696
A61: 3 | B61: =VLOOKUP(C61,PROYECTADA!$Y$7:$AD$54,6,0) -> 10.401248 | C61: =C9 -> Calla G Guillermina | D61: =IF(D9="F",0,+$B61*D9) -> 83.209985 | E61: =IF(E9="F",0,+$B61*E9) -> 93.611233 | F61: =IF(F9="F",0,+$B61*F9) -> 72.808736 | H61: =IF(H9="F",0,+$B61*H9) -> 83.209985 | I61: =IF(I9="F",0,+$B61*I9) -> 83.209985 | J61: =IF(J9="F",0,+$B61*J9) -> 83.209985 | K61: =IF(K9="F",0,+$B61*K9) -> 93.611233 | L61: =IF(L9="F",0,+$B61*L9) -> 93.611233 | M61: =IF(M9="F",0,+$B61*M9) -> 62.407488 | O61: =IF(O9="F",0,+$B61*O9) -> 83.209985 | P61: =IF(P9="F",0,+$B61*P9) -> 83.209985 | Q61: =IF(Q9="F",0,+$B61*Q9) -> 83.209985 | R61: =IF(R9="F",0,+$B61*R9) -> 93.611233 | S61: =IF(S9="F",0,+$B61*S9) -> 93.611233 | T61: =IF(T9="F",0,+$B61*T9) -> 62.407488 | U61: =IF(U9="F",0,+$B61*U9) -> 0 | V61: =IF(V9="F",0,+$B61*V9) -> 83.209985 | ... AA61: =IF(AA9="F",0,+$B61*AA9) -> 62.407488 | AC61: =IF(AC9="F",0,+$B61*AC9) -> 83.209985 | AD61: =IF(AD9="F",0,+$B61*AD9) -> 83.209985 | AE61: =IF(AE9="F",0,+$B61*AE9) -> 83.209985 | AF61: =IF(AF9="F",0,+$B61*AF9) -> 93.611233 | AG61: =IF(AG9="F",0,+$B61*AG9) -> 93.611233 | AH61: =IF(AH9="F",0,+$B61*AH9) -> 62.407488 | AI61: =SUM(D61:AH61) -> 2246.6696 | AQ61: =+AQ59-AO59 -> 5519.0972
A62: 4 | B62: =VLOOKUP(C62,PROYECTADA!$Y$7:$AD$54,6,0) -> 10.309889 | C62: =C10 -> Challco Laime, Gilberta | D62: =IF(D10="F",0,+$B62*D10) -> 82.479112 | E62: =IF(E10="F",0,+$B62*E10) -> 92.789001 | F62: =IF(F10="F",0,+$B62*F10) -> 72.169223 | H62: =IF(H10="F",0,+$B62*H10) -> 82.479112 | I62: =IF(I10="F",0,+$B62*I10) -> 82.479112 | J62: =IF(J10="F",0,+$B62*J10) -> 82.479112 | K62: =IF(K10="F",0,+$B62*K10) -> 92.789001 | L62: =IF(L10="F",0,+$B62*L10) -> 92.789001 | M62: =IF(M10="F",0,+$B62*M10) -> 61.859334 | O62: =IF(O10="F",0,+$B62*O10) -> 82.479112 | P62: =IF(P10="F",0,+$B62*P10) -> 82.479112 | Q62: =IF(Q10="F",0,+$B62*Q10) -> 82.479112 | R62: =IF(R10="F",0,+$B62*R10) -> 92.789001 | S62: =IF(S10="F",0,+$B62*S10) -> 92.789001 | T62: =IF(T10="F",0,+$B62*T10) -> 61.859334 | U62: =IF(U10="F",0,+$B62*U10) -> 0 | V62: =IF(V10="F",0,+$B62*V10) -> 82.479112 | ... AA62: =IF(AA10="F",0,+$B62*AA10) -> 61.859334 | AC62: =IF(AC10="F",0,+$B62*AC10) -> 0 | AD62: =IF(AD10="F",0,+$B62*AD10) -> 82.479112 | AE62: =IF(AE10="F",0,+$B62*AE10) -> 82.479112 | AF62: =IF(AF10="F",0,+$B62*AF10) -> 92.789001 | AG62: =IF(AG10="F",0,+$B62*AG10) -> 92.789001 | AH62: =IF(AH10="F",0,+$B62*AH10) -> 61.859334 | AI62: =SUM(D62:AH62) -> 2144.4569
A63: 5 | B63: =VLOOKUP(C63,PROYECTADA!$Y$7:$AD$54,6,0) -> 10.411563 | C63: =C11 -> Choquehuayta Huallpa, Estefania | D63: =IF(D11="F",0,+$B63*D11) -> 83.292502 | E63: =IF(E11="F",0,+$B63*E11) -> 93.704065 | F63: =IF(F11="F",0,+$B63*F11) -> 72.88094 | H63: =IF(H11="F",0,+$B63*H11) -> 83.292502 | I63: =IF(I11="F",0,+$B63*I11) -> 83.292502 | J63: =IF(J11="F",0,+$B63*J11) -> 83.292502 | K63: =IF(K11="F",0,+$B63*K11) -> 93.704065 | L63: =IF(L11="F",0,+$B63*L11) -> 93.704065 | M63: =IF(M11="F",0,+$B63*M11) -> 62.469377 | O63: =IF(O11="F",0,+$B63*O11) -> 83.292502 | P63: =IF(P11="F",0,+$B63*P11) -> 83.292502 | Q63: =IF(Q11="F",0,+$B63*Q11) -> 83.292502 | R63: =IF(R11="F",0,+$B63*R11) -> 93.704065 | S63: =IF(S11="F",0,+$B63*S11) -> 93.704065 | T63: =IF(T11="F",0,+$B63*T11) -> 62.469377 | U63: =IF(U11="F",0,+$B63*U11) -> 0 | V63: =IF(V11="F",0,+$B63*V11) -> 83.292502 | ... AA63: =IF(AA11="F",0,+$B63*AA11) -> 0 | AC63: =IF(AC11="F",0,+$B63*AC11) -> 83.292502 | AD63: =IF(AD11="F",0,+$B63*AD11) -> 83.292502 | AE63: =IF(AE11="F",0,+$B63*AE11) -> 83.292502 | AF63: =IF(AF11="F",0,+$B63*AF11) -> 93.704065 | AG63: =IF(AG11="F",0,+$B63*AG11) -> 93.704065 | AH63: =IF(AH11="F",0,+$B63*AH11) -> 62.469377 | AI63: =SUM(D63:AH63) -> 2186.4282
A64: 6 | B64: =VLOOKUP(C64,PROYECTADA!$Y$7:$AD$54,6,0) -> 10.398005 | C64: =C12 -> Idme Huaraccallo, Gladis | D64: =IF(D12="F",0,+$B64*D12) -> 83.184036 | E64: =IF(E12="F",0,+$B64*E12) -> 93.582041 | F64: =IF(F12="F",0,+$B64*F12) -> 72.786032 | H64: =IF(H12="F",0,+$B64*H12) -> 83.184036 | I64: =IF(I12="F",0,+$B64*I12) -> 83.184036 | J64: =IF(J12="F",0,+$B64*J12) -> 83.184036 | K64: =IF(K12="F",0,+$B64*K12) -> 93.582041 | L64: =IF(L12="F",0,+$B64*L12) -> 93.582041 | M64: =IF(M12="F",0,+$B64*M12) -> 62.388027 | O64: =IF(O12="F",0,+$B64*O12) -> 83.184036 | P64: =IF(P12="F",0,+$B64*P12) -> 83.184036 | Q64: =IF(Q12="F",0,+$B64*Q12) -> 83.184036 | R64: =IF(R12="F",0,+$B64*R12) -> 93.582041 | S64: =IF(S12="F",0,+$B64*S12) -> 93.582041 | T64: =IF(T12="F",0,+$B64*T12) -> 62.388027 | U64: =IF(U12="F",0,+$B64*U12) -> 0 | V64: =IF(V12="F",0,+$B64*V12) -> 83.184036 | ... AA64: =IF(AA12="F",0,+$B64*AA12) -> 62.388027 | AC64: =IF(AC12="F",0,+$B64*AC12) -> 83.184036 | AD64: =IF(AD12="F",0,+$B64*AD12) -> 83.184036 | AE64: =IF(AE12="F",0,+$B64*AE12) -> 83.184036 | AF64: =IF(AF12="F",0,+$B64*AF12) -> 93.582041 | AG64: =IF(AG12="F",0,+$B64*AG12) -> 93.582041 | AH64: =IF(AH12="F",0,+$B64*AH12) -> 62.388027 | AI64: =SUM(D64:AH64) -> 2245.969
A65: 7 | B65: =VLOOKUP(C65,PROYECTADA!$Y$7:$AD$54,6,0) -> 11.088124 | C65: =C13 -> Jacha Gomez, Flavia | D65: =IF(D13="F",0,+$B65*D13) -> 88.704994 | E65: =IF(E13="F",0,+$B65*E13) -> 99.793119 | F65: =IF(F13="F",0,+$B65*F13) -> 77.61687 | H65: =IF(H13="F",0,+$B65*H13) -> 88.704994 | I65: =IF(I13="F",0,+$B65*I13) -> 88.704994 | J65: =IF(J13="F",0,+$B65*J13) -> 88.704994 | K65: =IF(K13="F",0,+$B65*K13) -> 99.793119 | L65: =IF(L13="F",0,+$B65*L13) -> 99.793119 | M65: =IF(M13="F",0,+$B65*M13) -> 66.528746 | O65: =IF(O13="F",0,+$B65*O13) -> 88.704994 | P65: =IF(P13="F",0,+$B65*P13) -> 88.704994 | Q65: =IF(Q13="F",0,+$B65*Q13) -> 88.704994 | R65: =IF(R13="F",0,+$B65*R13) -> 99.793119 | S65: =IF(S13="F",0,+$B65*S13) -> 99.793119 | T65: =IF(T13="F",0,+$B65*T13) -> 66.528746 | U65: =IF(U13="F",0,+$B65*U13) -> 0 | V65: =IF(V13="F",0,+$B65*V13) -> 88.704994 | ... AA65: =IF(AA13="F",0,+$B65*AA13) -> 0 | AC65: =IF(AC13="F",0,+$B65*AC13) -> 0 | AD65: =IF(AD13="F",0,+$B65*AD13) -> 0 | AE65: =IF(AE13="F",0,+$B65*AE13) -> 88.704994 | AF65: =IF(AF13="F",0,+$B65*AF13) -> 99.793119 | AG65: =IF(AG13="F",0,+$B65*AG13) -> 99.793119 | AH65: =IF(AH13="F",0,+$B65*AH13) -> 66.528746 | AI65: =SUM(D65:AH65) -> 2040.2149
A66: 8 | B66: =VLOOKUP(C66,PROYECTADA!$Y$7:$AD$54,6,0) -> 10.511763 | C66: =C14 -> Lerma Yanarico Elena | D66: =IF(D14="F",0,+$B66*D14) -> 84.094105 | E66: =IF(E14="F",0,+$B66*E14) -> 94.605868 | F66: =IF(F14="F",0,+$B66*F14) -> 73.582342 | H66: =IF(H14="F",0,+$B66*H14) -> 84.094105 | I66: =IF(I14="F",0,+$B66*I14) -> 84.094105 | J66: =IF(J14="F",0,+$B66*J14) -> 84.094105 | K66: =IF(K14="F",0,+$B66*K14) -> 94.605868 | L66: =IF(L14="F",0,+$B66*L14) -> 94.605868 | M66: =IF(M14="F",0,+$B66*M14) -> 63.070579 | O66: =IF(O14="F",0,+$B66*O14) -> 84.094105 | P66: =IF(P14="F",0,+$B66*P14) -> 84.094105 | Q66: =IF(Q14="F",0,+$B66*Q14) -> 84.094105 | R66: =IF(R14="F",0,+$B66*R14) -> 94.605868 | S66: =IF(S14="F",0,+$B66*S14) -> 94.605868 | T66: =IF(T14="F",0,+$B66*T14) -> 63.070579 | U66: =IF(U14="F",0,+$B66*U14) -> 0 | V66: =IF(V14="F",0,+$B66*V14) -> 84.094105 | ... AA66: =IF(AA14="F",0,+$B66*AA14) -> 63.070579 | AC66: =IF(AC14="F",0,+$B66*AC14) -> 84.094105 | AD66: =IF(AD14="F",0,+$B66*AD14) -> 84.094105 | AE66: =IF(AE14="F",0,+$B66*AE14) -> 84.094105 | AF66: =IF(AF14="F",0,+$B66*AF14) -> 94.605868 | AG66: =IF(AG14="F",0,+$B66*AG14) -> 94.605868 | AH66: =IF(AH14="F",0,+$B66*AH14) -> 63.070579 | AI66: =SUM(D66:AH66) -> 2270.5408
A67: 9 | B67: =VLOOKUP(C67,PROYECTADA!$Y$7:$AD$54,6,0) -> 10.411563 | C67: =C15 -> Machaca Calcina, Benedicta | D67: =IF(D15="F",0,+$B67*D15) -> 83.292502 | E67: =IF(E15="F",0,+$B67*E15) -> 0 | F67: =IF(F15="F",0,+$B67*F15) -> 72.88094 | H67: =IF(H15="F",0,+$B67*H15) -> 83.292502 | I67: =IF(I15="F",0,+$B67*I15) -> 83.292502 | J67: =IF(J15="F",0,+$B67*J15) -> 0 | K67: =IF(K15="F",0,+$B67*K15) -> 93.704065 | L67: =IF(L15="F",0,+$B67*L15) -> 93.704065 | M67: =IF(M15="F",0,+$B67*M15) -> 62.469377 | O67: =IF(O15="F",0,+$B67*O15) -> 83.292502 | P67: =IF(P15="F",0,+$B67*P15) -> 83.292502 | Q67: =IF(Q15="F",0,+$B67*Q15) -> 83.292502 | R67: =IF(R15="F",0,+$B67*R15) -> 93.704065 | S67: =IF(S15="F",0,+$B67*S15) -> 93.704065 | T67: =IF(T15="F",0,+$B67*T15) -> 62.469377 | U67: =IF(U15="F",0,+$B67*U15) -> 0 | V67: =IF(V15="F",0,+$B67*V15) -> 0 | ... AA67: =IF(AA15="F",0,+$B67*AA15) -> 62.469377 | AC67: =IF(AC15="F",0,+$B67*AC15) -> 83.292502 | AD67: =IF(AD15="F",0,+$B67*AD15) -> 83.292502 | AE67: =IF(AE15="F",0,+$B67*AE15) -> 83.292502 | AF67: =IF(AF15="F",0,+$B67*AF15) -> 93.704065 | AG67: =IF(AG15="F",0,+$B67*AG15) -> 0 | AH67: =IF(AH15="F",0,+$B67*AH15) -> 62.469377 | AI67: =SUM(D67:AH67) -> 1894.9044
A68: 10 | B68: =VLOOKUP(C68,PROYECTADA!$Y$7:$AD$54,6,0) -> 10.503463 | C68: =C16 -> Mamani Hancco, Elsa Teresa | D68: =IF(D16="F",0,+$B68*D16) -> 84.0277 | E68: =IF(E16="F",0,+$B68*E16) -> 94.531163 | F68: =IF(F16="F",0,+$B68*F16) -> 73.524238 | H68: =IF(H16="F",0,+$B68*H16) -> 84.0277 | I68: =IF(I16="F",0,+$B68*I16) -> 84.0277 | J68: =IF(J16="F",0,+$B68*J16) -> 84.0277 | K68: =IF(K16="F",0,+$B68*K16) -> 94.531163 | L68: =IF(L16="F",0,+$B68*L16) -> 94.531163 | M68: =IF(M16="F",0,+$B68*M16) -> 63.020775 | O68: =IF(O16="F",0,+$B68*O16) -> 84.0277 | P68: =IF(P16="F",0,+$B68*P16) -> 84.0277 | Q68: =IF(Q16="F",0,+$B68*Q16) -> 84.0277 | R68: =IF(R16="F",0,+$B68*R16) -> 94.531163 | S68: =IF(S16="F",0,+$B68*S16) -> 94.531163 | T68: =IF(T16="F",0,+$B68*T16) -> 63.020775 | U68: =IF(U16="F",0,+$B68*U16) -> 0 | V68: =IF(V16="F",0,+$B68*V16) -> 84.0277 | ... AA68: =IF(AA16="F",0,+$B68*AA16) -> 63.020775 | AC68: =IF(AC16="F",0,+$B68*AC16) -> 84.0277 | AD68: =IF(AD16="F",0,+$B68*AD16) -> 84.0277 | AE68: =IF(AE16="F",0,+$B68*AE16) -> 84.0277 | AF68: =IF(AF16="F",0,+$B68*AF16) -> 94.531163 | AG68: =IF(AG16="F",0,+$B68*AG16) -> 94.531163 | AH68: =IF(AH16="F",0,+$B68*AH16) -> 63.020775 | AI68: =SUM(D68:AH68) -> 2268.7479
A69: 11 | B69: =VLOOKUP(C69,PROYECTADA!$Y$7:$AD$54,6,0) -> 10.309889 | C69: =C17 -> Mamani Itusaca de Perca Guzmila | D69: =IF(D17="F",0,+$B69*D17) -> 82.479112 | E69: =IF(E17="F",0,+$B69*E17) -> 92.789001 | F69: =IF(F17="F",0,+$B69*F17) -> 72.169223 | H69: =IF(H17="F",0,+$B69*H17) -> 82.479112 | I69: =IF(I17="F",0,+$B69*I17) -> 82.479112 | J69: =IF(J17="F",0,+$B69*J17) -> 82.479112 | K69: =IF(K17="F",0,+$B69*K17) -> 92.789001 | L69: =IF(L17="F",0,+$B69*L17) -> 92.789001 | M69: =IF(M17="F",0,+$B69*M17) -> 61.859334 | O69: =IF(O17="F",0,+$B69*O17) -> 82.479112 | P69: =IF(P17="F",0,+$B69*P17) -> 82.479112 | Q69: =IF(Q17="F",0,+$B69*Q17) -> 82.479112 | R69: =IF(R17="F",0,+$B69*R17) -> 92.789001 | S69: =IF(S17="F",0,+$B69*S17) -> 92.789001 | T69: =IF(T17="F",0,+$B69*T17) -> 61.859334 | U69: =IF(U17="F",0,+$B69*U17) -> 0 | V69: =IF(V17="F",0,+$B69*V17) -> 0 | ... AA69: =IF(AA17="F",0,+$B69*AA17) -> 61.859334 | AC69: =IF(AC17="F",0,+$B69*AC17) -> 82.479112 | AD69: =IF(AD17="F",0,+$B69*AD17) -> 82.479112 | AE69: =IF(AE17="F",0,+$B69*AE17) -> 82.479112 | AF69: =IF(AF17="F",0,+$B69*AF17) -> 92.789001 | AG69: =IF(AG17="F",0,+$B69*AG17) -> 92.789001 | AH69: =IF(AH17="F",0,+$B69*AH17) -> 61.859334 | AI69: =SUM(D69:AH69) -> 2144.4569
A70: 12 | B70: =VLOOKUP(C70,PROYECTADA!$Y$7:$AD$54,6,0) -> 10.309889 | C70: =C18 -> Mayta Coaquira Janet Venancia | D70: =IF(D18="F",0,+$B70*D18) -> 82.479112 | E70: =IF(E18="F",0,+$B70*E18) -> 92.789001 | F70: =IF(F18="F",0,+$B70*F18) -> 72.169223 | H70: =IF(H18="F",0,+$B70*H18) -> 82.479112 | I70: =IF(I18="F",0,+$B70*I18) -> 82.479112 | J70: =IF(J18="F",0,+$B70*J18) -> 82.479112 | K70: =IF(K18="F",0,+$B70*K18) -> 92.789001 | L70: =IF(L18="F",0,+$B70*L18) -> 92.789001 | M70: =IF(M18="F",0,+$B70*M18) -> 61.859334 | O70: =IF(O18="F",0,+$B70*O18) -> 82.479112 | P70: =IF(P18="F",0,+$B70*P18) -> 82.479112 | Q70: =IF(Q18="F",0,+$B70*Q18) -> 82.479112 | R70: =IF(R18="F",0,+$B70*R18) -> 92.789001 | S70: =IF(S18="F",0,+$B70*S18) -> 92.789001 | T70: =IF(T18="F",0,+$B70*T18) -> 61.859334 | U70: =IF(U18="F",0,+$B70*U18) -> 0 | V70: =IF(V18="F",0,+$B70*V18) -> 0 | ... AA70: =IF(AA18="F",0,+$B70*AA18) -> 0 | AC70: =IF(AC18="F",0,+$B70*AC18) -> 0 | AD70: =IF(AD18="F",0,+$B70*AD18) -> 0 | AE70: =IF(AE18="F",0,+$B70*AE18) -> 0 | AF70: =IF(AF18="F",0,+$B70*AF18) -> 0 | AG70: =IF(AG18="F",0,+$B70*AG18) -> 0 | AH70: =IF(AH18="F",0,+$B70*AH18) -> 0 | AI70: =SUM(D70:AH70) -> 1237.1867
A71: 13 | B71: =VLOOKUP(C71,PROYECTADA!$Y$7:$AD$54,6,0) -> 10.309889 | C71: =C19 -> Parari Laura Teresa Lucy | D71: =IF(D19="F",0,+$B71*D19) -> 82.479112 | E71: =IF(E19="F",0,+$B71*E19) -> 92.789001 | F71: =IF(F19="F",0,+$B71*F19) -> 72.169223 | H71: =IF(H19="F",0,+$B71*H19) -> 82.479112 | I71: =IF(I19="F",0,+$B71*I19) -> 82.479112 | J71: =IF(J19="F",0,+$B71*J19) -> 82.479112 | K71: =IF(K19="F",0,+$B71*K19) -> 92.789001 | L71: =IF(L19="F",0,+$B71*L19) -> 92.789001 | M71: =IF(M19="F",0,+$B71*M19) -> 61.859334 | O71: =IF(O19="F",0,+$B71*O19) -> 82.479112 | P71: =IF(P19="F",0,+$B71*P19) -> 82.479112 | Q71: =IF(Q19="F",0,+$B71*Q19) -> 82.479112 | R71: =IF(R19="F",0,+$B71*R19) -> 92.789001 | S71: =IF(S19="F",0,+$B71*S19) -> 92.789001 | T71: =IF(T19="F",0,+$B71*T19) -> 61.859334 | U71: =IF(U19="F",0,+$B71*U19) -> 0 | V71: =IF(V19="F",0,+$B71*V19) -> 82.479112 | ... AA71: =IF(AA19="F",0,+$B71*AA19) -> 61.859334 | AC71: =IF(AC19="F",0,+$B71*AC19) -> 82.479112 | AD71: =IF(AD19="F",0,+$B71*AD19) -> 82.479112 | AE71: =IF(AE19="F",0,+$B71*AE19) -> 82.479112 | AF71: =IF(AF19="F",0,+$B71*AF19) -> 92.789001 | AG71: =IF(AG19="F",0,+$B71*AG19) -> 92.789001 | AH71: =IF(AH19="F",0,+$B71*AH19) -> 61.859334 | AI71: =SUM(D71:AH71) -> 2226.936
A72: 14 | B72: =VLOOKUP(C72,PROYECTADA!$Y$7:$AD$54,6,0) -> 10.309889 | C72: =C20 -> Pelinco Machaca, Monica | D72: =IF(D20="F",0,+$B72*D20) -> 82.479112 | E72: =IF(E20="F",0,+$B72*E20) -> 92.789001 | F72: =IF(F20="F",0,+$B72*F20) -> 72.169223 | H72: =IF(H20="F",0,+$B72*H20) -> 82.479112 | I72: =IF(I20="F",0,+$B72*I20) -> 82.479112 | J72: =IF(J20="F",0,+$B72*J20) -> 82.479112 | K72: =IF(K20="F",0,+$B72*K20) -> 92.789001 | L72: =IF(L20="F",0,+$B72*L20) -> 92.789001 | M72: =IF(M20="F",0,+$B72*M20) -> 61.859334 | O72: =IF(O20="F",0,+$B72*O20) -> 82.479112 | P72: =IF(P20="F",0,+$B72*P20) -> 82.479112 | Q72: =IF(Q20="F",0,+$B72*Q20) -> 82.479112 | R72: =IF(R20="F",0,+$B72*R20) -> 92.789001 | S72: =IF(S20="F",0,+$B72*S20) -> 92.789001 | T72: =IF(T20="F",0,+$B72*T20) -> 61.859334 | U72: =IF(U20="F",0,+$B72*U20) -> 0 | V72: =IF(V20="F",0,+$B72*V20) -> 82.479112 | ... AA72: =IF(AA20="F",0,+$B72*AA20) -> 61.859334 | AC72: =IF(AC20="F",0,+$B72*AC20) -> 82.479112 | AD72: =IF(AD20="F",0,+$B72*AD20) -> 82.479112 | AE72: =IF(AE20="F",0,+$B72*AE20) -> 82.479112 | AF72: =IF(AF20="F",0,+$B72*AF20) -> 92.789001 | AG72: =IF(AG20="F",0,+$B72*AG20) -> 92.789001 | AH72: =IF(AH20="F",0,+$B72*AH20) -> 61.859334 | AI72: =SUM(D72:AH72) -> 2226.936
A73: 15 | B73: =VLOOKUP(C73,PROYECTADA!$Y$7:$AD$54,6,0) -> 10.401248 | C73: =C21 -> Quispe Pacco Obita | D73: =IF(D21="F",0,+$B73*D21) -> 83.209985 | E73: =IF(E21="F",0,+$B73*E21) -> 93.611233 | F73: =IF(F21="F",0,+$B73*F21) -> 72.808736 | H73: =IF(H21="F",0,+$B73*H21) -> 83.209985 | I73: =IF(I21="F",0,+$B73*I21) -> 83.209985 | J73: =IF(J21="F",0,+$B73*J21) -> 83.209985 | K73: =IF(K21="F",0,+$B73*K21) -> 93.611233 | L73: =IF(L21="F",0,+$B73*L21) -> 93.611233 | M73: =IF(M21="F",0,+$B73*M21) -> 62.407488 | O73: =IF(O21="F",0,+$B73*O21) -> 83.209985 | P73: =IF(P21="F",0,+$B73*P21) -> 83.209985 | Q73: =IF(Q21="F",0,+$B73*Q21) -> 83.209985 | R73: =IF(R21="F",0,+$B73*R21) -> 93.611233 | S73: =IF(S21="F",0,+$B73*S21) -> 93.611233 | T73: =IF(T21="F",0,+$B73*T21) -> 62.407488 | U73: =IF(U21="F",0,+$B73*U21) -> 0 | V73: =IF(V21="F",0,+$B73*V21) -> 83.209985 | ... AA73: =IF(AA21="F",0,+$B73*AA21) -> 62.407488 | AC73: =IF(AC21="F",0,+$B73*AC21) -> 83.209985 | AD73: =IF(AD21="F",0,+$B73*AD21) -> 83.209985 | AE73: =IF(AE21="F",0,+$B73*AE21) -> 83.209985 | AF73: =IF(AF21="F",0,+$B73*AF21) -> 93.611233 | AG73: =IF(AG21="F",0,+$B73*AG21) -> 93.611233 | AH73: =IF(AH21="F",0,+$B73*AH21) -> 62.407488 | AI73: =SUM(D73:AH73) -> 2246.6696
... A106: 48 | B106: =VLOOKUP(C106,PROYECTADA!$Y$7:$AD$54,6,0) -> 11.189946 | C106: =C54 -> Santiago Espinoza Yovani | D106: =IF(D54="F",0,+$B106*D54) -> 89.519568 | E106: =IF(E54="F",0,+$B106*E54) -> 0 | F106: =IF(F54="F",0,+$B106*F54) -> 0 | H106: =IF(H54="F",0,+$B106*H54) -> 89.519568 | I106: =IF(I54="F",0,+$B106*I54) -> 89.519568 | J106: =IF(J54="F",0,+$B106*J54) -> 89.519568 | K106: =IF(K54="F",0,+$B106*K54) -> 100.70951 | L106: =IF(L54="F",0,+$B106*L54) -> 100.70951 | M106: =IF(M54="F",0,+$B106*M54) -> 67.139676 | O106: =IF(O54="F",0,+$B106*O54) -> 89.519568 | P106: =IF(P54="F",0,+$B106*P54) -> 89.519568 | Q106: =IF(Q54="F",0,+$B106*Q54) -> 89.519568 | R106: =IF(R54="F",0,+$B106*R54) -> 100.70951 | S106: =IF(S54="F",0,+$B106*S54) -> 100.70951 | T106: =IF(T54="F",0,+$B106*T54) -> 67.139676 | U106: =IF(U54="F",0,+$B106*U54) -> 0 | V106: =IF(V54="F",0,+$B106*V54) -> 89.519568 | ... AA106: =IF(AA54="F",0,+$B106*AA54) -> 67.139676 | AC106: =IF(AC54="F",0,+$B106*AC54) -> 89.519568 | AD106: =IF(AD54="F",0,+$B106*AD54) -> 89.519568 | AE106: =IF(AE54="F",0,+$B106*AE54) -> 89.519568 | AF106: =IF(AF54="F",0,+$B106*AF54) -> 100.70951 | AG106: =IF(AG54="F",0,+$B106*AG54) -> 100.70951 | AH106: =IF(AH54="F",0,+$B106*AH54) -> 67.139676 | AI106: =SUM(D106:AH106) -> 2237.9892
D107: =SUM(D59:D106) -> 4276.9214 | E107: =SUM(E59:E106) -> 4487.3747 | F107: =SUM(F59:F106) -> 3668.9648 | G107: =SUM(G59:G106) -> 0 | H107: =SUM(H59:H106) -> 4214.4404 | I107: =SUM(I59:I106) -> 4131.291 | J107: =SUM(J59:J106) -> 3995.257 | K107: =SUM(K59:K106) -> 4334.657 | ... AI107: =SUM(AI59:AI106) -> 108268.55
D108: ok | E108: ok | F108: ok | H108: ok | I108: ok | J108: ok | K108: ok | L108: OK | M108: ok | O108: ok | P108: ok | Q108: ok | R108: ok | S108: ok | T108: ok | V108: ok | W108: ok | X108: ok | Y108: ok | Z108: ok | AA108: ok | AC108: OK | AD108: OK | AE108: OK | AF108: OK | AG108: ok | AH108: OK
C110: diferencia
W114: =250-140 -> 110

Sheet DESCUENTO AFP
A1: AFP | B1: COMISIÓN | C1: COMISIÓN | D1: PRIMA DE | E1: APORTE OBLIGATORIO AL FONDO DE PENSIONES | F1: REMUNERACIÓN MÁXIMA ASEGURABLE
B2: SOBRE FLUJO | C2: ANUAL SOBRE | D2: SEGUROS (%) 3/ | E2: (% Remuneración Bruta Mensual)
B3: (% Remuneración Bruta Mensual) | C3: SALDO | D3: (% Remuneración Bruta Mensual)
A4: HABITAT | B4: 0.0147 | C4: 0.0125 | D4: 0.0137 | E4: 0.1 | F4: 12209.11
A5: INTEGRA | B5: 0.0155 | C5: 0.0078 | D5: 0.0137 | E5: 0.1 | F5: 12209.11
A6: PRIMA | B6: 0.016 | C6: 0.0125 | D6: 0.0137 | E6: 0.1 | F6: 12209.11
A7: PROFUTURO | B7: 0.0169 | C7: 0.0068 | D7: 0.0137 | E7: 0.1 | F7: 12209.11
